{"type": "baselines", "imagename": "D:\\Users\\kju10\\Documents\\LMU-STATISTICS & DATA SCIENCE MASTER\\SS2026\\Thesis\\OCC_HTR\\data\\raw\\original_manuscript\\reproduction14453_100\\8 - f. 003v - 004.jpg", "text_direction": "horizontal-lr", "script_detection": false, "lines": [{"id": "65578431-d823-4eb2-b04c-ac84f78986d3", "baseline": [[453, 246], [873, 247]], "boundary": [[851, 223], [840, 226], [829, 226], [818, 226], [807, 226], [796, 226], [784, 226], [773, 226], [762, 226], [751, 226], [740, 226], [729, 226], [718, 226], [707, 226], [696, 226], [685, 226], [674, 226], [662, 226], [651, 226], [640, 226], [629, 226], [618, 226], [607, 226], [596, 226], [585, 226], [574, 226], [563, 226], [552, 226], [541, 226], [529, 226], [518, 226], [507, 226], [496, 226], [485, 226], [474, 226], [463, 226], [453, 228], [453, 246], [452, 257], [872, 256], [873, 247], [872, 222], [852, 222], [851, 223]], "text": null, "base_dir": null, "type": "baselines", "imagename": null, "tags": {"type": "default"}, "split": null, "regions": ["17e45a62-26eb-4227-b064-32400bbf2dbb"]}, {"id": "71f7208b-0646-4445-b5d9-d42266ecfccd", "baseline": [[450, 273], [863, 271]], "boundary": [[450, 273], [450, 284], [566, 288], [567, 288], [595, 282], [645, 288], [646, 288], [703, 281], [750, 287], [751, 287], [752, 287], [753, 287], [761, 281], [844, 287], [845, 287], [847, 287], [863, 280], [863, 271], [861, 254], [449, 254], [450, 273]], "text": null, "base_dir": null, "type": "baselines", "imagename": null, "tags": {"type": "default"}, "split": null, "regions": ["17e45a62-26eb-4227-b064-32400bbf2dbb"]}, {"id": "a9ddc432-ea7a-4e04-bcd7-fd583f5565f1", "baseline": [[449, 298], [862, 300]], "boundary": [[449, 298], [447, 309], [861, 309], [862, 300], [861, 279], [449, 277], [449, 298]], "text": null, "base_dir": null, "type": "baselines", "imagename": null, "tags": {"type": "default"}, "split": null, "regions": ["17e45a62-26eb-4227-b064-32400bbf2dbb"]}, {"id": "2271cc85-25b0-4d6b-b184-7e756a2ed127", "baseline": [[451, 323], [861, 326]], "boundary": [[451, 323], [450, 332], [601, 340], [603, 340], [860, 335], [861, 326], [860, 310], [451, 307], [451, 323]], "text": null, "base_dir": null, "type": "baselines", "imagename": null, "tags": {"type": "default"}, "split": null, "regions": ["17e45a62-26eb-4227-b064-32400bbf2dbb"]}, {"id": "1b17d44a-8648-4ca5-a3f5-07061a5b42f4", "baseline": [[452, 352], [865, 354]], "boundary": [[452, 352], [451, 363], [864, 362], [865, 354], [863, 330], [452, 332], [452, 352]], "text": null, "base_dir": null, "type": "baselines", "imagename": null, "tags": {"type": "default"}, "split": null, "regions": ["17e45a62-26eb-4227-b064-32400bbf2dbb"]}, {"id": "fddd1355-4341-4713-ad1b-2840ff136c5c", "baseline": [[452, 375], [886, 380]], "boundary": [[552, 353], [544, 353], [533, 357], [452, 355], [452, 375], [451, 389], [884, 394], [886, 380], [885, 355], [790, 361], [779, 355], [778, 355], [777, 355], [669, 360], [575, 360], [554, 353], [552, 353]], "text": null, "base_dir": null, "type": "baselines", "imagename": null, "tags": {"type": "default"}, "split": null, "regions": ["17e45a62-26eb-4227-b064-32400bbf2dbb"]}, {"id": "552e8128-2fc5-44d9-96e8-4629aac8c959", "baseline": [[450, 402], [861, 406]], "boundary": [[450, 402], [449, 412], [805, 421], [807, 421], [860, 415], [861, 406], [861, 386], [450, 383], [450, 402]], "text": null, "base_dir": null, "type": "baselines", "imagename": null, "tags": {"type": "default"}, "split": null, "regions": ["17e45a62-26eb-4227-b064-32400bbf2dbb"]}, {"id": "66051fed-a0f0-4b42-98b8-5f7d187d83c8", "baseline": [[451, 434], [856, 431]], "boundary": [[451, 434], [451, 446], [855, 445], [856, 431], [853, 408], [450, 410], [451, 434]], "text": null, "base_dir": null, "type": "baselines", "imagename": null, "tags": {"type": "default"}, "split": null, "regions": ["17e45a62-26eb-4227-b064-32400bbf2dbb"]}, {"id": "5f4d7107-b3bc-47fa-bea6-5a92a1814994", "baseline": [[451, 462], [851, 462]], "boundary": [[451, 462], [451, 474], [851, 474], [851, 462], [851, 438], [451, 438], [451, 462]], "text": null, "base_dir": null, "type": "baselines", "imagename": null, "tags": {"type": "default"}, "split": null, "regions": ["17e45a62-26eb-4227-b064-32400bbf2dbb"]}, {"id": "619a1e41-d620-4e6b-bb85-48aa091e7b1d", "baseline": [[451, 489], [858, 487]], "boundary": [[451, 489], [451, 503], [856, 497], [858, 487], [855, 471], [450, 467], [451, 489]], "text": null, "base_dir": null, "type": "baselines", "imagename": null, "tags": {"type": "default"}, "split": null, "regions": ["17e45a62-26eb-4227-b064-32400bbf2dbb"]}, {"id": "db2fda2f-68ce-4ef8-8ba1-a5ddebf199bf", "baseline": [[451, 515], [849, 512]], "boundary": [[451, 515], [451, 529], [848, 525], [849, 512], [845, 490], [450, 496], [451, 515]], "text": null, "base_dir": null, "type": "baselines", "imagename": null, "tags": {"type": "default"}, "split": null, "regions": ["17e45a62-26eb-4227-b064-32400bbf2dbb"]}, {"id": "ac3cf0eb-cf0a-4a4d-92f8-c095e17aa280", "baseline": [[451, 541], [861, 537]], "boundary": [[451, 541], [451, 553], [860, 553], [861, 537], [858, 520], [450, 520], [451, 541]], "text": null, "base_dir": null, "type": "baselines", "imagename": null, "tags": {"type": "default"}, "split": null, "regions": ["17e45a62-26eb-4227-b064-32400bbf2dbb"]}, {"id": "45802f93-61b3-4e4c-834e-0bfb809ad15b", "baseline": [[451, 567], [861, 565]], "boundary": [[451, 567], [451, 578], [654, 582], [655, 582], [656, 582], [657, 582], [665, 576], [721, 576], [733, 581], [735, 581], [736, 581], [737, 581], [754, 576], [859, 581], [861, 565], [859, 548], [662, 543], [661, 543], [450, 549], [451, 567]], "text": null, "base_dir": null, "type": "baselines", "imagename": null, "tags": {"type": "default"}, "split": null, "regions": ["17e45a62-26eb-4227-b064-32400bbf2dbb"]}, {"id": "c26d4b3e-7b43-4e0d-8e5b-5452f80b3444", "baseline": [[450, 594], [862, 590]], "boundary": [[450, 594], [450, 608], [861, 604], [862, 590], [859, 574], [449, 576], [450, 594]], "text": null, "base_dir": null, "type": "baselines", "imagename": null, "tags": {"type": "default"}, "split": null, "regions": ["17e45a62-26eb-4227-b064-32400bbf2dbb"]}, {"id": "f6d6ce3d-0b79-4f08-9e9c-9455fb681e39", "baseline": [[451, 620], [866, 616]], "boundary": [[451, 620], [451, 631], [866, 631], [866, 616], [864, 599], [782, 599], [773, 592], [772, 592], [771, 592], [770, 592], [769, 592], [768, 592], [768, 594], [762, 598], [682, 594], [681, 594], [680, 594], [654, 600], [539, 596], [538, 596], [537, 596], [536, 596], [536, 597], [531, 602], [481, 602], [462, 596], [461, 596], [460, 596], [458, 596], [457, 596], [450, 600], [451, 620]], "text": null, "base_dir": null, "type": "baselines", "imagename": null, "tags": {"type": "default"}, "split": null, "regions": ["17e45a62-26eb-4227-b064-32400bbf2dbb"]}, {"id": "6d4be65a-1c7f-4cbd-bfae-b40c47124d3c", "baseline": [[452, 645], [852, 642]], "boundary": [[452, 645], [452, 658], [851, 652], [852, 642], [850, 625], [516, 621], [515, 621], [451, 627], [452, 645]], "text": null, "base_dir": null, "type": "baselines", "imagename": null, "tags": {"type": "default"}, "split": null, "regions": ["17e45a62-26eb-4227-b064-32400bbf2dbb"]}, {"id": "71073f52-65b7-4536-9d31-5d68778c886a", "baseline": [[452, 670], [854, 667]], "boundary": [[452, 670], [452, 686], [853, 678], [854, 667], [851, 650], [451, 652], [452, 670]], "text": null, "base_dir": null, "type": "baselines", "imagename": null, "tags": {"type": "default"}, "split": null, "regions": ["17e45a62-26eb-4227-b064-32400bbf2dbb"]}, {"id": "c798c70c-efa7-4d79-9978-43b5d975b938", "baseline": [[452, 696], [862, 692]], "boundary": [[452, 696], [452, 709], [861, 700], [862, 692], [859, 673], [451, 678], [452, 696]], "text": null, "base_dir": null, "type": "baselines", "imagename": null, "tags": {"type": "default"}, "split": null, "regions": ["17e45a62-26eb-4227-b064-32400bbf2dbb"]}, {"id": "9b8e16ae-e01f-4265-add6-f6cf27d054df", "baseline": [[452, 722], [864, 719]], "boundary": [[452, 722], [452, 732], [725, 737], [726, 737], [812, 731], [847, 735], [848, 735], [849, 735], [864, 729], [864, 719], [862, 703], [821, 696], [820, 696], [819, 696], [818, 696], [808, 703], [754, 703], [729, 696], [728, 696], [727, 696], [726, 696], [725, 696], [725, 697], [723, 697], [718, 703], [679, 697], [678, 697], [629, 703], [613, 698], [611, 698], [610, 698], [609, 698], [586, 706], [536, 706], [519, 698], [518, 698], [517, 698], [451, 702], [452, 722]], "text": null, "base_dir": null, "type": "baselines", "imagename": null, "tags": {"type": "default"}, "split": null, "regions": ["17e45a62-26eb-4227-b064-32400bbf2dbb"]}, {"id": "c3f28c72-173c-4d47-ab11-eb7d197af40d", "baseline": [[450, 749], [863, 745]], "boundary": [[450, 749], [450, 759], [862, 756], [863, 745], [859, 722], [844, 729], [823, 723], [822, 723], [821, 723], [820, 723], [819, 723], [809, 730], [720, 730], [644, 724], [643, 724], [604, 730], [449, 728], [450, 749]], "text": null, "base_dir": null, "type": "baselines", "imagename": null, "tags": {"type": "default"}, "split": null, "regions": ["17e45a62-26eb-4227-b064-32400bbf2dbb"]}, {"id": "450adc4a-fad7-4b8f-bcfc-8db27abcd93c", "baseline": [[452, 775], [859, 775]], "boundary": [[452, 775], [452, 786], [859, 786], [859, 775], [859, 758], [452, 756], [452, 775]], "text": null, "base_dir": null, "type": "baselines", "imagename": null, "tags": {"type": "default"}, "split": null, "regions": ["17e45a62-26eb-4227-b064-32400bbf2dbb"]}, {"id": "bc1dddf9-b27f-4bbd-90ee-af2e2843df94", "baseline": [[452, 804], [864, 802]], "boundary": [[452, 804], [452, 815], [863, 815], [864, 802], [861, 781], [451, 784], [452, 804]], "text": null, "base_dir": null, "type": "baselines", "imagename": null, "tags": {"type": "default"}, "split": null, "regions": ["17e45a62-26eb-4227-b064-32400bbf2dbb"]}, {"id": "5f56e2c7-871c-4fdc-b494-a0f8e502c053", "baseline": [[452, 832], [860, 827]], "boundary": [[452, 832], [452, 843], [859, 839], [860, 827], [858, 809], [451, 809], [452, 832]], "text": null, "base_dir": null, "type": "baselines", "imagename": null, "tags": {"type": "default"}, "split": null, "regions": ["17e45a62-26eb-4227-b064-32400bbf2dbb"]}, {"id": "aa79ed27-c862-4f64-9c1b-eddfad3699b5", "baseline": [[452, 857], [850, 854]], "boundary": [[452, 857], [452, 867], [849, 864], [850, 854], [847, 836], [451, 840], [452, 857]], "text": null, "base_dir": null, "type": "baselines", "imagename": null, "tags": {"type": "default"}, "split": null, "regions": ["17e45a62-26eb-4227-b064-32400bbf2dbb"]}, {"id": "04fdb611-f629-41b0-844e-82be39e4cadf", "baseline": [[452, 884], [870, 880]], "boundary": [[452, 884], [452, 894], [869, 891], [870, 880], [868, 863], [771, 857], [770, 857], [769, 857], [768, 857], [760, 863], [461, 861], [460, 861], [458, 861], [457, 861], [451, 864], [452, 884]], "text": null, "base_dir": null, "type": "baselines", "imagename": null, "tags": {"type": "default"}, "split": null, "regions": ["17e45a62-26eb-4227-b064-32400bbf2dbb"]}, {"id": "46466493-6fe2-4759-9409-9a52f47c7915", "baseline": [[451, 908], [859, 908]], "boundary": [[451, 908], [451, 918], [858, 923], [859, 908], [858, 886], [451, 888], [451, 908]], "text": null, "base_dir": null, "type": "baselines", "imagename": null, "tags": {"type": "default"}, "split": null, "regions": ["17e45a62-26eb-4227-b064-32400bbf2dbb"]}, {"id": "8e66b446-4410-4ca9-b1da-9f7963ab11ec", "baseline": [[450, 938], [863, 933]], "boundary": [[450, 938], [450, 946], [863, 940], [863, 933], [860, 911], [449, 915], [450, 938]], "text": null, "base_dir": null, "type": "baselines", "imagename": null, "tags": {"type": "default"}, "split": null, "regions": ["17e45a62-26eb-4227-b064-32400bbf2dbb"]}, {"id": "333e94b2-76ff-495c-b25f-62d124084e26", "baseline": [[453, 960], [849, 958]], "boundary": [[453, 960], [453, 973], [848, 969], [849, 958], [845, 943], [452, 944], [453, 960]], "text": null, "base_dir": null, "type": "baselines", "imagename": null, "tags": {"type": "default"}, "split": null, "regions": ["17e45a62-26eb-4227-b064-32400bbf2dbb"]}, {"id": "ad6103fa-df41-4499-ac1b-b1ce7a26f1d3", "baseline": [[450, 986], [862, 984]], "boundary": [[450, 986], [450, 996], [646, 1001], [647, 1001], [648, 1001], [659, 996], [798, 1000], [799, 1000], [800, 1000], [819, 995], [860, 1000], [862, 984], [860, 963], [493, 963], [492, 963], [449, 968], [450, 986]], "text": null, "base_dir": null, "type": "baselines", "imagename": null, "tags": {"type": "default"}, "split": null, "regions": ["17e45a62-26eb-4227-b064-32400bbf2dbb"]}, {"id": "3e955b2b-5bac-4522-8308-920b9b6ab284", "baseline": [[424, 1014], [854, 1010]], "boundary": [[819, 985], [818, 985], [817, 985], [815, 985], [798, 993], [743, 993], [729, 985], [728, 985], [727, 985], [726, 985], [706, 993], [423, 988], [424, 1014], [424, 1030], [615, 1024], [670, 1024], [688, 1030], [689, 1030], [690, 1030], [854, 1026], [854, 1010], [851, 991], [827, 991], [820, 986], [820, 985], [819, 985]], "text": null, "base_dir": null, "type": "baselines", "imagename": null, "tags": {"type": "default"}, "split": null, "regions": ["17e45a62-26eb-4227-b064-32400bbf2dbb"]}, {"id": "0211f25d-8c51-4bed-bfb5-9ad410cee642", "baseline": [[452, 1039], [729, 1037]], "boundary": [[452, 1039], [452, 1055], [604, 1049], [719, 1054], [720, 1054], [721, 1054], [722, 1054], [729, 1048], [729, 1037], [727, 1020], [614, 1015], [613, 1015], [611, 1015], [587, 1021], [451, 1021], [452, 1039]], "text": null, "base_dir": null, "type": "baselines", "imagename": null, "tags": {"type": "default"}, "split": null, "regions": ["17e45a62-26eb-4227-b064-32400bbf2dbb"]}, {"id": "aeca37f6-e3e2-4334-954a-4bf5571f506f", "baseline": [[552, 1066], [865, 1066]], "boundary": [[552, 1066], [552, 1078], [865, 1078], [865, 1066], [865, 1047], [552, 1041], [552, 1066]], "text": null, "base_dir": null, "type": "baselines", "imagename": null, "tags": {"type": "default"}, "split": null, "regions": ["17e45a62-26eb-4227-b064-32400bbf2dbb"]}, {"id": "286b8090-7140-45bb-b86a-51761851ba1d", "baseline": [[461, 1093], [859, 1092]], "boundary": [[461, 1093], [461, 1105], [856, 1106], [859, 1092], [856, 1073], [460, 1073], [461, 1093]], "text": null, "base_dir": null, "type": "baselines", "imagename": null, "tags": {"type": "default"}, "split": null, "regions": ["17e45a62-26eb-4227-b064-32400bbf2dbb"]}, {"id": "d6de8c1d-25dc-4bd9-b088-1686d18fd03c", "baseline": [[453, 1119], [862, 1116]], "boundary": [[453, 1119], [453, 1132], [862, 1128], [862, 1116], [860, 1098], [452, 1095], [453, 1119]], "text": null, "base_dir": null, "type": "baselines", "imagename": null, "tags": {"type": "default"}, "split": null, "regions": ["17e45a62-26eb-4227-b064-32400bbf2dbb"]}, {"id": "d3896e46-37f4-4261-9c17-56aae768d6c4", "baseline": [[456, 1144], [865, 1142]], "boundary": [[456, 1144], [456, 1154], [863, 1155], [865, 1142], [863, 1126], [497, 1121], [496, 1121], [455, 1127], [456, 1144]], "text": null, "base_dir": null, "type": "baselines", "imagename": null, "tags": {"type": "default"}, "split": null, "regions": ["17e45a62-26eb-4227-b064-32400bbf2dbb"]}, {"id": "8b7b960f-4783-41a1-92cd-c7639e04e1f6", "baseline": [[456, 1169], [868, 1171]], "boundary": [[456, 1169], [455, 1179], [688, 1188], [689, 1188], [690, 1188], [701, 1182], [710, 1188], [711, 1188], [712, 1188], [713, 1188], [783, 1182], [848, 1188], [849, 1188], [850, 1188], [866, 1181], [868, 1171], [866, 1152], [456, 1150], [456, 1169]], "text": null, "base_dir": null, "type": "baselines", "imagename": null, "tags": {"type": "default"}, "split": null, "regions": ["17e45a62-26eb-4227-b064-32400bbf2dbb"]}, {"id": "5083725e-ab47-403e-b773-40298dafcd70", "baseline": [[455, 1197], [861, 1199]], "boundary": [[455, 1197], [454, 1205], [473, 1212], [474, 1212], [475, 1212], [860, 1209], [861, 1199], [859, 1175], [690, 1180], [455, 1173], [455, 1197]], "text": null, "base_dir": null, "type": "baselines", "imagename": null, "tags": {"type": "default"}, "split": null, "regions": ["17e45a62-26eb-4227-b064-32400bbf2dbb"]}, {"id": "0870fbc4-b780-4dd6-a35b-efb756ce9fc1", "baseline": [[454, 1226], [868, 1226]], "boundary": [[454, 1226], [454, 1242], [868, 1242], [868, 1226], [868, 1209], [803, 1202], [802, 1202], [801, 1202], [788, 1208], [773, 1202], [772, 1202], [771, 1202], [770, 1202], [769, 1202], [760, 1209], [717, 1209], [709, 1202], [708, 1202], [707, 1202], [706, 1202], [705, 1202], [703, 1202], [696, 1208], [689, 1202], [688, 1202], [687, 1202], [686, 1202], [685, 1202], [684, 1202], [676, 1208], [633, 1202], [631, 1202], [630, 1202], [607, 1208], [579, 1202], [578, 1202], [454, 1205], [454, 1226]], "text": null, "base_dir": null, "type": "baselines", "imagename": null, "tags": {"type": "default"}, "split": null, "regions": ["17e45a62-26eb-4227-b064-32400bbf2dbb"]}, {"id": "477d5f8d-6d0a-4848-9ce9-a3b1170a4d3d", "baseline": [[450, 1327], [849, 1326]], "boundary": [[450, 1327], [450, 1339], [519, 1343], [521, 1343], [522, 1343], [535, 1336], [541, 1342], [541, 1343], [542, 1343], [543, 1343], [544, 1344], [568, 1344], [568, 1343], [569, 1343], [588, 1336], [645, 1336], [659, 1343], [660, 1343], [661, 1344], [700, 1344], [700, 1343], [701, 1343], [702, 1343], [711, 1336], [726, 1343], [727, 1343], [728, 1344], [829, 1344], [829, 1343], [830, 1343], [849, 1334], [849, 1326], [847, 1308], [472, 1301], [471, 1301], [470, 1301], [449, 1308], [450, 1327]], "text": null, "base_dir": null, "type": "baselines", "imagename": null, "tags": {"type": "default"}, "split": null, "regions": ["17e45a62-26eb-4227-b064-32400bbf2dbb"]}, {"id": "53175630-c2ed-4d63-8c4f-c394d0810807", "baseline": [[454, 1351], [875, 1353]], "boundary": [[656, 1327], [655, 1327], [654, 1327], [626, 1333], [588, 1327], [587, 1327], [586, 1327], [560, 1335], [454, 1335], [454, 1351], [453, 1362], [873, 1367], [875, 1353], [874, 1328], [794, 1335], [760, 1330], [759, 1330], [758, 1330], [757, 1330], [757, 1331], [750, 1337], [699, 1337], [687, 1330], [686, 1330], [685, 1330], [684, 1330], [682, 1330], [665, 1335], [657, 1328], [657, 1327], [656, 1327]], "text": null, "base_dir": null, "type": "baselines", "imagename": null, "tags": {"type": "default"}, "split": null, "regions": ["17e45a62-26eb-4227-b064-32400bbf2dbb"]}, {"id": "fb50c50c-64c2-41c6-874a-d2a1627828aa", "baseline": [[455, 1380], [868, 1380]], "boundary": [[455, 1380], [455, 1394], [868, 1390], [868, 1380], [868, 1362], [455, 1362], [455, 1380]], "text": null, "base_dir": null, "type": "baselines", "imagename": null, "tags": {"type": "default"}, "split": null, "regions": ["17e45a62-26eb-4227-b064-32400bbf2dbb"]}, {"id": "0449e06a-3199-4931-a4b4-fdc48c2fe9de", "baseline": [[455, 1407], [872, 1407]], "boundary": [[455, 1407], [455, 1420], [871, 1421], [872, 1407], [871, 1386], [455, 1388], [455, 1407]], "text": null, "base_dir": null, "type": "baselines", "imagename": null, "tags": {"type": "default"}, "split": null, "regions": ["17e45a62-26eb-4227-b064-32400bbf2dbb"]}, {"id": "c22e80eb-c3cf-488f-95b8-1966f45181c1", "baseline": [[456, 1431], [872, 1435]], "boundary": [[456, 1431], [455, 1444], [870, 1447], [872, 1435], [870, 1413], [456, 1413], [456, 1431]], "text": null, "base_dir": null, "type": "baselines", "imagename": null, "tags": {"type": "default"}, "split": null, "regions": ["17e45a62-26eb-4227-b064-32400bbf2dbb"]}, {"id": "bc205711-4cd4-4acb-90e9-5526fcff8999", "baseline": [[457, 1458], [884, 1459]], "boundary": [[457, 1458], [456, 1469], [883, 1468], [884, 1459], [884, 1437], [457, 1436], [457, 1458]], "text": null, "base_dir": null, "type": "baselines", "imagename": null, "tags": {"type": "default"}, "split": null, "regions": ["17e45a62-26eb-4227-b064-32400bbf2dbb"]}, {"id": "c5758869-4fae-4186-add7-701db9c98909", "baseline": [[457, 1486], [865, 1486]], "boundary": [[457, 1486], [457, 1496], [864, 1497], [865, 1486], [865, 1467], [457, 1464], [457, 1486]], "text": null, "base_dir": null, "type": "baselines", "imagename": null, "tags": {"type": "default"}, "split": null, "regions": ["17e45a62-26eb-4227-b064-32400bbf2dbb"]}, {"id": "8430816c-8cf8-4c7d-9f8a-095e668a3481", "baseline": [[457, 1515], [865, 1510]], "boundary": [[457, 1515], [457, 1523], [864, 1519], [865, 1510], [863, 1490], [565, 1490], [564, 1490], [563, 1490], [562, 1490], [555, 1496], [480, 1491], [478, 1491], [477, 1491], [456, 1497], [457, 1515]], "text": null, "base_dir": null, "type": "baselines", "imagename": null, "tags": {"type": "default"}, "split": null, "regions": ["17e45a62-26eb-4227-b064-32400bbf2dbb"]}, {"id": "724bc8ab-4b2e-449c-8996-df9a47bd7949", "baseline": [[457, 1540], [874, 1537]], "boundary": [[457, 1540], [457, 1563], [505, 1553], [519, 1562], [521, 1562], [522, 1562], [523, 1562], [610, 1561], [611, 1561], [628, 1554], [699, 1561], [700, 1561], [701, 1561], [737, 1551], [766, 1559], [767, 1559], [768, 1559], [769, 1559], [770, 1559], [781, 1551], [808, 1559], [809, 1559], [810, 1559], [811, 1559], [812, 1559], [823, 1551], [860, 1551], [870, 1558], [874, 1537], [871, 1518], [456, 1518], [457, 1540]], "text": null, "base_dir": null, "type": "baselines", "imagename": null, "tags": {"type": "default"}, "split": null, "regions": ["17e45a62-26eb-4227-b064-32400bbf2dbb"]}, {"id": "8764f0b4-960b-4d3d-af83-a49000c092d1", "baseline": [[432, 1573], [534, 1578]], "boundary": [[432, 1573], [431, 1584], [478, 1587], [491, 1598], [492, 1598], [493, 1598], [494, 1598], [533, 1597], [534, 1578], [534, 1562], [516, 1547], [516, 1546], [515, 1546], [514, 1546], [513, 1546], [512, 1546], [478, 1559], [468, 1559], [456, 1543], [455, 1543], [455, 1542], [454, 1542], [453, 1542], [452, 1542], [433, 1543], [432, 1573]], "text": null, "base_dir": null, "type": "baselines", "imagename": null, "tags": {"type": "default"}, "split": null, "regions": ["17e45a62-26eb-4227-b064-32400bbf2dbb"]}, {"id": "bc705749-c8ab-430a-b35c-9e84e5102a9d", "baseline": [[930, 248], [1344, 251]], "boundary": [[1340, 233], [1329, 227], [1324, 224], [1309, 220], [1307, 220], [1300, 219], [1269, 229], [1250, 219], [1249, 219], [1195, 218], [1194, 218], [1192, 218], [1162, 228], [1124, 218], [1123, 218], [1121, 218], [1120, 218], [1089, 228], [1059, 220], [1058, 220], [1057, 220], [949, 227], [931, 220], [930, 248], [929, 260], [1343, 260], [1344, 251], [1344, 236], [1340, 233]], "text": null, "base_dir": null, "type": "baselines", "imagename": null, "tags": {"type": "default"}, "split": null, "regions": ["17e45a62-26eb-4227-b064-32400bbf2dbb"]}, {"id": "9901ad13-783c-4444-a377-1a815c5a1127", "baseline": [[933, 272], [1349, 278]], "boundary": [[933, 272], [932, 291], [1018, 292], [1019, 292], [1021, 292], [1022, 292], [1031, 285], [1043, 292], [1044, 292], [1045, 292], [1046, 292], [1047, 292], [1059, 284], [1085, 284], [1347, 292], [1349, 278], [1348, 261], [933, 252], [933, 272]], "text": null, "base_dir": null, "type": "baselines", "imagename": null, "tags": {"type": "default"}, "split": null, "regions": ["17e45a62-26eb-4227-b064-32400bbf2dbb"]}, {"id": "ec13f938-49a2-4b09-8b5c-b57585666742", "baseline": [[1013, 300], [1339, 303]], "boundary": [[1013, 300], [1012, 312], [1338, 312], [1339, 303], [1338, 284], [1013, 281], [1013, 300]], "text": null, "base_dir": null, "type": "baselines", "imagename": null, "tags": {"type": "default"}, "split": null, "regions": ["17e45a62-26eb-4227-b064-32400bbf2dbb"]}, {"id": "86abf25d-7f37-4220-a05a-885936936175", "baseline": [[954, 326], [1328, 330]], "boundary": [[1032, 301], [1021, 301], [1017, 294], [1016, 294], [1015, 294], [954, 293], [954, 326], [953, 336], [1325, 341], [1328, 330], [1327, 311], [1282, 304], [1281, 304], [1280, 304], [1263, 310], [1103, 304], [1101, 304], [1068, 309], [1039, 301], [1032, 301]], "text": null, "base_dir": null, "type": "baselines", "imagename": null, "tags": {"type": "default"}, "split": null, "regions": ["17e45a62-26eb-4227-b064-32400bbf2dbb"]}, {"id": "4dc6b4e8-b5e7-44b8-a725-fef4af5d79a8", "baseline": [[941, 357], [1330, 359]], "boundary": [[941, 357], [940, 364], [981, 371], [982, 371], [1329, 365], [1330, 359], [1329, 336], [1070, 330], [1069, 330], [1044, 335], [1027, 329], [1026, 329], [941, 328], [941, 357]], "text": null, "base_dir": null, "type": "baselines", "imagename": null, "tags": {"type": "default"}, "split": null, "regions": ["17e45a62-26eb-4227-b064-32400bbf2dbb"]}, {"id": "0741f3d1-4bae-464d-a069-d7535accffc7", "baseline": [[934, 379], [1338, 385]], "boundary": [[934, 379], [933, 389], [1335, 394], [1338, 385], [1335, 363], [1271, 367], [1117, 360], [1116, 360], [934, 361], [934, 379]], "text": null, "base_dir": null, "type": "baselines", "imagename": null, "tags": {"type": "default"}, "split": null, "regions": ["17e45a62-26eb-4227-b064-32400bbf2dbb"]}, {"id": "5cfe05b2-e686-461a-b371-b1fd0e40cf5f", "baseline": [[936, 406], [1330, 410]], "boundary": [[1292, 385], [1291, 385], [1290, 385], [1290, 386], [1284, 392], [1207, 392], [1159, 384], [1158, 384], [1092, 390], [1064, 383], [1063, 383], [1062, 383], [1034, 389], [986, 383], [985, 383], [984, 383], [983, 383], [976, 389], [936, 382], [936, 406], [935, 418], [1329, 418], [1330, 410], [1329, 392], [1293, 385], [1292, 385]], "text": null, "base_dir": null, "type": "baselines", "imagename": null, "tags": {"type": "default"}, "split": null, "regions": ["17e45a62-26eb-4227-b064-32400bbf2dbb"]}, {"id": "3790a766-5721-4adc-97c0-6b7967b8dc3f", "baseline": [[936, 431], [1328, 436]], "boundary": [[936, 431], [935, 438], [1325, 445], [1328, 436], [1327, 417], [936, 412], [936, 431]], "text": null, "base_dir": null, "type": "baselines", "imagename": null, "tags": {"type": "default"}, "split": null, "regions": ["17e45a62-26eb-4227-b064-32400bbf2dbb"]}, {"id": "2e570503-5829-48bf-a799-36a67c5702a1", "baseline": [[935, 458], [1342, 462]], "boundary": [[1190, 435], [1189, 435], [1065, 440], [1056, 434], [1055, 434], [1054, 434], [1053, 434], [947, 440], [936, 434], [935, 458], [934, 469], [1340, 471], [1342, 462], [1341, 443], [1235, 436], [1233, 436], [1208, 442], [1191, 435], [1190, 435]], "text": null, "base_dir": null, "type": "baselines", "imagename": null, "tags": {"type": "default"}, "split": null, "regions": ["17e45a62-26eb-4227-b064-32400bbf2dbb"]}, {"id": "032819ee-5241-4b74-bdf2-8404e575ba6a", "baseline": [[936, 487], [1345, 487]], "boundary": [[1340, 471], [936, 471], [936, 487], [936, 498], [1345, 496], [1345, 487], [1345, 479], [1340, 471]], "text": null, "base_dir": null, "type": "baselines", "imagename": null, "tags": {"type": "default"}, "split": null, "regions": ["17e45a62-26eb-4227-b064-32400bbf2dbb"]}, {"id": "a6701245-7d50-4f62-8a40-d6fc2b4cc57f", "baseline": [[935, 510], [1343, 514]], "boundary": [[935, 510], [934, 524], [1342, 524], [1343, 514], [1342, 494], [935, 489], [935, 510]], "text": null, "base_dir": null, "type": "baselines", "imagename": null, "tags": {"type": "default"}, "split": null, "regions": ["17e45a62-26eb-4227-b064-32400bbf2dbb"]}, {"id": "771f1b9f-4c63-46dc-adb0-4e1f4016cd03", "baseline": [[936, 536], [1349, 539]], "boundary": [[1347, 522], [1340, 516], [936, 515], [936, 536], [935, 548], [1347, 551], [1349, 539], [1348, 522], [1347, 522]], "text": null, "base_dir": null, "type": "baselines", "imagename": null, "tags": {"type": "default"}, "split": null, "regions": ["17e45a62-26eb-4227-b064-32400bbf2dbb"]}, {"id": "e0e32de6-8ec4-4250-843d-65ab1150cec5", "baseline": [[935, 560], [1340, 565]], "boundary": [[935, 560], [934, 573], [1338, 577], [1340, 565], [1339, 547], [935, 543], [935, 560]], "text": null, "base_dir": null, "type": "baselines", "imagename": null, "tags": {"type": "default"}, "split": null, "regions": ["17e45a62-26eb-4227-b064-32400bbf2dbb"]}, {"id": "7560f96d-1c0e-4131-9ae8-ea14b483bff5", "baseline": [[937, 591], [1352, 591]], "boundary": [[1350, 569], [937, 571], [937, 591], [937, 600], [1351, 605], [1352, 591], [1351, 581], [1350, 569]], "text": null, "base_dir": null, "type": "baselines", "imagename": null, "tags": {"type": "default"}, "split": null, "regions": ["17e45a62-26eb-4227-b064-32400bbf2dbb"]}, {"id": "d97f39d7-a765-4e9c-b2e0-2f1f2e3b4148", "baseline": [[937, 616], [1332, 618]], "boundary": [[1015, 592], [1004, 592], [993, 592], [982, 592], [971, 592], [960, 592], [949, 592], [937, 592], [937, 616], [936, 625], [1330, 630], [1332, 618], [1331, 597], [1016, 592], [1015, 592]], "text": null, "base_dir": null, "type": "baselines", "imagename": null, "tags": {"type": "default"}, "split": null, "regions": ["17e45a62-26eb-4227-b064-32400bbf2dbb"]}, {"id": "b66bae29-9599-4745-92b1-0fa10746224c", "baseline": [[937, 643], [1334, 646]], "boundary": [[937, 643], [936, 652], [1333, 652], [1334, 646], [1332, 622], [937, 622], [937, 643]], "text": null, "base_dir": null, "type": "baselines", "imagename": null, "tags": {"type": "default"}, "split": null, "regions": ["17e45a62-26eb-4227-b064-32400bbf2dbb"]}, {"id": "0fa7cc7f-75c0-47c1-a909-7831d01846ec", "baseline": [[939, 671], [1332, 671]], "boundary": [[939, 671], [939, 683], [1332, 680], [1332, 671], [1332, 648], [939, 647], [939, 671]], "text": null, "base_dir": null, "type": "baselines", "imagename": null, "tags": {"type": "default"}, "split": null, "regions": ["17e45a62-26eb-4227-b064-32400bbf2dbb"]}, {"id": "e70a6a72-417e-4c29-bb3b-ce7acaa1ca1c", "baseline": [[939, 694], [1333, 697]], "boundary": [[939, 694], [937, 707], [1332, 706], [1333, 697], [1331, 673], [939, 676], [939, 694]], "text": null, "base_dir": null, "type": "baselines", "imagename": null, "tags": {"type": "default"}, "split": null, "regions": ["17e45a62-26eb-4227-b064-32400bbf2dbb"]}, {"id": "d0d02eb2-11c9-4f83-8f5d-c55b5c236ae0", "baseline": [[939, 719], [1341, 723]], "boundary": [[939, 719], [937, 728], [1339, 737], [1341, 723], [1339, 700], [939, 700], [939, 719]], "text": null, "base_dir": null, "type": "baselines", "imagename": null, "tags": {"type": "default"}, "split": null, "regions": ["17e45a62-26eb-4227-b064-32400bbf2dbb"]}, {"id": "baa535f2-a923-4d16-a7c0-2102770cd12b", "baseline": [[937, 744], [1341, 749]], "boundary": [[937, 744], [936, 756], [1339, 758], [1341, 749], [1340, 729], [937, 725], [937, 744]], "text": null, "base_dir": null, "type": "baselines", "imagename": null, "tags": {"type": "default"}, "split": null, "regions": ["17e45a62-26eb-4227-b064-32400bbf2dbb"]}, {"id": "0998ab01-48e9-4432-96de-a98f71150710", "baseline": [[936, 775], [1344, 775]], "boundary": [[1339, 751], [936, 751], [936, 775], [936, 785], [1343, 789], [1344, 775], [1343, 753], [1339, 751]], "text": null, "base_dir": null, "type": "baselines", "imagename": null, "tags": {"type": "default"}, "split": null, "regions": ["17e45a62-26eb-4227-b064-32400bbf2dbb"]}, {"id": "52d02f9a-3b61-446c-828d-317117904b38", "baseline": [[939, 801], [1348, 803]], "boundary": [[1341, 784], [939, 782], [939, 801], [937, 812], [1347, 812], [1348, 803], [1347, 798], [1341, 784]], "text": null, "base_dir": null, "type": "baselines", "imagename": null, "tags": {"type": "default"}, "split": null, "regions": ["17e45a62-26eb-4227-b064-32400bbf2dbb"]}, {"id": "da92705c-7b16-4145-9ddb-35cfa70da32c", "baseline": [[940, 829], [1330, 829]], "boundary": [[940, 829], [940, 839], [1330, 837], [1330, 829], [1330, 810], [940, 810], [940, 829]], "text": null, "base_dir": null, "type": "baselines", "imagename": null, "tags": {"type": "default"}, "split": null, "regions": ["17e45a62-26eb-4227-b064-32400bbf2dbb"]}, {"id": "be6c7aa6-9771-4c13-af0d-1ccf95b74819", "baseline": [[939, 853], [1345, 855]], "boundary": [[1117, 830], [1116, 830], [1115, 830], [1085, 835], [939, 834], [939, 853], [937, 862], [1343, 864], [1345, 855], [1345, 837], [1333, 831], [1332, 831], [1331, 831], [1268, 836], [1182, 831], [1181, 831], [1125, 835], [1118, 830], [1117, 830]], "text": null, "base_dir": null, "type": "baselines", "imagename": null, "tags": {"type": "default"}, "split": null, "regions": ["17e45a62-26eb-4227-b064-32400bbf2dbb"]}, {"id": "d840aacd-a174-48d9-b6c0-dcf7ffd49032", "baseline": [[939, 880], [1343, 882]], "boundary": [[937, 889], [949, 895], [950, 895], [951, 895], [1342, 893], [1343, 882], [1342, 864], [1140, 857], [1139, 857], [954, 862], [940, 856], [939, 880], [937, 889]], "text": null, "base_dir": null, "type": "baselines", "imagename": null, "tags": {"type": "default"}, "split": null, "regions": ["17e45a62-26eb-4227-b064-32400bbf2dbb"]}, {"id": "b98d65c6-b436-48ac-afe6-346040f700c5", "baseline": [[939, 908], [1347, 911]], "boundary": [[937, 922], [1141, 919], [1171, 925], [1172, 926], [1345, 926], [1347, 911], [1343, 884], [1328, 889], [1321, 884], [1320, 884], [1319, 884], [1318, 884], [1196, 889], [1116, 883], [1115, 883], [953, 888], [940, 882], [939, 908], [937, 922]], "text": null, "base_dir": null, "type": "baselines", "imagename": null, "tags": {"type": "default"}, "split": null, "regions": ["17e45a62-26eb-4227-b064-32400bbf2dbb"]}, {"id": "5b47ad3a-bdba-4a89-89cc-78bc0a73f67f", "baseline": [[939, 934], [1352, 939]], "boundary": [[939, 934], [937, 950], [1351, 950], [1352, 939], [1351, 915], [939, 915], [939, 934]], "text": null, "base_dir": null, "type": "baselines", "imagename": null, "tags": {"type": "default"}, "split": null, "regions": ["17e45a62-26eb-4227-b064-32400bbf2dbb"]}, {"id": "0538e0ce-c805-4de5-93b3-d3c27570b873", "baseline": [[940, 963], [1349, 966]], "boundary": [[940, 963], [939, 970], [1347, 978], [1349, 966], [1347, 943], [940, 943], [940, 963]], "text": null, "base_dir": null, "type": "baselines", "imagename": null, "tags": {"type": "default"}, "split": null, "regions": ["17e45a62-26eb-4227-b064-32400bbf2dbb"]}, {"id": "7b3067cb-27b3-4f7e-8a1f-87acd450a9e6", "baseline": [[937, 986], [1340, 989]], "boundary": [[1104, 965], [1093, 965], [1082, 965], [1070, 964], [956, 968], [939, 963], [937, 986], [936, 998], [1339, 998], [1340, 989], [1339, 972], [1109, 965], [1104, 965]], "text": null, "base_dir": null, "type": "baselines", "imagename": null, "tags": {"type": "default"}, "split": null, "regions": ["17e45a62-26eb-4227-b064-32400bbf2dbb"]}, {"id": "170976bc-2cbc-4362-b9c4-16822374eafd", "baseline": [[939, 1010], [1347, 1017]], "boundary": [[939, 1010], [937, 1024], [1344, 1029], [1347, 1017], [1345, 993], [1280, 997], [1273, 991], [1272, 991], [1271, 991], [939, 991], [939, 1010]], "text": null, "base_dir": null, "type": "baselines", "imagename": null, "tags": {"type": "default"}, "split": null, "regions": ["17e45a62-26eb-4227-b064-32400bbf2dbb"]}, {"id": "2632ea4d-9885-4666-8f07-e7b71855cf1f", "baseline": [[939, 1036], [1340, 1040]], "boundary": [[939, 1036], [937, 1048], [1338, 1052], [1340, 1040], [1339, 1019], [939, 1018], [939, 1036]], "text": null, "base_dir": null, "type": "baselines", "imagename": null, "tags": {"type": "default"}, "split": null, "regions": ["17e45a62-26eb-4227-b064-32400bbf2dbb"]}, {"id": "56d49912-5f91-4c9a-a7dd-da75f1b814e1", "baseline": [[937, 1062], [1352, 1067]], "boundary": [[1348, 1051], [1344, 1048], [937, 1042], [937, 1062], [936, 1078], [1350, 1082], [1352, 1067], [1351, 1049], [1348, 1048], [1348, 1051]], "text": null, "base_dir": null, "type": "baselines", "imagename": null, "tags": {"type": "default"}, "split": null, "regions": ["17e45a62-26eb-4227-b064-32400bbf2dbb"]}, {"id": "e07b4c92-2d55-4292-8d60-33f9591fa87c", "baseline": [[939, 1089], [1335, 1095]], "boundary": [[939, 1089], [937, 1102], [1286, 1110], [1287, 1110], [1334, 1105], [1335, 1095], [1334, 1075], [939, 1071], [939, 1089]], "text": null, "base_dir": null, "type": "baselines", "imagename": null, "tags": {"type": "default"}, "split": null, "regions": ["17e45a62-26eb-4227-b064-32400bbf2dbb"]}, {"id": "a6546e0a-7090-4561-b8bf-269b992103c7", "baseline": [[939, 1119], [1347, 1121]], "boundary": [[939, 1119], [937, 1133], [1345, 1133], [1347, 1121], [1344, 1099], [939, 1099], [939, 1119]], "text": null, "base_dir": null, "type": "baselines", "imagename": null, "tags": {"type": "default"}, "split": null, "regions": ["17e45a62-26eb-4227-b064-32400bbf2dbb"]}, {"id": "690fdf58-c6c6-4c67-80d9-a7add91adb32", "baseline": [[937, 1147], [1339, 1144]], "boundary": [[937, 1147], [937, 1159], [1337, 1161], [1339, 1144], [1337, 1126], [960, 1123], [958, 1123], [957, 1123], [936, 1129], [937, 1147]], "text": null, "base_dir": null, "type": "baselines", "imagename": null, "tags": {"type": "default"}, "split": null, "regions": ["17e45a62-26eb-4227-b064-32400bbf2dbb"]}, {"id": "0665fb9e-9479-42c1-bc5f-1b78ed665a83", "baseline": [[936, 1173], [1339, 1169]], "boundary": [[1335, 1151], [935, 1151], [936, 1173], [936, 1185], [1339, 1182], [1339, 1169], [1337, 1157], [1335, 1151]], "text": null, "base_dir": null, "type": "baselines", "imagename": null, "tags": {"type": "default"}, "split": null, "regions": ["17e45a62-26eb-4227-b064-32400bbf2dbb"]}, {"id": "510a97a7-f2cf-42f7-8ec8-508e9e34a336", "baseline": [[937, 1202], [1324, 1195]], "boundary": [[937, 1202], [939, 1220], [950, 1214], [1062, 1218], [1063, 1218], [1064, 1218], [1065, 1218], [1073, 1212], [1322, 1213], [1324, 1195], [1321, 1177], [936, 1180], [937, 1202]], "text": null, "base_dir": null, "type": "baselines", "imagename": null, "tags": {"type": "default"}, "split": null, "regions": ["17e45a62-26eb-4227-b064-32400bbf2dbb"]}, {"id": "db2dfbc5-2fc3-4f53-8d79-be2aad1a6957", "baseline": [[933, 1229], [1332, 1226]], "boundary": [[933, 1229], [933, 1240], [1331, 1238], [1332, 1226], [1329, 1206], [932, 1209], [933, 1229]], "text": null, "base_dir": null, "type": "baselines", "imagename": null, "tags": {"type": "default"}, "split": null, "regions": ["17e45a62-26eb-4227-b064-32400bbf2dbb"]}, {"id": "ee4d6209-7c40-432b-8195-08546ee256cb", "baseline": [[933, 1256], [1185, 1251]], "boundary": [[933, 1256], [933, 1267], [1185, 1260], [1185, 1251], [1181, 1232], [932, 1236], [933, 1256]], "text": null, "base_dir": null, "type": "baselines", "imagename": null, "tags": {"type": "default"}, "split": null, "regions": ["17e45a62-26eb-4227-b064-32400bbf2dbb"]}, {"id": "3b8d8e8a-6618-408b-935a-00ba880e04a1", "baseline": [[1021, 1277], [1339, 1273]], "boundary": [[1175, 1252], [1171, 1252], [1140, 1257], [1069, 1254], [1064, 1254], [1053, 1254], [1042, 1254], [1039, 1254], [1019, 1259], [1021, 1277], [1021, 1292], [1338, 1283], [1339, 1273], [1335, 1247], [1294, 1255], [1262, 1250], [1261, 1250], [1260, 1250], [1235, 1256], [1191, 1249], [1190, 1249], [1175, 1251], [1175, 1252]], "text": null, "base_dir": null, "type": "baselines", "imagename": null, "tags": {"type": "default"}, "split": null, "regions": ["17e45a62-26eb-4227-b064-32400bbf2dbb"]}, {"id": "45058a5c-3b36-44f3-9e79-9b70f84cc69d", "baseline": [[951, 1303], [1337, 1297]], "boundary": [[951, 1303], [951, 1311], [1335, 1307], [1337, 1297], [1333, 1281], [950, 1281], [951, 1303]], "text": null, "base_dir": null, "type": "baselines", "imagename": null, "tags": {"type": "default"}, "split": null, "regions": ["17e45a62-26eb-4227-b064-32400bbf2dbb"]}, {"id": "b3741d95-53cd-4a98-b1ca-779517572d42", "baseline": [[936, 1327], [1337, 1324]], "boundary": [[1123, 1301], [1121, 1301], [1066, 1308], [1049, 1302], [1048, 1302], [1047, 1302], [1046, 1302], [1045, 1302], [1035, 1308], [935, 1303], [936, 1327], [936, 1338], [1335, 1335], [1337, 1324], [1335, 1307], [1318, 1300], [1317, 1300], [1315, 1300], [1314, 1300], [1313, 1300], [1303, 1306], [1273, 1301], [1272, 1301], [1144, 1307], [1124, 1301], [1123, 1301]], "text": null, "base_dir": null, "type": "baselines", "imagename": null, "tags": {"type": "default"}, "split": null, "regions": ["17e45a62-26eb-4227-b064-32400bbf2dbb"]}, {"id": "2c376cf2-3a7c-46f3-8d7e-a1fe245c3de0", "baseline": [[932, 1353], [1333, 1349]], "boundary": [[932, 1353], [932, 1365], [1333, 1358], [1333, 1349], [1331, 1333], [1199, 1328], [1198, 1328], [1197, 1328], [1196, 1328], [1196, 1330], [1189, 1335], [1143, 1330], [1141, 1330], [1140, 1330], [1118, 1335], [1107, 1330], [1106, 1330], [1105, 1330], [1104, 1330], [1087, 1336], [961, 1336], [931, 1331], [932, 1353]], "text": null, "base_dir": null, "type": "baselines", "imagename": null, "tags": {"type": "default"}, "split": null, "regions": ["17e45a62-26eb-4227-b064-32400bbf2dbb"]}, {"id": "0cc3e7df-2b9b-49b3-9daf-38b62c1ceddf", "baseline": [[934, 1382], [1342, 1377]], "boundary": [[934, 1382], [934, 1394], [1342, 1389], [1342, 1377], [1340, 1358], [1239, 1353], [1238, 1353], [1237, 1353], [1236, 1353], [1236, 1354], [1230, 1358], [942, 1356], [941, 1356], [940, 1356], [939, 1356], [933, 1359], [934, 1382]], "text": null, "base_dir": null, "type": "baselines", "imagename": null, "tags": {"type": "default"}, "split": null, "regions": ["17e45a62-26eb-4227-b064-32400bbf2dbb"]}, {"id": "e01c75dd-de1b-40d6-9fad-6113d0b218be", "baseline": [[934, 1406], [1337, 1403]], "boundary": [[1202, 1379], [1201, 1379], [1200, 1379], [1200, 1380], [1195, 1385], [985, 1382], [984, 1382], [933, 1387], [934, 1406], [934, 1417], [1335, 1417], [1337, 1403], [1334, 1385], [1203, 1379], [1202, 1379]], "text": null, "base_dir": null, "type": "baselines", "imagename": null, "tags": {"type": "default"}, "split": null, "regions": ["17e45a62-26eb-4227-b064-32400bbf2dbb"]}, {"id": "9e8c3f53-bc2d-4503-8a82-cbaa55288a50", "baseline": [[935, 1433], [1147, 1427], [1322, 1429]], "boundary": [[1147, 1405], [1146, 1405], [1134, 1410], [1067, 1406], [1066, 1406], [934, 1413], [935, 1433], [935, 1448], [1042, 1440], [1320, 1443], [1322, 1429], [1321, 1409], [1148, 1405], [1147, 1405]], "text": null, "base_dir": null, "type": "baselines", "imagename": null, "tags": {"type": "default"}, "split": null, "regions": ["17e45a62-26eb-4227-b064-32400bbf2dbb"]}, {"id": "1a439bfc-60fa-4cfe-a609-3a7f35b894ed", "baseline": [[935, 1459], [1107, 1453], [1339, 1455]], "boundary": [[935, 1459], [935, 1467], [1337, 1469], [1339, 1455], [1337, 1433], [934, 1439], [935, 1459]], "text": null, "base_dir": null, "type": "baselines", "imagename": null, "tags": {"type": "default"}, "split": null, "regions": ["17e45a62-26eb-4227-b064-32400bbf2dbb"]}, {"id": "6d39e53b-05c7-47c3-b7cc-e5521d26e01d", "baseline": [[936, 1485], [1341, 1485]], "boundary": [[936, 1485], [936, 1498], [1341, 1498], [1341, 1485], [1341, 1466], [936, 1466], [936, 1485]], "text": null, "base_dir": null, "type": "baselines", "imagename": null, "tags": {"type": "default"}, "split": null, "regions": ["17e45a62-26eb-4227-b064-32400bbf2dbb"]}, {"id": "ada0f575-6f2c-4359-a940-ea18fa77279b", "baseline": [[936, 1507], [1335, 1507]], "boundary": [[936, 1507], [936, 1519], [1335, 1518], [1335, 1507], [1335, 1490], [936, 1490], [936, 1507]], "text": null, "base_dir": null, "type": "baselines", "imagename": null, "tags": {"type": "default"}, "split": null, "regions": ["17e45a62-26eb-4227-b064-32400bbf2dbb"]}, {"id": "37b72095-7f81-427f-adc7-67250c7f8300", "baseline": [[940, 1536], [1339, 1532]], "boundary": [[940, 1536], [941, 1560], [974, 1550], [1064, 1550], [1084, 1558], [1085, 1558], [1086, 1558], [1087, 1558], [1107, 1549], [1134, 1558], [1135, 1558], [1136, 1559], [1197, 1559], [1197, 1558], [1338, 1547], [1339, 1532], [1337, 1515], [981, 1511], [980, 1511], [939, 1517], [940, 1536]], "text": null, "base_dir": null, "type": "baselines", "imagename": null, "tags": {"type": "default"}, "split": null, "regions": ["17e45a62-26eb-4227-b064-32400bbf2dbb"]}, {"id": "160f1258-9ca5-498c-8948-02a922c38520", "baseline": [[1613, 247], [2034, 240]], "boundary": [[1878, 213], [1866, 213], [1855, 213], [1844, 215], [1833, 215], [1822, 216], [1813, 216], [1794, 221], [1659, 217], [1658, 217], [1611, 224], [1613, 247], [1613, 263], [1730, 262], [1731, 262], [1761, 254], [2005, 258], [2006, 258], [2007, 258], [2034, 249], [2034, 240], [2032, 217], [1878, 212], [1878, 213]], "text": null, "base_dir": null, "type": "baselines", "imagename": null, "tags": {"type": "default"}, "split": null, "regions": ["a40d4c8d-a287-44fc-b2bf-42b78aa5d1fc"]}, {"id": "826b13aa-2eaf-41e0-abec-d544fcbf3edc", "baseline": [[1590, 274], [1974, 271]], "boundary": [[1590, 274], [1590, 283], [1713, 290], [1715, 290], [1767, 283], [1782, 289], [1783, 289], [1784, 289], [1974, 282], [1974, 271], [1972, 252], [1889, 247], [1888, 247], [1817, 256], [1754, 256], [1745, 249], [1743, 249], [1742, 249], [1741, 249], [1709, 256], [1589, 253], [1590, 274]], "text": null, "base_dir": null, "type": "baselines", "imagename": null, "tags": {"type": "default"}, "split": null, "regions": ["a40d4c8d-a287-44fc-b2bf-42b78aa5d1fc"]}, {"id": "d332a5a1-7ff5-41e5-aa3c-45562b93d1c5", "baseline": [[1594, 305], [2000, 297]], "boundary": [[1956, 272], [1955, 272], [1954, 272], [1945, 279], [1905, 273], [1904, 273], [1903, 273], [1902, 273], [1894, 281], [1593, 281], [1594, 305], [1594, 322], [1666, 313], [1686, 321], [1687, 321], [1688, 321], [1689, 321], [1708, 311], [1767, 311], [1779, 316], [1780, 316], [1781, 316], [1866, 310], [1895, 318], [1896, 318], [1898, 318], [2000, 305], [2000, 297], [1997, 279], [1957, 272], [1956, 272]], "text": null, "base_dir": null, "type": "baselines", "imagename": null, "tags": {"type": "default"}, "split": null, "regions": ["a40d4c8d-a287-44fc-b2bf-42b78aa5d1fc"]}, {"id": "90a4ddb0-7262-4cb7-b5b8-71acd6c0feac", "baseline": [[1626, 330], [2013, 321]], "boundary": [[1626, 330], [1626, 345], [1712, 344], [1713, 344], [1729, 336], [1799, 342], [1800, 342], [1801, 342], [1823, 334], [1944, 339], [1945, 339], [2013, 332], [2013, 321], [2009, 302], [1625, 311], [1626, 330]], "text": null, "base_dir": null, "type": "baselines", "imagename": null, "tags": {"type": "default"}, "split": null, "regions": ["a40d4c8d-a287-44fc-b2bf-42b78aa5d1fc"]}, {"id": "8cd6d83a-38d9-4c75-82a4-16b3ec845b6f", "baseline": [[1647, 353], [1662, 353]], "boundary": [[1647, 353], [1647, 360], [1662, 357], [1662, 353], [1661, 333], [1647, 333], [1647, 353]], "text": null, "base_dir": null, "type": "baselines", "imagename": null, "tags": {"type": "default"}, "split": null, "regions": ["a40d4c8d-a287-44fc-b2bf-42b78aa5d1fc"]}, {"id": "7b745cf8-3b3c-4742-980f-698207e6a5d2", "baseline": [[1705, 352], [2003, 345]], "boundary": [[1705, 352], [1705, 366], [2003, 357], [2003, 345], [2000, 326], [1703, 329], [1705, 352]], "text": null, "base_dir": null, "type": "baselines", "imagename": null, "tags": {"type": "default"}, "split": null, "regions": ["a40d4c8d-a287-44fc-b2bf-42b78aa5d1fc"]}, {"id": "7b6c02d7-5e15-437b-a07a-73199d80ad99", "baseline": [[1707, 376], [2038, 370]], "boundary": [[2036, 361], [2035, 351], [1706, 359], [1707, 376], [1707, 386], [2037, 383], [2038, 370], [2037, 365], [2036, 361]], "text": null, "base_dir": null, "type": "baselines", "imagename": null, "tags": {"type": "default"}, "split": null, "regions": ["a40d4c8d-a287-44fc-b2bf-42b78aa5d1fc"]}, {"id": "0b93dc18-aac5-4d8b-8872-17fccea5ae7a", "baseline": [[1580, 400], [2008, 399]], "boundary": [[1812, 375], [1804, 375], [1793, 383], [1710, 383], [1682, 372], [1681, 372], [1680, 372], [1679, 372], [1678, 372], [1666, 383], [1640, 383], [1627, 372], [1626, 372], [1625, 372], [1624, 372], [1579, 372], [1580, 400], [1580, 413], [2007, 410], [2008, 399], [2004, 376], [1983, 382], [1902, 374], [1901, 374], [1900, 374], [1886, 382], [1872, 374], [1871, 374], [1870, 374], [1869, 374], [1847, 382], [1819, 374], [1812, 375]], "text": null, "base_dir": null, "type": "baselines", "imagename": null, "tags": {"type": "default"}, "split": null, "regions": ["a40d4c8d-a287-44fc-b2bf-42b78aa5d1fc"]}, {"id": "728db369-cd2c-478d-ba59-9c8931c4dbd9", "baseline": [[1526, 424], [1722, 427], [2009, 422]], "boundary": [[1980, 400], [1975, 400], [1933, 406], [1915, 400], [1914, 400], [1913, 400], [1902, 400], [1891, 400], [1880, 400], [1869, 400], [1864, 400], [1863, 400], [1862, 400], [1843, 407], [1630, 408], [1620, 402], [1619, 402], [1618, 402], [1527, 402], [1525, 404], [1526, 424], [1526, 440], [2008, 435], [2009, 422], [2008, 405], [1988, 400], [1980, 400]], "text": null, "base_dir": null, "type": "baselines", "imagename": null, "tags": {"type": "default"}, "split": null, "regions": ["a40d4c8d-a287-44fc-b2bf-42b78aa5d1fc"]}, {"id": "cff2f779-b0d8-4687-b5cf-7871d92ac027", "baseline": [[1523, 453], [2012, 448]], "boundary": [[1523, 453], [1523, 471], [1572, 464], [1643, 469], [1644, 469], [1841, 462], [1895, 466], [1896, 466], [1898, 466], [1914, 461], [1978, 466], [1980, 466], [2011, 459], [2012, 448], [2009, 431], [1914, 425], [1913, 425], [1912, 425], [1911, 425], [1911, 426], [1904, 432], [1656, 430], [1655, 430], [1654, 430], [1631, 435], [1618, 428], [1617, 428], [1558, 428], [1557, 428], [1522, 436], [1523, 453]], "text": null, "base_dir": null, "type": "baselines", "imagename": null, "tags": {"type": "default"}, "split": null, "regions": ["a40d4c8d-a287-44fc-b2bf-42b78aa5d1fc"]}, {"id": "a8121751-a8c1-4d77-86b2-b0929312c5ae", "baseline": [[1522, 482], [2012, 476]], "boundary": [[1522, 482], [1523, 499], [1553, 490], [1680, 497], [1681, 497], [1735, 492], [1743, 496], [1745, 496], [1746, 496], [1747, 496], [1748, 496], [1754, 489], [1779, 496], [1780, 496], [1781, 496], [1782, 496], [1783, 496], [1783, 495], [1789, 489], [1837, 489], [1896, 495], [1898, 495], [1899, 495], [1929, 486], [1966, 492], [1967, 492], [2011, 485], [2012, 476], [2006, 453], [1998, 458], [1935, 452], [1934, 452], [1933, 452], [1910, 459], [1842, 454], [1841, 454], [1809, 461], [1717, 456], [1716, 456], [1685, 463], [1630, 463], [1620, 455], [1619, 455], [1618, 455], [1617, 455], [1521, 464], [1522, 482]], "text": null, "base_dir": null, "type": "baselines", "imagename": null, "tags": {"type": "default"}, "split": null, "regions": ["a40d4c8d-a287-44fc-b2bf-42b78aa5d1fc"]}, {"id": "610f899d-33e3-426b-ab89-ecbb8eb27335", "baseline": [[1554, 510], [1563, 510]], "boundary": [[1554, 510], [1555, 530], [1563, 526], [1563, 510], [1563, 484], [1554, 483], [1554, 510]], "text": null, "base_dir": null, "type": "baselines", "imagename": null, "tags": {"type": "default"}, "split": null, "regions": ["a40d4c8d-a287-44fc-b2bf-42b78aa5d1fc"]}, {"id": "809c0ce1-f2dd-4036-81f8-7038f325de1c", "baseline": [[1577, 620], [1597, 617]], "boundary": [[1577, 620], [1578, 633], [1599, 633], [1597, 617], [1593, 595], [1572, 592], [1577, 620]], "text": null, "base_dir": null, "type": "baselines", "imagename": null, "tags": {"type": "default"}, "split": null, "regions": ["a40d4c8d-a287-44fc-b2bf-42b78aa5d1fc"]}, {"id": "983d855c-7a6f-4c8d-afdd-a2149e55d2c5", "baseline": [[1580, 981], [1595, 981]], "boundary": [[1580, 949], [1580, 981], [1580, 1004], [1595, 1004], [1595, 981], [1593, 934], [1588, 934], [1580, 949]], "text": null, "base_dir": null, "type": "baselines", "imagename": null, "tags": {"type": "default"}, "split": null, "regions": ["a40d4c8d-a287-44fc-b2bf-42b78aa5d1fc"]}, {"id": "4af4d183-1c25-48d5-bf43-a97c34b81134", "baseline": [[1604, 507], [2014, 500]], "boundary": [[1604, 507], [1604, 517], [2014, 514], [2014, 500], [2011, 478], [1788, 487], [1767, 482], [1766, 482], [1764, 482], [1763, 482], [1738, 488], [1603, 485], [1604, 507]], "text": null, "base_dir": null, "type": "baselines", "imagename": null, "tags": {"type": "default"}, "split": null, "regions": ["a40d4c8d-a287-44fc-b2bf-42b78aa5d1fc"]}, {"id": "c32140a1-c4e3-4a9c-a56c-a86086901f21", "baseline": [[1613, 538], [2018, 525]], "boundary": [[1613, 538], [1613, 553], [2018, 539], [2018, 525], [2015, 508], [1611, 515], [1613, 538]], "text": null, "base_dir": null, "type": "baselines", "imagename": null, "tags": {"type": "default"}, "split": null, "regions": ["a40d4c8d-a287-44fc-b2bf-42b78aa5d1fc"]}, {"id": "4fb8cd36-5c22-4515-9a92-5e9c7f687d8a", "baseline": [[1618, 563], [2005, 550]], "boundary": [[1618, 563], [1618, 571], [2005, 564], [2005, 550], [2003, 535], [1828, 534], [1827, 534], [1825, 534], [1810, 539], [1652, 539], [1651, 539], [1617, 546], [1618, 563]], "text": null, "base_dir": null, "type": "baselines", "imagename": null, "tags": {"type": "default"}, "split": null, "regions": ["a40d4c8d-a287-44fc-b2bf-42b78aa5d1fc"]}, {"id": "e8363ac5-5d25-4cb0-bc3c-a824f768b213", "baseline": [[1617, 589], [1834, 579], [2012, 577]], "boundary": [[1617, 589], [1617, 599], [2012, 589], [2012, 577], [2009, 558], [1922, 555], [1921, 555], [1616, 569], [1617, 589]], "text": null, "base_dir": null, "type": "baselines", "imagename": null, "tags": {"type": "default"}, "split": null, "regions": ["a40d4c8d-a287-44fc-b2bf-42b78aa5d1fc"]}, {"id": "084dfef4-4859-47bd-8b41-16e3f1b79268", "baseline": [[1614, 616], [2007, 604]], "boundary": [[1614, 616], [1614, 627], [2007, 615], [2007, 604], [2004, 581], [1717, 594], [1684, 589], [1682, 589], [1644, 596], [1613, 591], [1614, 616]], "text": null, "base_dir": null, "type": "baselines", "imagename": null, "tags": {"type": "default"}, "split": null, "regions": ["a40d4c8d-a287-44fc-b2bf-42b78aa5d1fc"]}, {"id": "01eaedc5-3290-4c90-b60e-9f657439d019", "baseline": [[1619, 642], [2012, 629]], "boundary": [[1619, 642], [1619, 651], [2012, 642], [2012, 629], [2009, 609], [1915, 608], [1914, 608], [1879, 615], [1850, 610], [1849, 610], [1814, 617], [1790, 612], [1789, 612], [1715, 620], [1656, 617], [1655, 617], [1618, 623], [1619, 642]], "text": null, "base_dir": null, "type": "baselines", "imagename": null, "tags": {"type": "default"}, "split": null, "regions": ["a40d4c8d-a287-44fc-b2bf-42b78aa5d1fc"]}, {"id": "86f8c63f-a45b-4b18-84c0-515d46fb3676", "baseline": [[1619, 666], [2008, 656]], "boundary": [[1619, 666], [1619, 678], [2008, 670], [2008, 656], [2005, 637], [1618, 642], [1619, 666]], "text": null, "base_dir": null, "type": "baselines", "imagename": null, "tags": {"type": "default"}, "split": null, "regions": ["a40d4c8d-a287-44fc-b2bf-42b78aa5d1fc"]}, {"id": "ae62ad2f-e76a-4c42-8429-a930937fd9ed", "baseline": [[1618, 690], [2002, 681]], "boundary": [[1618, 690], [1618, 701], [2002, 692], [2002, 681], [1998, 663], [1617, 670], [1618, 690]], "text": null, "base_dir": null, "type": "baselines", "imagename": null, "tags": {"type": "default"}, "split": null, "regions": ["a40d4c8d-a287-44fc-b2bf-42b78aa5d1fc"]}, {"id": "0d8f3663-3f48-4e46-94f1-a677e2137ad7", "baseline": [[1618, 717], [2018, 708]], "boundary": [[1618, 717], [1618, 727], [2018, 718], [2018, 708], [2015, 690], [1617, 693], [1618, 717]], "text": null, "base_dir": null, "type": "baselines", "imagename": null, "tags": {"type": "default"}, "split": null, "regions": ["a40d4c8d-a287-44fc-b2bf-42b78aa5d1fc"]}, {"id": "645bef46-1288-4a65-b8fb-9fe83ec21742", "baseline": [[1618, 742], [2023, 734]], "boundary": [[1618, 742], [1618, 755], [2023, 743], [2023, 734], [2019, 712], [1617, 723], [1618, 742]], "text": null, "base_dir": null, "type": "baselines", "imagename": null, "tags": {"type": "default"}, "split": null, "regions": ["a40d4c8d-a287-44fc-b2bf-42b78aa5d1fc"]}, {"id": "673f7e4a-0bca-43f5-8333-4abe95efdf81", "baseline": [[1617, 765], [2012, 760]], "boundary": [[1617, 765], [1617, 776], [2011, 774], [2012, 760], [2008, 739], [1616, 747], [1617, 765]], "text": null, "base_dir": null, "type": "baselines", "imagename": null, "tags": {"type": "default"}, "split": null, "regions": ["a40d4c8d-a287-44fc-b2bf-42b78aa5d1fc"]}, {"id": "86257979-fd09-4de8-88ce-012fc758a550", "baseline": [[1617, 794], [2021, 786]], "boundary": [[1617, 794], [1617, 803], [2021, 798], [2021, 786], [2018, 770], [1974, 764], [1973, 764], [1900, 772], [1616, 772], [1617, 794]], "text": null, "base_dir": null, "type": "baselines", "imagename": null, "tags": {"type": "default"}, "split": null, "regions": ["a40d4c8d-a287-44fc-b2bf-42b78aa5d1fc"]}, {"id": "69008dc1-9392-48ff-9e6e-8b5a6d1d6955", "baseline": [[1616, 822], [2015, 814]], "boundary": [[1616, 822], [1616, 832], [2015, 823], [2015, 814], [2012, 794], [1670, 795], [1669, 795], [1657, 801], [1615, 796], [1616, 822]], "text": null, "base_dir": null, "type": "baselines", "imagename": null, "tags": {"type": "default"}, "split": null, "regions": ["a40d4c8d-a287-44fc-b2bf-42b78aa5d1fc"]}, {"id": "3c1d7c90-e900-4db9-a452-bda8cda6a644", "baseline": [[1616, 846], [2009, 839]], "boundary": [[1616, 846], [1616, 861], [2009, 848], [2009, 839], [2006, 819], [1876, 824], [1840, 820], [1839, 820], [1838, 820], [1817, 825], [1804, 821], [1803, 821], [1802, 821], [1801, 821], [1781, 826], [1728, 822], [1727, 822], [1726, 822], [1715, 827], [1671, 823], [1670, 823], [1615, 830], [1616, 846]], "text": null, "base_dir": null, "type": "baselines", "imagename": null, "tags": {"type": "default"}, "split": null, "regions": ["a40d4c8d-a287-44fc-b2bf-42b78aa5d1fc"]}, {"id": "f1230ed7-affb-4a89-ad3b-ad33c5777ddb", "baseline": [[1617, 873], [2021, 864]], "boundary": [[1617, 873], [1617, 884], [2021, 876], [2021, 864], [2017, 842], [1917, 848], [1876, 844], [1875, 844], [1874, 844], [1873, 844], [1865, 850], [1820, 845], [1819, 845], [1818, 845], [1817, 845], [1817, 846], [1811, 851], [1741, 847], [1740, 847], [1739, 847], [1715, 853], [1627, 850], [1626, 850], [1625, 850], [1624, 850], [1616, 854], [1617, 873]], "text": null, "base_dir": null, "type": "baselines", "imagename": null, "tags": {"type": "default"}, "split": null, "regions": ["a40d4c8d-a287-44fc-b2bf-42b78aa5d1fc"]}, {"id": "1cba7410-9756-442f-a95c-cb3973f9740e", "baseline": [[1619, 902], [2022, 894]], "boundary": [[2018, 875], [1676, 875], [1675, 875], [1618, 882], [1619, 902], [1619, 912], [2021, 907], [2022, 894], [2021, 893], [2018, 875]], "text": null, "base_dir": null, "type": "baselines", "imagename": null, "tags": {"type": "default"}, "split": null, "regions": ["a40d4c8d-a287-44fc-b2bf-42b78aa5d1fc"]}, {"id": "f82129d8-93a7-42e2-a9ce-5752596e36c1", "baseline": [[1618, 925], [2024, 917]], "boundary": [[1618, 925], [1618, 940], [2023, 928], [2024, 917], [2021, 899], [1617, 904], [1618, 925]], "text": null, "base_dir": null, "type": "baselines", "imagename": null, "tags": {"type": "default"}, "split": null, "regions": ["a40d4c8d-a287-44fc-b2bf-42b78aa5d1fc"]}, {"id": "6010aecc-908c-43cd-acb6-25ad95975688", "baseline": [[1615, 953], [2021, 945]], "boundary": [[1615, 953], [1615, 963], [2021, 956], [2021, 945], [2017, 922], [1614, 933], [1615, 953]], "text": null, "base_dir": null, "type": "baselines", "imagename": null, "tags": {"type": "default"}, "split": null, "regions": ["a40d4c8d-a287-44fc-b2bf-42b78aa5d1fc"]}, {"id": "75fd9799-5b18-4c71-a50a-442f6263479a", "baseline": [[1614, 981], [2017, 969]], "boundary": [[1614, 981], [1614, 993], [1684, 997], [1685, 997], [1686, 997], [1687, 997], [1687, 996], [1688, 996], [1692, 989], [1722, 989], [1790, 994], [1791, 994], [1864, 991], [1865, 991], [1866, 991], [1875, 985], [1898, 990], [1899, 990], [1900, 990], [2017, 986], [2017, 969], [2015, 952], [1838, 952], [1837, 952], [1835, 952], [1834, 952], [1828, 957], [1797, 953], [1796, 953], [1754, 959], [1725, 955], [1723, 955], [1680, 962], [1647, 957], [1646, 957], [1613, 963], [1614, 981]], "text": null, "base_dir": null, "type": "baselines", "imagename": null, "tags": {"type": "default"}, "split": null, "regions": ["a40d4c8d-a287-44fc-b2bf-42b78aa5d1fc"]}, {"id": "5b6f0dc8-252e-467a-a62f-2630820783d8", "baseline": [[1626, 1009], [2024, 1003]], "boundary": [[1626, 1009], [1626, 1019], [2024, 1013], [2024, 1003], [2022, 984], [1968, 978], [1967, 978], [1966, 978], [1954, 985], [1625, 985], [1626, 1009]], "text": null, "base_dir": null, "type": "baselines", "imagename": null, "tags": {"type": "default"}, "split": null, "regions": ["a40d4c8d-a287-44fc-b2bf-42b78aa5d1fc"]}, {"id": "62814510-66ab-4aec-af95-862ce3ff5baf", "baseline": [[1620, 1037], [2008, 1027]], "boundary": [[1620, 1037], [1620, 1049], [1702, 1052], [1703, 1052], [1705, 1052], [1722, 1044], [1831, 1048], [1832, 1048], [1882, 1040], [1919, 1046], [1920, 1046], [1921, 1046], [1922, 1046], [1922, 1045], [1927, 1039], [2008, 1035], [2008, 1027], [2005, 1009], [1619, 1017], [1620, 1037]], "text": null, "base_dir": null, "type": "baselines", "imagename": null, "tags": {"type": "default"}, "split": null, "regions": ["a40d4c8d-a287-44fc-b2bf-42b78aa5d1fc"]}, {"id": "7f88839a-26d6-4293-ad95-c0f8935af116", "baseline": [[1713, 1059], [2009, 1051]], "boundary": [[1713, 1059], [1713, 1070], [2009, 1060], [2009, 1051], [2006, 1031], [1712, 1039], [1713, 1059]], "text": null, "base_dir": null, "type": "baselines", "imagename": null, "tags": {"type": "default"}, "split": null, "regions": ["a40d4c8d-a287-44fc-b2bf-42b78aa5d1fc"]}, {"id": "f4b30385-381f-47c2-ad79-17e10b056160", "baseline": [[1646, 1086], [2011, 1076]], "boundary": [[1646, 1086], [1646, 1091], [1805, 1097], [1807, 1097], [1956, 1092], [1957, 1092], [1973, 1086], [1998, 1091], [2000, 1091], [2001, 1091], [2002, 1091], [2011, 1086], [2011, 1076], [2007, 1054], [1645, 1067], [1646, 1086]], "text": null, "base_dir": null, "type": "baselines", "imagename": null, "tags": {"type": "default"}, "split": null, "regions": ["a40d4c8d-a287-44fc-b2bf-42b78aa5d1fc"]}, {"id": "44e2ed1e-44ac-4aeb-a37e-39e052956f11", "baseline": [[1590, 1110], [2017, 1105]], "boundary": [[1590, 1110], [1590, 1123], [1665, 1126], [1666, 1126], [1700, 1119], [1759, 1124], [1760, 1124], [1805, 1118], [1824, 1123], [1825, 1123], [1827, 1123], [1828, 1123], [1856, 1117], [1917, 1117], [1927, 1122], [1929, 1122], [1930, 1122], [1931, 1122], [2016, 1114], [2017, 1105], [2014, 1083], [1589, 1092], [1590, 1110]], "text": null, "base_dir": null, "type": "baselines", "imagename": null, "tags": {"type": "default"}, "split": null, "regions": ["a40d4c8d-a287-44fc-b2bf-42b78aa5d1fc"]}, {"id": "58354b55-7055-45d2-8e94-a150f5b86277", "baseline": [[1620, 1139], [2022, 1129]], "boundary": [[1620, 1139], [1620, 1153], [2022, 1139], [2022, 1129], [2019, 1112], [1798, 1111], [1797, 1111], [1619, 1121], [1620, 1139]], "text": null, "base_dir": null, "type": "baselines", "imagename": null, "tags": {"type": "default"}, "split": null, "regions": ["a40d4c8d-a287-44fc-b2bf-42b78aa5d1fc"]}, {"id": "478d1a7c-052c-4b76-973c-bf47c0db7bff", "baseline": [[1621, 1165], [2019, 1153]], "boundary": [[1621, 1165], [1621, 1177], [2019, 1165], [2019, 1153], [2016, 1133], [1620, 1149], [1621, 1165]], "text": null, "base_dir": null, "type": "baselines", "imagename": null, "tags": {"type": "default"}, "split": null, "regions": ["a40d4c8d-a287-44fc-b2bf-42b78aa5d1fc"]}, {"id": "43608151-992b-4156-9eaf-181d7bcabaf6", "baseline": [[1624, 1189], [2022, 1181]], "boundary": [[1624, 1189], [1624, 1199], [2022, 1195], [2022, 1181], [2019, 1165], [1919, 1161], [1917, 1161], [1623, 1172], [1624, 1189]], "text": null, "base_dir": null, "type": "baselines", "imagename": null, "tags": {"type": "default"}, "split": null, "regions": ["a40d4c8d-a287-44fc-b2bf-42b78aa5d1fc"]}, {"id": "72605b27-53ec-4bc7-ac83-afacc3ec7d8f", "baseline": [[1619, 1216], [2025, 1209]], "boundary": [[1619, 1216], [1619, 1232], [2024, 1220], [2025, 1209], [2023, 1192], [1965, 1185], [1964, 1185], [1963, 1185], [1939, 1192], [1907, 1188], [1906, 1188], [1848, 1194], [1618, 1193], [1619, 1216]], "text": null, "base_dir": null, "type": "baselines", "imagename": null, "tags": {"type": "default"}, "split": null, "regions": ["a40d4c8d-a287-44fc-b2bf-42b78aa5d1fc"]}, {"id": "b833fac7-8632-4f37-b06d-88abea669515", "baseline": [[1616, 1242], [2019, 1233]], "boundary": [[1616, 1242], [1616, 1256], [2019, 1246], [2019, 1233], [2016, 1216], [1615, 1220], [1616, 1242]], "text": null, "base_dir": null, "type": "baselines", "imagename": null, "tags": {"type": "default"}, "split": null, "regions": ["a40d4c8d-a287-44fc-b2bf-42b78aa5d1fc"]}, {"id": "77ad5a2d-d4a3-4827-b041-b7481a41457f", "baseline": [[1621, 1266], [2022, 1260]], "boundary": [[1621, 1266], [1621, 1282], [1688, 1275], [2021, 1275], [2022, 1260], [2018, 1240], [1620, 1249], [1621, 1266]], "text": null, "base_dir": null, "type": "baselines", "imagename": null, "tags": {"type": "default"}, "split": null, "regions": ["a40d4c8d-a287-44fc-b2bf-42b78aa5d1fc"]}, {"id": "054ec023-3365-40fc-93ca-c5401c16a8ba", "baseline": [[1621, 1290], [2021, 1285]], "boundary": [[1621, 1290], [1621, 1304], [2021, 1300], [2021, 1285], [2018, 1267], [1720, 1267], [1719, 1267], [1718, 1267], [1705, 1273], [1651, 1269], [1650, 1269], [1620, 1274], [1621, 1290]], "text": null, "base_dir": null, "type": "baselines", "imagename": null, "tags": {"type": "default"}, "split": null, "regions": ["a40d4c8d-a287-44fc-b2bf-42b78aa5d1fc"]}, {"id": "5ce455bc-543f-4c26-a4cc-a504071f7725", "baseline": [[1623, 1314], [2018, 1314]], "boundary": [[1623, 1314], [1623, 1324], [2017, 1327], [2018, 1314], [2017, 1295], [1623, 1295], [1623, 1314]], "text": null, "base_dir": null, "type": "baselines", "imagename": null, "tags": {"type": "default"}, "split": null, "regions": ["a40d4c8d-a287-44fc-b2bf-42b78aa5d1fc"]}, {"id": "3ee968f2-ae2c-4ddb-b6ae-b380c6ecedec", "baseline": [[1623, 1342], [2031, 1342]], "boundary": [[1623, 1342], [1623, 1357], [2031, 1357], [2031, 1342], [2031, 1322], [1623, 1317], [1623, 1342]], "text": null, "base_dir": null, "type": "baselines", "imagename": null, "tags": {"type": "default"}, "split": null, "regions": ["a40d4c8d-a287-44fc-b2bf-42b78aa5d1fc"]}, {"id": "21204efe-e54b-47e1-a696-ae269166ee76", "baseline": [[1625, 1368], [2023, 1366]], "boundary": [[1625, 1368], [1625, 1382], [2022, 1377], [2023, 1366], [2021, 1347], [1630, 1346], [1629, 1346], [1628, 1346], [1627, 1346], [1627, 1347], [1624, 1349], [1625, 1368]], "text": null, "base_dir": null, "type": "baselines", "imagename": null, "tags": {"type": "default"}, "split": null, "regions": ["a40d4c8d-a287-44fc-b2bf-42b78aa5d1fc"]}, {"id": "2d2ca5bb-929f-4348-8d38-b8b305f2af1c", "baseline": [[1624, 1396], [2022, 1392]], "boundary": [[1624, 1396], [1624, 1407], [2021, 1406], [2022, 1392], [2018, 1371], [1623, 1374], [1624, 1396]], "text": null, "base_dir": null, "type": "baselines", "imagename": null, "tags": {"type": "default"}, "split": null, "regions": ["a40d4c8d-a287-44fc-b2bf-42b78aa5d1fc"]}, {"id": "3401e815-db91-40d9-9b0f-51c8329545ae", "baseline": [[1625, 1421], [2022, 1417]], "boundary": [[1625, 1421], [1625, 1434], [2021, 1430], [2022, 1417], [2019, 1400], [1722, 1398], [1721, 1398], [1624, 1404], [1625, 1421]], "text": null, "base_dir": null, "type": "baselines", "imagename": null, "tags": {"type": "default"}, "split": null, "regions": ["a40d4c8d-a287-44fc-b2bf-42b78aa5d1fc"]}, {"id": "5a0888a9-5a49-49e0-8771-d3daa917f028", "baseline": [[1625, 1451], [2029, 1445]], "boundary": [[1625, 1451], [1625, 1461], [2028, 1455], [2029, 1445], [2027, 1426], [1963, 1420], [1962, 1420], [1961, 1420], [1940, 1427], [1624, 1427], [1625, 1451]], "text": null, "base_dir": null, "type": "baselines", "imagename": null, "tags": {"type": "default"}, "split": null, "regions": ["a40d4c8d-a287-44fc-b2bf-42b78aa5d1fc"]}, {"id": "82b84c2b-7fe0-4013-877b-9318c7c877fc", "baseline": [[1626, 1476], [2027, 1471]], "boundary": [[1626, 1476], [1626, 1491], [2026, 1485], [2027, 1471], [2024, 1450], [1625, 1459], [1626, 1476]], "text": null, "base_dir": null, "type": "baselines", "imagename": null, "tags": {"type": "default"}, "split": null, "regions": ["a40d4c8d-a287-44fc-b2bf-42b78aa5d1fc"]}, {"id": "47f60902-0605-4a58-935e-54093c574875", "baseline": [[1626, 1504], [2022, 1497]], "boundary": [[1626, 1504], [1626, 1515], [2022, 1507], [2022, 1497], [2019, 1481], [1966, 1476], [1965, 1476], [1934, 1481], [1830, 1478], [1829, 1478], [1625, 1486], [1626, 1504]], "text": null, "base_dir": null, "type": "baselines", "imagename": null, "tags": {"type": "default"}, "split": null, "regions": ["a40d4c8d-a287-44fc-b2bf-42b78aa5d1fc"]}, {"id": "ee5c624c-d3b6-4ae2-b664-c17eb58fb6d1", "baseline": [[1624, 1535], [2038, 1523]], "boundary": [[1624, 1535], [1624, 1554], [1688, 1553], [1689, 1553], [1707, 1545], [1729, 1552], [1730, 1552], [1731, 1552], [1732, 1552], [1749, 1543], [1788, 1551], [1789, 1551], [1832, 1541], [1936, 1547], [1937, 1547], [2038, 1541], [2038, 1523], [2035, 1504], [1658, 1508], [1623, 1513], [1624, 1535]], "text": null, "base_dir": null, "type": "baselines", "imagename": null, "tags": {"type": "default"}, "split": null, "regions": ["a40d4c8d-a287-44fc-b2bf-42b78aa5d1fc"]}, {"id": "bd62e29a-e112-4300-a406-965ca3485dae", "baseline": [[1577, 1570], [1831, 1569]], "boundary": [[1577, 1570], [1577, 1635], [1605, 1631], [1619, 1644], [1619, 1645], [1620, 1645], [1621, 1645], [1692, 1650], [1694, 1650], [1695, 1650], [1696, 1650], [1696, 1649], [1713, 1633], [1733, 1631], [1766, 1650], [1767, 1650], [1768, 1650], [1769, 1650], [1770, 1650], [1771, 1650], [1771, 1649], [1792, 1631], [1830, 1634], [1831, 1569], [1829, 1540], [1793, 1540], [1792, 1540], [1791, 1540], [1766, 1552], [1741, 1542], [1740, 1542], [1739, 1542], [1738, 1542], [1737, 1542], [1726, 1551], [1715, 1541], [1715, 1540], [1713, 1540], [1712, 1540], [1697, 1540], [1696, 1540], [1695, 1540], [1662, 1552], [1604, 1545], [1603, 1545], [1601, 1545], [1576, 1553], [1577, 1570]], "text": null, "base_dir": null, "type": "baselines", "imagename": null, "tags": {"type": "default"}, "split": null, "regions": ["a40d4c8d-a287-44fc-b2bf-42b78aa5d1fc"]}, {"id": "254af89f-b05b-4b8d-9918-b31fcd22fed3", "baseline": [[2062, 240], [2483, 232]], "boundary": [[2471, 219], [2460, 218], [2449, 218], [2437, 217], [2426, 216], [2415, 215], [2404, 215], [2393, 213], [2382, 212], [2371, 212], [2360, 211], [2349, 210], [2338, 210], [2327, 209], [2315, 208], [2304, 207], [2302, 207], [2289, 213], [2263, 209], [2262, 209], [2226, 215], [2203, 201], [2202, 201], [2201, 201], [2200, 201], [2119, 202], [2118, 202], [2089, 219], [2060, 219], [2062, 240], [2062, 256], [2121, 248], [2156, 253], [2157, 253], [2158, 253], [2182, 247], [2221, 253], [2222, 253], [2260, 246], [2271, 252], [2272, 252], [2273, 252], [2274, 252], [2483, 247], [2483, 232], [2474, 219], [2471, 219]], "text": null, "base_dir": null, "type": "baselines", "imagename": null, "tags": {"type": "default"}, "split": null, "regions": ["a40d4c8d-a287-44fc-b2bf-42b78aa5d1fc"]}, {"id": "580fbefc-fcb5-4423-842e-d51f2d199197", "baseline": [[2088, 270], [2496, 263]], "boundary": [[2088, 270], [2088, 278], [2154, 284], [2155, 284], [2296, 275], [2342, 281], [2343, 281], [2443, 273], [2467, 279], [2468, 279], [2470, 279], [2471, 279], [2496, 271], [2496, 263], [2493, 237], [2280, 246], [2215, 241], [2213, 241], [2186, 247], [2172, 240], [2171, 240], [2170, 240], [2169, 240], [2155, 247], [2148, 240], [2147, 240], [2146, 240], [2145, 240], [2087, 240], [2088, 270]], "text": null, "base_dir": null, "type": "baselines", "imagename": null, "tags": {"type": "default"}, "split": null, "regions": ["a40d4c8d-a287-44fc-b2bf-42b78aa5d1fc"]}, {"id": "f29fecd7-2f7a-4a2d-a999-f151149357d6", "baseline": [[2060, 297], [2494, 290]], "boundary": [[2060, 297], [2060, 311], [2092, 305], [2130, 311], [2131, 311], [2174, 304], [2188, 310], [2189, 310], [2190, 310], [2191, 310], [2215, 303], [2477, 305], [2478, 305], [2480, 305], [2494, 298], [2494, 290], [2491, 270], [2059, 277], [2060, 297]], "text": null, "base_dir": null, "type": "baselines", "imagename": null, "tags": {"type": "default"}, "split": null, "regions": ["a40d4c8d-a287-44fc-b2bf-42b78aa5d1fc"]}, {"id": "132e45ff-ce8c-4bad-ab98-1151b867044b", "baseline": [[2088, 322], [2497, 316]], "boundary": [[2088, 322], [2088, 331], [2496, 325], [2497, 316], [2494, 298], [2444, 299], [2437, 293], [2436, 293], [2435, 293], [2434, 293], [2354, 300], [2333, 294], [2332, 294], [2331, 294], [2290, 301], [2270, 295], [2269, 295], [2268, 295], [2267, 295], [2266, 295], [2258, 301], [2217, 297], [2216, 297], [2215, 297], [2194, 302], [2171, 297], [2170, 297], [2169, 297], [2168, 297], [2167, 297], [2167, 298], [2160, 303], [2087, 299], [2088, 322]], "text": null, "base_dir": null, "type": "baselines", "imagename": null, "tags": {"type": "default"}, "split": null, "regions": ["a40d4c8d-a287-44fc-b2bf-42b78aa5d1fc"]}, {"id": "fa8e8c87-cbdc-40c9-a515-792aced510ea", "baseline": [[2093, 345], [2496, 341]], "boundary": [[2093, 345], [2093, 355], [2495, 354], [2496, 341], [2493, 320], [2092, 325], [2093, 345]], "text": null, "base_dir": null, "type": "baselines", "imagename": null, "tags": {"type": "default"}, "split": null, "regions": ["a40d4c8d-a287-44fc-b2bf-42b78aa5d1fc"]}, {"id": "d7473221-1fdf-4a68-8d2c-68734307decb", "baseline": [[2089, 370], [2491, 367]], "boundary": [[2089, 370], [2089, 379], [2490, 376], [2491, 367], [2487, 350], [2088, 351], [2089, 370]], "text": null, "base_dir": null, "type": "baselines", "imagename": null, "tags": {"type": "default"}, "split": null, "regions": ["a40d4c8d-a287-44fc-b2bf-42b78aa5d1fc"]}, {"id": "3e270e3e-985c-489b-8213-aa3349ab5754", "baseline": [[2090, 394], [2496, 387]], "boundary": [[2488, 369], [2477, 369], [2466, 369], [2455, 369], [2444, 369], [2433, 369], [2425, 369], [2089, 373], [2090, 394], [2090, 408], [2496, 399], [2496, 387], [2493, 367], [2488, 367], [2488, 369]], "text": null, "base_dir": null, "type": "baselines", "imagename": null, "tags": {"type": "default"}, "split": null, "regions": ["a40d4c8d-a287-44fc-b2bf-42b78aa5d1fc"]}, {"id": "02c86150-4518-4cbe-9414-2d4d1195ec48", "baseline": [[2094, 424], [2504, 414]], "boundary": [[2094, 424], [2094, 434], [2504, 431], [2504, 414], [2501, 394], [2093, 403], [2094, 424]], "text": null, "base_dir": null, "type": "baselines", "imagename": null, "tags": {"type": "default"}, "split": null, "regions": ["a40d4c8d-a287-44fc-b2bf-42b78aa5d1fc"]}, {"id": "6d9585cc-8e84-4590-a0a4-9a14365725a1", "baseline": [[2093, 447], [2503, 443]], "boundary": [[2093, 447], [2093, 457], [2502, 456], [2503, 443], [2500, 425], [2092, 425], [2093, 447]], "text": null, "base_dir": null, "type": "baselines", "imagename": null, "tags": {"type": "default"}, "split": null, "regions": ["a40d4c8d-a287-44fc-b2bf-42b78aa5d1fc"]}, {"id": "e81a8d2c-9cfb-42db-9e9b-a15fc2154a3d", "baseline": [[2094, 473], [2505, 467]], "boundary": [[2094, 473], [2094, 488], [2504, 478], [2505, 467], [2502, 451], [2093, 451], [2094, 473]], "text": null, "base_dir": null, "type": "baselines", "imagename": null, "tags": {"type": "default"}, "split": null, "regions": ["a40d4c8d-a287-44fc-b2bf-42b78aa5d1fc"]}, {"id": "4b1e4a08-d420-4e62-88b8-95599881bd27", "baseline": [[2092, 500], [2225, 495], [2506, 496]], "boundary": [[2092, 500], [2092, 508], [2504, 510], [2506, 496], [2504, 478], [2090, 479], [2092, 500]], "text": null, "base_dir": null, "type": "baselines", "imagename": null, "tags": {"type": "default"}, "split": null, "regions": ["a40d4c8d-a287-44fc-b2bf-42b78aa5d1fc"]}, {"id": "96cca3aa-fdb3-4e14-bc03-062e0d86475f", "baseline": [[2092, 526], [2492, 520]], "boundary": [[2092, 526], [2092, 538], [2491, 530], [2492, 520], [2490, 503], [2250, 499], [2249, 499], [2090, 507], [2092, 526]], "text": null, "base_dir": null, "type": "baselines", "imagename": null, "tags": {"type": "default"}, "split": null, "regions": ["a40d4c8d-a287-44fc-b2bf-42b78aa5d1fc"]}, {"id": "94b01987-f060-4cb8-abd7-c1076b4fa886", "baseline": [[2093, 551], [2497, 544]], "boundary": [[2093, 551], [2093, 561], [2496, 554], [2497, 544], [2495, 527], [2221, 527], [2220, 527], [2219, 527], [2203, 533], [2155, 528], [2154, 528], [2092, 535], [2093, 551]], "text": null, "base_dir": null, "type": "baselines", "imagename": null, "tags": {"type": "default"}, "split": null, "regions": ["a40d4c8d-a287-44fc-b2bf-42b78aa5d1fc"]}, {"id": "4cc5b014-346b-4e8a-a527-e1d597634fb6", "baseline": [[2093, 576], [2492, 568]], "boundary": [[2093, 576], [2093, 590], [2492, 578], [2492, 568], [2488, 553], [2092, 559], [2093, 576]], "text": null, "base_dir": null, "type": "baselines", "imagename": null, "tags": {"type": "default"}, "split": null, "regions": ["a40d4c8d-a287-44fc-b2bf-42b78aa5d1fc"]}, {"id": "264cf91e-ab40-4721-9df2-c6b92c64ec1b", "baseline": [[2072, 600], [2487, 597]], "boundary": [[2219, 574], [2218, 574], [2199, 582], [2167, 577], [2166, 577], [2101, 582], [2094, 576], [2093, 576], [2092, 575], [2092, 575], [2090, 575], [2070, 575], [2072, 600], [2074, 617], [2083, 611], [2486, 612], [2487, 597], [2486, 580], [2461, 573], [2460, 573], [2458, 573], [2416, 579], [2356, 574], [2355, 574], [2354, 574], [2323, 582], [2259, 582], [2220, 574], [2219, 574]], "text": null, "base_dir": null, "type": "baselines", "imagename": null, "tags": {"type": "default"}, "split": null, "regions": ["a40d4c8d-a287-44fc-b2bf-42b78aa5d1fc"]}, {"id": "f579e150-2436-4e0f-aa39-cde1c77ff3bc", "baseline": [[2082, 629], [2495, 619]], "boundary": [[2082, 629], [2082, 645], [2141, 638], [2159, 643], [2160, 643], [2161, 643], [2162, 643], [2174, 638], [2196, 642], [2197, 642], [2198, 642], [2199, 642], [2206, 637], [2349, 639], [2350, 639], [2351, 639], [2370, 632], [2399, 638], [2400, 638], [2401, 638], [2402, 638], [2410, 631], [2427, 637], [2429, 637], [2430, 637], [2495, 630], [2495, 619], [2492, 601], [2080, 608], [2082, 629]], "text": null, "base_dir": null, "type": "baselines", "imagename": null, "tags": {"type": "default"}, "split": null, "regions": ["a40d4c8d-a287-44fc-b2bf-42b78aa5d1fc"]}, {"id": "b5f8201a-3de2-495b-8728-0b311e16d280", "baseline": [[2074, 655], [2495, 647]], "boundary": [[2074, 655], [2074, 667], [2495, 660], [2495, 647], [2492, 626], [2073, 636], [2074, 655]], "text": null, "base_dir": null, "type": "baselines", "imagename": null, "tags": {"type": "default"}, "split": null, "regions": ["a40d4c8d-a287-44fc-b2bf-42b78aa5d1fc"]}, {"id": "d92c20b3-9b0e-45b1-9f6d-dd205f74eb94", "baseline": [[2094, 683], [2493, 671]], "boundary": [[2094, 683], [2094, 693], [2384, 690], [2492, 681], [2493, 671], [2491, 653], [2347, 651], [2345, 651], [2093, 665], [2094, 683]], "text": null, "base_dir": null, "type": "baselines", "imagename": null, "tags": {"type": "default"}, "split": null, "regions": ["a40d4c8d-a287-44fc-b2bf-42b78aa5d1fc"]}, {"id": "70be573c-8dc5-4a65-91e1-bb95b4ee1340", "baseline": [[2090, 709], [2487, 697]], "boundary": [[2090, 709], [2090, 723], [2197, 715], [2233, 720], [2235, 720], [2307, 712], [2486, 712], [2487, 697], [2484, 679], [2089, 690], [2090, 709]], "text": null, "base_dir": null, "type": "baselines", "imagename": null, "tags": {"type": "default"}, "split": null, "regions": ["a40d4c8d-a287-44fc-b2bf-42b78aa5d1fc"]}, {"id": "8ce59521-a6ba-434b-b9f1-bd1b9e49da78", "baseline": [[2093, 734], [2497, 723]], "boundary": [[2093, 734], [2093, 744], [2497, 738], [2497, 723], [2495, 707], [2456, 701], [2455, 701], [2092, 715], [2093, 734]], "text": null, "base_dir": null, "type": "baselines", "imagename": null, "tags": {"type": "default"}, "split": null, "regions": ["a40d4c8d-a287-44fc-b2bf-42b78aa5d1fc"]}, {"id": "4b3cf314-7aa5-496c-8660-3a74860054a1", "baseline": [[2094, 759], [2493, 750]], "boundary": [[2094, 759], [2094, 772], [2493, 761], [2493, 750], [2491, 733], [2345, 731], [2344, 731], [2343, 731], [2342, 731], [2342, 732], [2341, 732], [2338, 737], [2263, 733], [2262, 733], [2093, 742], [2094, 759]], "text": null, "base_dir": null, "type": "baselines", "imagename": null, "tags": {"type": "default"}, "split": null, "regions": ["a40d4c8d-a287-44fc-b2bf-42b78aa5d1fc"]}, {"id": "4005e404-0856-4e5d-8d0d-7146dbd9838d", "baseline": [[2094, 786], [2490, 776]], "boundary": [[2094, 786], [2094, 800], [2490, 785], [2490, 776], [2487, 759], [2444, 753], [2443, 753], [2347, 761], [2318, 756], [2317, 756], [2315, 756], [2314, 756], [2307, 762], [2109, 762], [2108, 762], [2107, 762], [2093, 768], [2094, 786]], "text": null, "base_dir": null, "type": "baselines", "imagename": null, "tags": {"type": "default"}, "split": null, "regions": ["a40d4c8d-a287-44fc-b2bf-42b78aa5d1fc"]}, {"id": "05d2ce63-8627-430c-a596-ed274e9ecc23", "baseline": [[2095, 814], [2516, 799]], "boundary": [[2515, 794], [2509, 782], [2466, 778], [2465, 778], [2464, 778], [2463, 778], [2451, 785], [2094, 792], [2095, 814], [2095, 824], [2515, 814], [2516, 799], [2515, 793], [2515, 794]], "text": null, "base_dir": null, "type": "baselines", "imagename": null, "tags": {"type": "default"}, "split": null, "regions": ["a40d4c8d-a287-44fc-b2bf-42b78aa5d1fc"]}, {"id": "379d2dbb-4599-43be-bfa0-a2f8dc90c436", "baseline": [[2094, 841], [2514, 826]], "boundary": [[2506, 806], [2093, 819], [2094, 841], [2094, 851], [2124, 858], [2125, 858], [2200, 848], [2239, 854], [2240, 854], [2241, 854], [2270, 846], [2279, 853], [2280, 853], [2281, 853], [2282, 853], [2314, 852], [2315, 852], [2317, 852], [2328, 844], [2350, 851], [2351, 851], [2352, 851], [2353, 851], [2354, 851], [2364, 843], [2388, 847], [2389, 847], [2390, 847], [2417, 841], [2513, 844], [2514, 826], [2511, 812], [2506, 806]], "text": null, "base_dir": null, "type": "baselines", "imagename": null, "tags": {"type": "default"}, "split": null, "regions": ["a40d4c8d-a287-44fc-b2bf-42b78aa5d1fc"]}, {"id": "20bbe31e-ad73-4680-849a-96322e29cd59", "baseline": [[2094, 867], [2485, 856]], "boundary": [[2094, 867], [2094, 878], [2366, 876], [2406, 870], [2444, 874], [2445, 874], [2485, 866], [2485, 856], [2482, 834], [2093, 846], [2094, 867]], "text": null, "base_dir": null, "type": "baselines", "imagename": null, "tags": {"type": "default"}, "split": null, "regions": ["a40d4c8d-a287-44fc-b2bf-42b78aa5d1fc"]}, {"id": "228f2c2d-c3d2-4d36-a715-91c3b592036f", "baseline": [[2097, 896], [2492, 884]], "boundary": [[2097, 896], [2097, 913], [2200, 916], [2201, 916], [2202, 916], [2227, 905], [2235, 912], [2235, 913], [2236, 913], [2237, 913], [2261, 914], [2262, 914], [2263, 914], [2264, 914], [2278, 903], [2400, 909], [2401, 909], [2402, 909], [2403, 909], [2422, 897], [2492, 896], [2492, 884], [2488, 862], [2311, 872], [2288, 867], [2287, 867], [2286, 867], [2272, 873], [2133, 872], [2131, 872], [2096, 878], [2097, 896]], "text": null, "base_dir": null, "type": "baselines", "imagename": null, "tags": {"type": "default"}, "split": null, "regions": ["a40d4c8d-a287-44fc-b2bf-42b78aa5d1fc"]}, {"id": "afad0eb0-a633-484e-859f-fab60e941ed0", "baseline": [[2079, 1000], [2494, 987]], "boundary": [[2488, 973], [2477, 963], [2476, 962], [2472, 962], [2422, 969], [2368, 966], [2366, 966], [2263, 974], [2217, 966], [2216, 966], [2215, 966], [2213, 966], [2206, 973], [2192, 967], [2191, 967], [2190, 967], [2189, 967], [2169, 975], [2155, 968], [2154, 968], [2152, 968], [2078, 974], [2079, 1000], [2079, 1008], [2111, 1015], [2113, 1015], [2211, 1010], [2212, 1010], [2213, 1010], [2213, 1009], [2219, 1005], [2282, 1009], [2283, 1009], [2284, 1009], [2311, 1003], [2494, 1003], [2494, 987], [2493, 976], [2488, 973]], "text": null, "base_dir": null, "type": "baselines", "imagename": null, "tags": {"type": "default"}, "split": null, "regions": ["a40d4c8d-a287-44fc-b2bf-42b78aa5d1fc"]}, {"id": "570a69ba-d0be-49c0-bd8c-d5f8c7ef42af", "baseline": [[2190, 1026], [2483, 1015]], "boundary": [[2190, 1026], [2190, 1039], [2483, 1028], [2483, 1015], [2481, 996], [2403, 991], [2402, 991], [2401, 991], [2400, 991], [2391, 998], [2349, 994], [2348, 994], [2347, 994], [2333, 1000], [2189, 1000], [2190, 1026]], "text": null, "base_dir": null, "type": "baselines", "imagename": null, "tags": {"type": "default"}, "split": null, "regions": ["a40d4c8d-a287-44fc-b2bf-42b78aa5d1fc"]}, {"id": "a2c38c21-909f-4acb-8540-a8c23e9ac639", "baseline": [[2180, 1055], [2485, 1042]], "boundary": [[2180, 1055], [2180, 1061], [2485, 1054], [2485, 1042], [2482, 1019], [2315, 1028], [2261, 1025], [2260, 1025], [2259, 1025], [2258, 1025], [2252, 1030], [2235, 1026], [2233, 1026], [2232, 1026], [2231, 1026], [2203, 1032], [2178, 1028], [2180, 1055]], "text": null, "base_dir": null, "type": "baselines", "imagename": null, "tags": {"type": "default"}, "split": null, "regions": ["a40d4c8d-a287-44fc-b2bf-42b78aa5d1fc"]}, {"id": "932f2812-0777-48b0-badc-0d9e6d41ccab", "baseline": [[2090, 1077], [2488, 1069]], "boundary": [[2090, 1077], [2090, 1093], [2261, 1083], [2351, 1083], [2358, 1089], [2359, 1089], [2360, 1089], [2361, 1089], [2362, 1089], [2386, 1081], [2487, 1083], [2488, 1069], [2484, 1046], [2472, 1051], [2432, 1047], [2431, 1047], [2089, 1058], [2090, 1077]], "text": null, "base_dir": null, "type": "baselines", "imagename": null, "tags": {"type": "default"}, "split": null, "regions": ["a40d4c8d-a287-44fc-b2bf-42b78aa5d1fc"]}, {"id": "0894b2a7-3986-4747-be6f-3204e417ad80", "baseline": [[2096, 1102], [2493, 1092]], "boundary": [[2096, 1102], [2096, 1111], [2492, 1107], [2493, 1092], [2491, 1077], [2404, 1072], [2403, 1072], [2358, 1079], [2318, 1075], [2317, 1075], [2095, 1086], [2096, 1102]], "text": null, "base_dir": null, "type": "baselines", "imagename": null, "tags": {"type": "default"}, "split": null, "regions": ["a40d4c8d-a287-44fc-b2bf-42b78aa5d1fc"]}, {"id": "188df5ac-2943-4428-a1db-1db04779fc8f", "baseline": [[2100, 1129], [2500, 1118]], "boundary": [[2100, 1129], [2100, 1138], [2128, 1143], [2129, 1143], [2130, 1143], [2148, 1138], [2178, 1142], [2179, 1142], [2231, 1134], [2500, 1132], [2500, 1118], [2496, 1100], [2099, 1106], [2100, 1129]], "text": null, "base_dir": null, "type": "baselines", "imagename": null, "tags": {"type": "default"}, "split": null, "regions": ["a40d4c8d-a287-44fc-b2bf-42b78aa5d1fc"]}, {"id": "07c7fd7e-eac4-4a62-b4a4-253eae800c3a", "baseline": [[2098, 1154], [2501, 1146]], "boundary": [[2098, 1154], [2098, 1168], [2400, 1158], [2500, 1160], [2501, 1146], [2498, 1127], [2304, 1126], [2303, 1126], [2196, 1133], [2151, 1129], [2150, 1129], [2149, 1129], [2128, 1134], [2097, 1130], [2098, 1154]], "text": null, "base_dir": null, "type": "baselines", "imagename": null, "tags": {"type": "default"}, "split": null, "regions": ["a40d4c8d-a287-44fc-b2bf-42b78aa5d1fc"]}, {"id": "a54ed5b7-8267-4b8e-b205-90fc2f591429", "baseline": [[2100, 1181], [2504, 1173]], "boundary": [[2100, 1181], [2100, 1192], [2503, 1185], [2504, 1173], [2501, 1151], [2099, 1161], [2100, 1181]], "text": null, "base_dir": null, "type": "baselines", "imagename": null, "tags": {"type": "default"}, "split": null, "regions": ["a40d4c8d-a287-44fc-b2bf-42b78aa5d1fc"]}, {"id": "099a0e98-080c-4365-87e4-51ca177f626a", "baseline": [[2101, 1209], [2493, 1200]], "boundary": [[2101, 1209], [2101, 1220], [2340, 1220], [2340, 1219], [2407, 1212], [2432, 1216], [2433, 1216], [2493, 1209], [2493, 1200], [2491, 1182], [2462, 1177], [2461, 1177], [2460, 1177], [2442, 1182], [2431, 1178], [2430, 1178], [2429, 1178], [2392, 1183], [2350, 1179], [2349, 1179], [2348, 1179], [2347, 1179], [2339, 1185], [2100, 1185], [2101, 1209]], "text": null, "base_dir": null, "type": "baselines", "imagename": null, "tags": {"type": "default"}, "split": null, "regions": ["a40d4c8d-a287-44fc-b2bf-42b78aa5d1fc"]}, {"id": "c2921a0e-f143-4e40-8635-8593352b2a04", "baseline": [[2101, 1233], [2500, 1223]], "boundary": [[2101, 1233], [2101, 1243], [2500, 1238], [2500, 1223], [2496, 1202], [2320, 1212], [2100, 1212], [2101, 1233]], "text": null, "base_dir": null, "type": "baselines", "imagename": null, "tags": {"type": "default"}, "split": null, "regions": ["a40d4c8d-a287-44fc-b2bf-42b78aa5d1fc"]}, {"id": "207ecb20-7823-41c6-8c0d-5a464f4de2b3", "baseline": [[2101, 1260], [2500, 1250]], "boundary": [[2101, 1260], [2101, 1269], [2500, 1263], [2500, 1250], [2496, 1232], [2100, 1236], [2101, 1260]], "text": null, "base_dir": null, "type": "baselines", "imagename": null, "tags": {"type": "default"}, "split": null, "regions": ["a40d4c8d-a287-44fc-b2bf-42b78aa5d1fc"]}, {"id": "7bac2cdd-dafc-42a4-b05c-cf606fe337af", "baseline": [[2101, 1285], [2488, 1273]], "boundary": [[2101, 1285], [2101, 1297], [2488, 1283], [2488, 1273], [2485, 1256], [2100, 1263], [2101, 1285]], "text": null, "base_dir": null, "type": "baselines", "imagename": null, "tags": {"type": "default"}, "split": null, "regions": ["a40d4c8d-a287-44fc-b2bf-42b78aa5d1fc"]}, {"id": "816e2195-8754-4a14-9cbe-ba6f168faf6f", "baseline": [[2103, 1312], [2497, 1297]], "boundary": [[2103, 1312], [2103, 1325], [2497, 1312], [2497, 1297], [2494, 1277], [2101, 1291], [2103, 1312]], "text": null, "base_dir": null, "type": "baselines", "imagename": null, "tags": {"type": "default"}, "split": null, "regions": ["a40d4c8d-a287-44fc-b2bf-42b78aa5d1fc"]}, {"id": "555f62f4-9714-4711-a3f8-adb8d1029dc4", "baseline": [[2103, 1338], [2347, 1328], [2484, 1328]], "boundary": [[2103, 1338], [2103, 1351], [2484, 1335], [2484, 1328], [2482, 1303], [2101, 1316], [2103, 1338]], "text": null, "base_dir": null, "type": "baselines", "imagename": null, "tags": {"type": "default"}, "split": null, "regions": ["a40d4c8d-a287-44fc-b2bf-42b78aa5d1fc"]}, {"id": "e4d43d93-5f02-4b32-916f-d8ea3372abc9", "baseline": [[2106, 1365], [2488, 1353]], "boundary": [[2106, 1365], [2106, 1380], [2315, 1368], [2487, 1368], [2488, 1353], [2486, 1333], [2349, 1332], [2348, 1332], [2105, 1345], [2106, 1365]], "text": null, "base_dir": null, "type": "baselines", "imagename": null, "tags": {"type": "default"}, "split": null, "regions": ["a40d4c8d-a287-44fc-b2bf-42b78aa5d1fc"]}, {"id": "aa58efc9-392e-41d2-aa35-49fb5438a6ab", "baseline": [[2104, 1393], [2384, 1383], [2497, 1384]], "boundary": [[2104, 1393], [2104, 1402], [2497, 1393], [2497, 1384], [2496, 1364], [2399, 1361], [2398, 1361], [2396, 1361], [2395, 1361], [2388, 1367], [2321, 1368], [2298, 1363], [2297, 1363], [2296, 1363], [2294, 1363], [2274, 1369], [2256, 1364], [2254, 1364], [2253, 1364], [2211, 1372], [2179, 1366], [2178, 1366], [2177, 1366], [2176, 1366], [2167, 1373], [2120, 1368], [2119, 1368], [2118, 1368], [2103, 1374], [2104, 1393]], "text": null, "base_dir": null, "type": "baselines", "imagename": null, "tags": {"type": "default"}, "split": null, "regions": ["a40d4c8d-a287-44fc-b2bf-42b78aa5d1fc"]}, {"id": "6b4c8957-3e6d-4792-a64e-7771d694b9c0", "baseline": [[2104, 1416], [2493, 1408]], "boundary": [[2104, 1416], [2104, 1425], [2157, 1430], [2158, 1430], [2159, 1430], [2175, 1425], [2213, 1429], [2215, 1429], [2493, 1418], [2493, 1408], [2490, 1388], [2103, 1394], [2104, 1416]], "text": null, "base_dir": null, "type": "baselines", "imagename": null, "tags": {"type": "default"}, "split": null, "regions": ["a40d4c8d-a287-44fc-b2bf-42b78aa5d1fc"]}, {"id": "9992282e-1c9c-49c0-80fc-15eddbe54556", "baseline": [[2100, 1443], [2490, 1435]], "boundary": [[2100, 1443], [2100, 1454], [2490, 1447], [2490, 1435], [2486, 1415], [2099, 1419], [2100, 1443]], "text": null, "base_dir": null, "type": "baselines", "imagename": null, "tags": {"type": "default"}, "split": null, "regions": ["a40d4c8d-a287-44fc-b2bf-42b78aa5d1fc"]}, {"id": "c88b8d4b-a496-490a-8ace-d810e47ef2f4", "baseline": [[2103, 1469], [2495, 1461]], "boundary": [[2103, 1469], [2103, 1479], [2494, 1471], [2495, 1461], [2492, 1441], [2101, 1449], [2103, 1469]], "text": null, "base_dir": null, "type": "baselines", "imagename": null, "tags": {"type": "default"}, "split": null, "regions": ["a40d4c8d-a287-44fc-b2bf-42b78aa5d1fc"]}, {"id": "7145f24d-b3b4-4f45-8f9f-23c2497a87e7", "baseline": [[2101, 1494], [2495, 1485]], "boundary": [[2101, 1494], [2101, 1509], [2215, 1500], [2236, 1506], [2237, 1506], [2238, 1506], [2239, 1506], [2240, 1506], [2251, 1499], [2342, 1504], [2343, 1504], [2344, 1504], [2372, 1497], [2442, 1501], [2443, 1501], [2495, 1495], [2495, 1485], [2492, 1463], [2100, 1472], [2101, 1494]], "text": null, "base_dir": null, "type": "baselines", "imagename": null, "tags": {"type": "default"}, "split": null, "regions": ["a40d4c8d-a287-44fc-b2bf-42b78aa5d1fc"]}, {"id": "ac6f8984-cc2c-4ccf-94b1-6b2b725b6ce4", "baseline": [[2101, 1519], [2500, 1511]], "boundary": [[2101, 1519], [2101, 1533], [2320, 1535], [2321, 1535], [2322, 1535], [2343, 1527], [2401, 1532], [2402, 1532], [2403, 1532], [2422, 1526], [2497, 1531], [2500, 1511], [2496, 1490], [2100, 1500], [2101, 1519]], "text": null, "base_dir": null, "type": "baselines", "imagename": null, "tags": {"type": "default"}, "split": null, "regions": ["a40d4c8d-a287-44fc-b2bf-42b78aa5d1fc"]}, {"id": "43675a5e-8817-44b8-9dbe-93ea5a6a1a71", "baseline": [[2148, 1538], [2159, 1537]], "boundary": [[2148, 1538], [2154, 1601], [2164, 1603], [2159, 1537], [2156, 1522], [2146, 1523], [2148, 1538]], "text": null, "base_dir": null, "type": "baselines", "imagename": null, "tags": {"type": "default"}, "split": null, "regions": ["a40d4c8d-a287-44fc-b2bf-42b78aa5d1fc"]}, {"id": "db5a2597-14e0-4a72-a6ab-cd9c491853ba", "baseline": [[1547, 1389], [1567, 1392]], "boundary": [[1558, 1380], [1558, 1376], [1548, 1375], [1547, 1389], [1544, 1418], [1563, 1421], [1567, 1392], [1566, 1389], [1558, 1380]], "text": null, "base_dir": null, "type": "baselines", "imagename": null, "tags": {"type": "default"}, "split": null, "regions": ["26467e63-53cc-43ca-a70d-cea8a1ecf60d"]}, {"id": "a720d7d2-4679-4aa8-be4b-0e2b5576031a", "baseline": [[1563, 1478], [1563, 1472]], "boundary": [[1555, 1478], [1563, 1478], [1582, 1478], [1583, 1472], [1563, 1472], [1553, 1472], [1555, 1478]], "text": null, "base_dir": null, "type": "baselines", "imagename": null, "tags": {"type": "default"}, "split": null, "regions": ["26467e63-53cc-43ca-a70d-cea8a1ecf60d"]}], "regions": {"text": [{"id": "643af036-d977-4b38-87fd-2eb6fbd523e3", "boundary": [[424, 939], [424, 947], [421, 947], [421, 939], [424, 939]], "imagename": null, "tags": {"type": "text"}}, {"id": "17e45a62-26eb-4227-b064-32400bbf2dbb", "boundary": [[885, 199], [1320, 221], [1351, 239], [1342, 442], [1355, 601], [1342, 694], [1360, 938], [1338, 1197], [1351, 1245], [1347, 1537], [1315, 1550], [962, 1559], [872, 1581], [814, 1563], [589, 1559], [531, 1590], [430, 1590], [407, 1529], [439, 1519], [439, 1298], [456, 1267], [443, 1257], [447, 1183], [424, 1160], [416, 1173], [407, 1151], [403, 984], [439, 969], [443, 929], [443, 243], [456, 226], [850, 226], [885, 199]], "imagename": null, "tags": {"type": "text"}}, {"id": "92cfcdef-4237-47ac-b076-8caf59da2a22", "boundary": [[415, 1178], [412, 1178], [412, 1174], [415, 1174], [415, 1178]], "imagename": null, "tags": {"type": "text"}}, {"id": "15ea1bb0-cf94-4510-855f-230e20d8f771", "boundary": [[1558, 1361], [1563, 1361], [1563, 1368], [1555, 1368], [1558, 1361]], "imagename": null, "tags": {"type": "text"}}, {"id": "4c21b98e-f459-4848-8d2f-f7d9578f020b", "boundary": [[1558, 1210], [1567, 1210], [1567, 1213], [1555, 1213], [1558, 1210]], "imagename": null, "tags": {"type": "text"}}, {"id": "26467e63-53cc-43ca-a70d-cea8a1ecf60d", "boundary": [[1558, 1378], [1576, 1400], [1558, 1430], [1580, 1445], [1563, 1492], [1542, 1453], [1558, 1378]], "imagename": null, "tags": {"type": "text"}}, {"id": "8e9451d9-3a70-4814-ae29-a46f2cf034ba", "boundary": [[1598, 1210], [1598, 1213], [1595, 1213], [1595, 1210], [1598, 1210]], "imagename": null, "tags": {"type": "text"}}, {"id": "6e0f2d14-ea85-4cd9-a48f-8fbb32898015", "boundary": [[1997, 1569], [2011, 1569], [2011, 1572], [1994, 1572], [1997, 1569]], "imagename": null, "tags": {"type": "text"}}, {"id": "a40d4c8d-a287-44fc-b2bf-42b78aa5d1fc", "boundary": [[2050, 190], [2498, 221], [2512, 372], [2503, 761], [2521, 784], [2503, 863], [2525, 912], [2201, 929], [2109, 929], [2087, 912], [2087, 780], [2078, 735], [2052, 725], [2047, 699], [2052, 563], [2078, 553], [2083, 530], [2083, 407], [2078, 367], [2043, 362], [2019, 385], [2015, 545], [2033, 718], [2019, 837], [2033, 1009], [2019, 1062], [2033, 1112], [2037, 1501], [2056, 1497], [2056, 1454], [2068, 1454], [2059, 1492], [2078, 1497], [2096, 1435], [2096, 1197], [2074, 1134], [2047, 1111], [2074, 1054], [2052, 988], [2105, 953], [2476, 962], [2498, 979], [2507, 1103], [2507, 1515], [2476, 1532], [2185, 1537], [2011, 1563], [1892, 1550], [1829, 1581], [1564, 1577], [1568, 1547], [1604, 1546], [1613, 1506], [1604, 1205], [1617, 1188], [1613, 1130], [1550, 1120], [1555, 1028], [1568, 1019], [1546, 1010], [1608, 903], [1608, 709], [1595, 669], [1519, 592], [1519, 416], [1542, 384], [1528, 371], [1533, 234], [1582, 203], [1807, 217], [2006, 208], [2050, 190]], "imagename": null, "tags": {"type": "text"}}]}, "line_orders": []}