{"type": "baselines", "imagename": "D:\\Users\\kju10\\Documents\\LMU-STATISTICS & DATA SCIENCE MASTER\\SS2026\\Thesis\\OCC_HTR\\data\\raw\\original_manuscript\\reproduction14453_100\\64 - f. 059v - 060.jpg", "text_direction": "horizontal-lr", "script_detection": false, "lines": [{"id": "c20757f0-7df9-4b65-9e18-1a277bab007e", "baseline": [[454, 239], [861, 233]], "boundary": [[852, 217], [841, 217], [830, 217], [819, 217], [808, 217], [797, 217], [786, 217], [774, 217], [763, 217], [752, 217], [741, 217], [730, 217], [719, 217], [708, 217], [697, 217], [686, 217], [675, 217], [664, 217], [652, 217], [641, 217], [630, 217], [619, 217], [608, 217], [597, 217], [586, 217], [575, 217], [564, 217], [553, 217], [542, 217], [532, 217], [528, 219], [475, 219], [464, 220], [456, 228], [454, 239], [454, 250], [860, 244], [861, 233], [859, 217], [852, 217]], "text": null, "base_dir": null, "type": "baselines", "imagename": null, "tags": {"type": "default"}, "split": null, "regions": ["2f180ab0-a8d5-4974-a6e0-518278a0a9e5"]}, {"id": "9693182b-7e6b-4d28-9577-95978377e961", "baseline": [[457, 318], [851, 313]], "boundary": [[844, 307], [833, 297], [822, 297], [811, 297], [800, 297], [789, 297], [778, 297], [767, 297], [756, 297], [745, 297], [733, 297], [722, 297], [711, 297], [700, 297], [689, 297], [678, 297], [667, 297], [656, 297], [646, 297], [645, 298], [621, 297], [611, 297], [600, 297], [589, 297], [578, 297], [567, 297], [556, 297], [545, 297], [534, 297], [523, 297], [512, 297], [505, 297], [465, 299], [457, 309], [457, 318], [457, 328], [850, 323], [851, 313], [850, 312], [844, 307]], "text": null, "base_dir": null, "type": "baselines", "imagename": null, "tags": {"type": "default"}, "split": null, "regions": ["e0625826-88ea-4e95-bcd6-30acc2df7de5"]}, {"id": "c0c00e3a-1ed4-4ef4-8d58-d9815a175b85", "baseline": [[456, 345], [863, 338]], "boundary": [[858, 320], [455, 326], [456, 345], [456, 356], [863, 346], [863, 338], [860, 322], [858, 320]], "text": null, "base_dir": null, "type": "baselines", "imagename": null, "tags": {"type": "default"}, "split": null, "regions": ["e0625826-88ea-4e95-bcd6-30acc2df7de5"]}, {"id": "feb6dea0-52c2-4636-b5b1-211a305df679", "baseline": [[457, 372], [863, 367]], "boundary": [[457, 372], [457, 386], [862, 381], [863, 367], [861, 351], [557, 348], [556, 348], [456, 354], [457, 372]], "text": null, "base_dir": null, "type": "baselines", "imagename": null, "tags": {"type": "default"}, "split": null, "regions": ["e0625826-88ea-4e95-bcd6-30acc2df7de5"]}, {"id": "2a1a20d3-94aa-4d42-8245-0e502fb092b5", "baseline": [[457, 397], [870, 393]], "boundary": [[457, 397], [457, 412], [869, 404], [870, 393], [868, 377], [456, 377], [457, 397]], "text": null, "base_dir": null, "type": "baselines", "imagename": null, "tags": {"type": "default"}, "split": null, "regions": ["e0625826-88ea-4e95-bcd6-30acc2df7de5"]}, {"id": "68540639-a07e-4a46-88cb-ba93691eca63", "baseline": [[458, 425], [882, 420]], "boundary": [[879, 415], [872, 402], [796, 397], [794, 397], [793, 397], [792, 397], [786, 403], [710, 399], [709, 399], [708, 399], [685, 404], [634, 400], [633, 400], [457, 405], [458, 425], [458, 434], [796, 436], [797, 436], [882, 430], [882, 420], [880, 415], [879, 415]], "text": null, "base_dir": null, "type": "baselines", "imagename": null, "tags": {"type": "default"}, "split": null, "regions": ["e0625826-88ea-4e95-bcd6-30acc2df7de5"]}, {"id": "31e3f914-7f19-4c4e-8ddf-5eb57b5930df", "baseline": [[457, 452], [858, 447]], "boundary": [[457, 452], [457, 462], [858, 459], [858, 447], [855, 430], [672, 425], [671, 425], [670, 425], [651, 431], [579, 426], [578, 426], [456, 433], [457, 452]], "text": null, "base_dir": null, "type": "baselines", "imagename": null, "tags": {"type": "default"}, "split": null, "regions": ["e0625826-88ea-4e95-bcd6-30acc2df7de5"]}, {"id": "1112faa8-e6cf-4afd-b15d-8ff1bbfee850", "baseline": [[457, 478], [855, 475]], "boundary": [[457, 478], [457, 487], [854, 484], [855, 475], [852, 453], [456, 458], [457, 478]], "text": null, "base_dir": null, "type": "baselines", "imagename": null, "tags": {"type": "default"}, "split": null, "regions": ["e0625826-88ea-4e95-bcd6-30acc2df7de5"]}, {"id": "2e5863f4-e6b2-470c-828b-6050413665c1", "baseline": [[455, 505], [861, 500]], "boundary": [[455, 505], [455, 514], [861, 510], [861, 500], [859, 482], [454, 479], [455, 505]], "text": null, "base_dir": null, "type": "baselines", "imagename": null, "tags": {"type": "default"}, "split": null, "regions": ["e0625826-88ea-4e95-bcd6-30acc2df7de5"]}, {"id": "6f355978-0af6-4cd1-81a7-4f7c7e6b8f85", "baseline": [[458, 529], [861, 527]], "boundary": [[457, 525], [458, 529], [458, 544], [860, 537], [861, 527], [858, 512], [464, 513], [457, 525]], "text": null, "base_dir": null, "type": "baselines", "imagename": null, "tags": {"type": "default"}, "split": null, "regions": ["e0625826-88ea-4e95-bcd6-30acc2df7de5"]}, {"id": "53a99587-a688-4a72-a996-4ade47dc38f9", "baseline": [[458, 554], [868, 549]], "boundary": [[457, 545], [458, 554], [458, 565], [868, 564], [868, 549], [864, 535], [461, 538], [457, 545]], "text": null, "base_dir": null, "type": "baselines", "imagename": null, "tags": {"type": "default"}, "split": null, "regions": ["e0625826-88ea-4e95-bcd6-30acc2df7de5"]}, {"id": "f312d0ed-b017-46fd-9b7b-b9d0ad962fd3", "baseline": [[458, 580], [855, 576]], "boundary": [[457, 564], [458, 580], [458, 591], [854, 587], [855, 576], [852, 558], [457, 563], [457, 564]], "text": null, "base_dir": null, "type": "baselines", "imagename": null, "tags": {"type": "default"}, "split": null, "regions": ["e0625826-88ea-4e95-bcd6-30acc2df7de5"]}, {"id": "0ee08029-a871-4e09-afa6-0cbff375750d", "baseline": [[457, 610], [861, 604]], "boundary": [[457, 610], [457, 621], [860, 615], [861, 604], [858, 587], [456, 590], [457, 610]], "text": null, "base_dir": null, "type": "baselines", "imagename": null, "tags": {"type": "default"}, "split": null, "regions": ["e0625826-88ea-4e95-bcd6-30acc2df7de5"]}, {"id": "5c4e363f-cccd-402b-aca2-d51d0dbd0e2b", "baseline": [[458, 637], [872, 631]], "boundary": [[458, 637], [458, 645], [872, 642], [872, 631], [869, 609], [457, 614], [458, 637]], "text": null, "base_dir": null, "type": "baselines", "imagename": null, "tags": {"type": "default"}, "split": null, "regions": ["e0625826-88ea-4e95-bcd6-30acc2df7de5"]}, {"id": "bcaac833-5886-46c7-9de1-1c0603b80a15", "baseline": [[458, 665], [855, 657]], "boundary": [[458, 665], [458, 674], [793, 673], [794, 673], [796, 673], [802, 667], [855, 666], [855, 657], [852, 636], [457, 645], [458, 665]], "text": null, "base_dir": null, "type": "baselines", "imagename": null, "tags": {"type": "default"}, "split": null, "regions": ["e0625826-88ea-4e95-bcd6-30acc2df7de5"]}, {"id": "6d8c001e-e12f-4870-845a-ce050034f3a1", "baseline": [[460, 691], [872, 683]], "boundary": [[460, 691], [460, 701], [871, 694], [872, 683], [869, 667], [458, 671], [460, 691]], "text": null, "base_dir": null, "type": "baselines", "imagename": null, "tags": {"type": "default"}, "split": null, "regions": ["e0625826-88ea-4e95-bcd6-30acc2df7de5"]}, {"id": "63ca4dfa-621c-45dd-a6f0-1e7328868f97", "baseline": [[461, 717], [868, 710]], "boundary": [[461, 717], [461, 727], [868, 718], [868, 710], [865, 694], [527, 693], [526, 693], [460, 700], [461, 717]], "text": null, "base_dir": null, "type": "baselines", "imagename": null, "tags": {"type": "default"}, "split": null, "regions": ["e0625826-88ea-4e95-bcd6-30acc2df7de5"]}, {"id": "0dd7c1b9-fc12-4c45-8001-06e58dc7ca80", "baseline": [[461, 743], [864, 738]], "boundary": [[461, 743], [461, 756], [863, 745], [864, 738], [861, 713], [460, 724], [461, 743]], "text": null, "base_dir": null, "type": "baselines", "imagename": null, "tags": {"type": "default"}, "split": null, "regions": ["e0625826-88ea-4e95-bcd6-30acc2df7de5"]}, {"id": "5b60a0c1-2ebc-409b-8c40-b6c73066be37", "baseline": [[460, 766], [869, 763]], "boundary": [[460, 766], [460, 779], [869, 772], [869, 763], [865, 741], [458, 748], [460, 766]], "text": null, "base_dir": null, "type": "baselines", "imagename": null, "tags": {"type": "default"}, "split": null, "regions": ["e0625826-88ea-4e95-bcd6-30acc2df7de5"]}, {"id": "aa26ce7d-327c-4e03-a23e-93cc7d5cf845", "baseline": [[462, 795], [863, 789]], "boundary": [[462, 795], [462, 803], [862, 800], [863, 789], [860, 766], [679, 772], [669, 766], [668, 766], [667, 766], [666, 766], [665, 766], [664, 766], [652, 773], [547, 769], [546, 769], [461, 776], [462, 795]], "text": null, "base_dir": null, "type": "baselines", "imagename": null, "tags": {"type": "default"}, "split": null, "regions": ["e0625826-88ea-4e95-bcd6-30acc2df7de5"]}, {"id": "ce6e97c9-ee4a-4bcb-9396-50b941bd5090", "baseline": [[462, 820], [876, 814]], "boundary": [[462, 820], [462, 833], [875, 825], [876, 814], [873, 795], [461, 795], [462, 820]], "text": null, "base_dir": null, "type": "baselines", "imagename": null, "tags": {"type": "default"}, "split": null, "regions": ["e0625826-88ea-4e95-bcd6-30acc2df7de5"]}, {"id": "b34925c7-dd63-4224-8972-2b2d9b670371", "baseline": [[462, 845], [871, 842]], "boundary": [[462, 845], [462, 855], [869, 856], [871, 842], [868, 820], [461, 824], [462, 845]], "text": null, "base_dir": null, "type": "baselines", "imagename": null, "tags": {"type": "default"}, "split": null, "regions": ["e0625826-88ea-4e95-bcd6-30acc2df7de5"]}, {"id": "eea9fa95-6210-467d-812c-d204d8eb7e4e", "baseline": [[462, 872], [870, 865]], "boundary": [[462, 872], [462, 883], [487, 881], [496, 887], [497, 887], [498, 887], [500, 888], [529, 888], [529, 887], [600, 878], [705, 884], [706, 884], [762, 877], [800, 883], [801, 883], [847, 876], [869, 881], [870, 865], [868, 850], [749, 845], [748, 845], [461, 854], [462, 872]], "text": null, "base_dir": null, "type": "baselines", "imagename": null, "tags": {"type": "default"}, "split": null, "regions": ["e0625826-88ea-4e95-bcd6-30acc2df7de5"]}, {"id": "df05f044-44d7-4403-9a2d-adc8f4b81624", "baseline": [[464, 899], [865, 892]], "boundary": [[464, 899], [464, 915], [525, 908], [577, 914], [578, 914], [631, 913], [633, 913], [634, 913], [644, 906], [865, 906], [865, 892], [862, 876], [798, 876], [776, 870], [774, 870], [773, 870], [772, 870], [758, 876], [709, 872], [708, 872], [707, 872], [685, 877], [635, 872], [634, 872], [589, 873], [588, 873], [574, 881], [541, 874], [539, 874], [538, 874], [537, 874], [529, 882], [463, 883], [464, 899]], "text": null, "base_dir": null, "type": "baselines", "imagename": null, "tags": {"type": "default"}, "split": null, "regions": ["e0625826-88ea-4e95-bcd6-30acc2df7de5"]}, {"id": "fa362f61-eda0-48e7-8fd9-874688143ee1", "baseline": [[464, 924], [861, 921]], "boundary": [[464, 924], [464, 939], [619, 933], [719, 938], [720, 938], [721, 938], [737, 932], [822, 937], [823, 937], [860, 931], [861, 921], [859, 907], [727, 899], [726, 899], [666, 907], [637, 901], [636, 901], [635, 901], [634, 901], [633, 901], [633, 902], [626, 908], [463, 909], [464, 924]], "text": null, "base_dir": null, "type": "baselines", "imagename": null, "tags": {"type": "default"}, "split": null, "regions": ["e0625826-88ea-4e95-bcd6-30acc2df7de5"]}, {"id": "2fdc5de3-b468-4cee-b682-f4aa51018418", "baseline": [[464, 952], [870, 946]], "boundary": [[464, 952], [464, 959], [847, 960], [848, 960], [849, 960], [870, 954], [870, 946], [868, 931], [808, 931], [801, 924], [800, 924], [799, 924], [798, 924], [754, 929], [726, 925], [725, 925], [723, 925], [705, 932], [544, 927], [543, 927], [463, 935], [464, 952]], "text": null, "base_dir": null, "type": "baselines", "imagename": null, "tags": {"type": "default"}, "split": null, "regions": ["e0625826-88ea-4e95-bcd6-30acc2df7de5"]}, {"id": "240be366-f66e-4905-b577-ba7790bcceb3", "baseline": [[463, 978], [865, 973]], "boundary": [[463, 978], [463, 986], [598, 990], [599, 990], [705, 983], [773, 988], [774, 988], [865, 979], [865, 973], [863, 957], [794, 952], [793, 952], [792, 952], [791, 952], [781, 958], [748, 953], [747, 953], [589, 960], [566, 955], [565, 955], [564, 955], [563, 955], [562, 955], [555, 962], [484, 962], [462, 956], [463, 978]], "text": null, "base_dir": null, "type": "baselines", "imagename": null, "tags": {"type": "default"}, "split": null, "regions": ["e0625826-88ea-4e95-bcd6-30acc2df7de5"]}, {"id": "15472d41-de83-4eb4-b6d6-cb7aadce70f0", "baseline": [[465, 1004], [873, 999]], "boundary": [[465, 1004], [465, 1015], [872, 1009], [873, 999], [871, 984], [670, 978], [669, 978], [636, 985], [471, 981], [470, 981], [468, 981], [467, 981], [467, 983], [464, 985], [465, 1004]], "text": null, "base_dir": null, "type": "baselines", "imagename": null, "tags": {"type": "default"}, "split": null, "regions": ["e0625826-88ea-4e95-bcd6-30acc2df7de5"]}, {"id": "60ae3e32-f655-4754-95f7-2ff18b189bd0", "baseline": [[464, 1027], [861, 1024]], "boundary": [[464, 1027], [464, 1042], [501, 1036], [565, 1041], [566, 1041], [596, 1036], [706, 1040], [707, 1040], [708, 1040], [719, 1035], [791, 1039], [792, 1039], [860, 1032], [861, 1024], [858, 1009], [463, 1011], [464, 1027]], "text": null, "base_dir": null, "type": "baselines", "imagename": null, "tags": {"type": "default"}, "split": null, "regions": ["e0625826-88ea-4e95-bcd6-30acc2df7de5"]}, {"id": "93320d27-2174-41fd-8e30-0862dcf82cf6", "baseline": [[466, 1055], [871, 1048]], "boundary": [[466, 1055], [466, 1067], [871, 1062], [871, 1048], [868, 1027], [797, 1034], [600, 1030], [599, 1030], [598, 1030], [597, 1030], [586, 1037], [465, 1037], [466, 1055]], "text": null, "base_dir": null, "type": "baselines", "imagename": null, "tags": {"type": "default"}, "split": null, "regions": ["e0625826-88ea-4e95-bcd6-30acc2df7de5"]}, {"id": "4987a7ee-2d11-4e25-b7ee-0598345bf3f3", "baseline": [[464, 1081], [868, 1077]], "boundary": [[464, 1081], [464, 1092], [868, 1087], [868, 1077], [865, 1061], [766, 1055], [764, 1055], [722, 1062], [463, 1062], [464, 1081]], "text": null, "base_dir": null, "type": "baselines", "imagename": null, "tags": {"type": "default"}, "split": null, "regions": ["e0625826-88ea-4e95-bcd6-30acc2df7de5"]}, {"id": "9748eb8f-e6f0-4b1f-8852-394ea5c901b9", "baseline": [[467, 1109], [871, 1102]], "boundary": [[467, 1109], [467, 1123], [870, 1112], [871, 1102], [868, 1081], [466, 1091], [467, 1109]], "text": null, "base_dir": null, "type": "baselines", "imagename": null, "tags": {"type": "default"}, "split": null, "regions": ["e0625826-88ea-4e95-bcd6-30acc2df7de5"]}, {"id": "c34c3f04-8f5b-4bc8-8fb7-3820a69c6be8", "baseline": [[467, 1134], [878, 1131]], "boundary": [[467, 1134], [467, 1144], [567, 1149], [568, 1149], [621, 1142], [691, 1148], [692, 1148], [876, 1140], [878, 1131], [874, 1109], [466, 1114], [467, 1134]], "text": null, "base_dir": null, "type": "baselines", "imagename": null, "tags": {"type": "default"}, "split": null, "regions": ["e0625826-88ea-4e95-bcd6-30acc2df7de5"]}, {"id": "65a16391-b340-4132-b754-69f2d630684d", "baseline": [[467, 1162], [859, 1157]], "boundary": [[467, 1162], [467, 1171], [858, 1165], [859, 1157], [856, 1141], [779, 1134], [778, 1134], [669, 1142], [664, 1138], [664, 1137], [662, 1137], [661, 1137], [623, 1137], [621, 1137], [620, 1137], [605, 1143], [476, 1140], [475, 1140], [474, 1140], [473, 1140], [466, 1143], [467, 1162]], "text": null, "base_dir": null, "type": "baselines", "imagename": null, "tags": {"type": "default"}, "split": null, "regions": ["e0625826-88ea-4e95-bcd6-30acc2df7de5"]}, {"id": "0dad9685-f232-4d7b-91d8-ef122d081801", "baseline": [[468, 1187], [863, 1183]], "boundary": [[468, 1187], [468, 1198], [861, 1199], [863, 1183], [860, 1165], [467, 1168], [468, 1187]], "text": null, "base_dir": null, "type": "baselines", "imagename": null, "tags": {"type": "default"}, "split": null, "regions": ["e0625826-88ea-4e95-bcd6-30acc2df7de5"]}, {"id": "7f0d2630-dc82-4f33-ac26-e943b41f30da", "baseline": [[468, 1215], [865, 1210]], "boundary": [[468, 1215], [468, 1224], [545, 1230], [546, 1230], [547, 1230], [548, 1230], [548, 1229], [555, 1223], [619, 1229], [620, 1229], [621, 1229], [623, 1229], [630, 1222], [684, 1228], [685, 1228], [686, 1228], [708, 1221], [749, 1226], [750, 1226], [864, 1220], [865, 1210], [863, 1193], [467, 1192], [468, 1215]], "text": null, "base_dir": null, "type": "baselines", "imagename": null, "tags": {"type": "default"}, "split": null, "regions": ["e0625826-88ea-4e95-bcd6-30acc2df7de5"]}, {"id": "f277824f-7302-4402-ae02-6897820b18ae", "baseline": [[470, 1241], [869, 1236]], "boundary": [[470, 1241], [470, 1250], [767, 1252], [768, 1252], [869, 1244], [869, 1236], [865, 1218], [468, 1222], [470, 1241]], "text": null, "base_dir": null, "type": "baselines", "imagename": null, "tags": {"type": "default"}, "split": null, "regions": ["e0625826-88ea-4e95-bcd6-30acc2df7de5"]}, {"id": "be05e4c5-5533-4626-854c-7b619de98747", "baseline": [[471, 1267], [866, 1264]], "boundary": [[471, 1267], [471, 1277], [865, 1274], [866, 1264], [864, 1247], [470, 1245], [471, 1267]], "text": null, "base_dir": null, "type": "baselines", "imagename": null, "tags": {"type": "default"}, "split": null, "regions": ["e0625826-88ea-4e95-bcd6-30acc2df7de5"]}, {"id": "605c05c8-2d35-4733-8f3f-45fa267f0e39", "baseline": [[472, 1294], [872, 1291]], "boundary": [[472, 1294], [472, 1306], [872, 1303], [872, 1291], [870, 1274], [757, 1267], [756, 1267], [754, 1267], [736, 1274], [515, 1270], [514, 1270], [471, 1276], [472, 1294]], "text": null, "base_dir": null, "type": "baselines", "imagename": null, "tags": {"type": "default"}, "split": null, "regions": ["e0625826-88ea-4e95-bcd6-30acc2df7de5"]}, {"id": "bc4f8833-7402-461a-af4e-51d8a4341418", "baseline": [[472, 1321], [868, 1316]], "boundary": [[472, 1321], [472, 1330], [866, 1325], [868, 1316], [865, 1297], [772, 1293], [771, 1293], [770, 1293], [769, 1293], [760, 1301], [694, 1301], [669, 1294], [668, 1294], [667, 1294], [666, 1294], [665, 1294], [665, 1295], [664, 1295], [659, 1302], [625, 1302], [594, 1295], [593, 1295], [544, 1302], [512, 1296], [511, 1296], [471, 1303], [472, 1321]], "text": null, "base_dir": null, "type": "baselines", "imagename": null, "tags": {"type": "default"}, "split": null, "regions": ["e0625826-88ea-4e95-bcd6-30acc2df7de5"]}, {"id": "14e5bc4c-0e04-4ab1-95ef-7b32fe23d08e", "baseline": [[472, 1347], [868, 1343]], "boundary": [[472, 1347], [472, 1358], [855, 1358], [855, 1357], [856, 1357], [868, 1351], [868, 1343], [865, 1326], [471, 1325], [472, 1347]], "text": null, "base_dir": null, "type": "baselines", "imagename": null, "tags": {"type": "default"}, "split": null, "regions": ["e0625826-88ea-4e95-bcd6-30acc2df7de5"]}, {"id": "d454ffbf-eff3-42ff-83c1-966d9556fdbe", "baseline": [[474, 1374], [873, 1371]], "boundary": [[474, 1374], [474, 1383], [872, 1380], [873, 1371], [871, 1353], [473, 1351], [474, 1374]], "text": null, "base_dir": null, "type": "baselines", "imagename": null, "tags": {"type": "default"}, "split": null, "regions": ["e0625826-88ea-4e95-bcd6-30acc2df7de5"]}, {"id": "65d1bcc5-e63d-4d48-a50f-79b3e8f68458", "baseline": [[474, 1399], [872, 1396]], "boundary": [[474, 1399], [474, 1410], [871, 1405], [872, 1396], [869, 1374], [699, 1379], [611, 1375], [610, 1375], [609, 1375], [596, 1380], [492, 1376], [491, 1376], [490, 1376], [473, 1382], [474, 1399]], "text": null, "base_dir": null, "type": "baselines", "imagename": null, "tags": {"type": "default"}, "split": null, "regions": ["e0625826-88ea-4e95-bcd6-30acc2df7de5"]}, {"id": "e7135de4-cb2a-485d-9cf8-0b6cce3316d6", "baseline": [[475, 1424], [884, 1424]], "boundary": [[475, 1424], [475, 1435], [884, 1435], [884, 1424], [883, 1400], [475, 1403], [475, 1424]], "text": null, "base_dir": null, "type": "baselines", "imagename": null, "tags": {"type": "default"}, "split": null, "regions": ["e0625826-88ea-4e95-bcd6-30acc2df7de5"]}, {"id": "ce607da5-30ed-445e-881c-ad66a271dbf5", "baseline": [[475, 1451], [871, 1449]], "boundary": [[475, 1451], [475, 1465], [870, 1459], [871, 1449], [870, 1433], [855, 1426], [854, 1426], [853, 1426], [669, 1433], [487, 1427], [486, 1427], [485, 1427], [484, 1427], [474, 1433], [475, 1451]], "text": null, "base_dir": null, "type": "baselines", "imagename": null, "tags": {"type": "default"}, "split": null, "regions": ["e0625826-88ea-4e95-bcd6-30acc2df7de5"]}, {"id": "5c63318c-ce1e-4668-9bbc-b1bd5b4a06b2", "baseline": [[476, 1478], [879, 1474]], "boundary": [[476, 1478], [476, 1489], [878, 1485], [879, 1474], [876, 1458], [475, 1457], [476, 1478]], "text": null, "base_dir": null, "type": "baselines", "imagename": null, "tags": {"type": "default"}, "split": null, "regions": ["e0625826-88ea-4e95-bcd6-30acc2df7de5"]}, {"id": "4e187b8f-bf58-4269-a7e0-f7999985caca", "baseline": [[476, 1504], [885, 1500]], "boundary": [[476, 1504], [476, 1516], [885, 1509], [885, 1500], [883, 1481], [623, 1481], [621, 1481], [620, 1481], [609, 1487], [490, 1482], [488, 1482], [487, 1482], [475, 1487], [476, 1504]], "text": null, "base_dir": null, "type": "baselines", "imagename": null, "tags": {"type": "default"}, "split": null, "regions": ["e0625826-88ea-4e95-bcd6-30acc2df7de5"]}, {"id": "96c570e7-6838-427b-ae67-c7f28fea847a", "baseline": [[476, 1529], [883, 1523]], "boundary": [[476, 1529], [476, 1551], [511, 1548], [552, 1559], [553, 1559], [554, 1559], [555, 1559], [580, 1550], [587, 1556], [587, 1557], [588, 1557], [589, 1557], [630, 1558], [631, 1558], [668, 1556], [669, 1556], [670, 1556], [686, 1546], [773, 1545], [803, 1554], [804, 1554], [805, 1554], [883, 1553], [883, 1523], [880, 1502], [475, 1511], [476, 1529]], "text": null, "base_dir": null, "type": "baselines", "imagename": null, "tags": {"type": "default"}, "split": null, "regions": ["e0625826-88ea-4e95-bcd6-30acc2df7de5"]}, {"id": "e55c843d-7e92-4c21-96bf-e4ce788ea828", "baseline": [[937, 233], [1343, 228]], "boundary": [[1313, 220], [1302, 220], [1291, 219], [1280, 219], [1269, 219], [1258, 219], [1247, 218], [1236, 218], [1225, 218], [1213, 218], [1202, 218], [1191, 217], [1180, 217], [1169, 217], [1158, 217], [1147, 216], [1136, 216], [1125, 216], [1114, 216], [1103, 216], [1092, 215], [1080, 215], [1069, 215], [1058, 215], [1047, 213], [1036, 213], [1025, 213], [1018, 213], [952, 217], [947, 221], [936, 229], [937, 233], [937, 243], [1342, 238], [1343, 228], [1317, 220], [1313, 220]], "text": null, "base_dir": null, "type": "baselines", "imagename": null, "tags": {"type": "default"}, "split": null, "regions": ["bcd90dbe-70ed-4fa4-bf6f-a731dd55f689"]}, {"id": "9a8dcd07-525b-40c5-9547-981830575e27", "baseline": [[935, 261], [1349, 254]], "boundary": [[935, 261], [936, 277], [949, 271], [992, 275], [993, 275], [994, 275], [1008, 270], [1349, 270], [1349, 254], [1345, 236], [934, 242], [935, 261]], "text": null, "base_dir": null, "type": "baselines", "imagename": null, "tags": {"type": "default"}, "split": null, "regions": ["bcd90dbe-70ed-4fa4-bf6f-a731dd55f689"]}, {"id": "06a2dfc3-f705-4bcf-b24f-21d71d83f2df", "baseline": [[937, 287], [1338, 282]], "boundary": [[937, 287], [937, 299], [1337, 293], [1338, 282], [1334, 264], [936, 269], [937, 287]], "text": null, "base_dir": null, "type": "baselines", "imagename": null, "tags": {"type": "default"}, "split": null, "regions": ["bcd90dbe-70ed-4fa4-bf6f-a731dd55f689"]}, {"id": "132e6418-dbe1-4a5b-9e5f-9b46e401724a", "baseline": [[937, 314], [1345, 309]], "boundary": [[937, 314], [937, 326], [1333, 325], [1334, 325], [1345, 319], [1345, 309], [1342, 292], [936, 294], [937, 314]], "text": null, "base_dir": null, "type": "baselines", "imagename": null, "tags": {"type": "default"}, "split": null, "regions": ["bcd90dbe-70ed-4fa4-bf6f-a731dd55f689"]}, {"id": "b2259158-3bfd-4ed7-ac87-15ec59a16755", "baseline": [[936, 341], [1338, 336]], "boundary": [[936, 341], [936, 351], [1337, 346], [1338, 336], [1334, 320], [935, 323], [936, 341]], "text": null, "base_dir": null, "type": "baselines", "imagename": null, "tags": {"type": "default"}, "split": null, "regions": ["bcd90dbe-70ed-4fa4-bf6f-a731dd55f689"]}, {"id": "227e6482-d66f-42b2-8632-09170e7f1bae", "baseline": [[941, 367], [1366, 363]], "boundary": [[1362, 346], [1048, 344], [1047, 344], [1046, 344], [1021, 351], [985, 345], [984, 345], [940, 352], [941, 367], [941, 385], [967, 380], [1365, 380], [1366, 363], [1364, 348], [1362, 346]], "text": null, "base_dir": null, "type": "baselines", "imagename": null, "tags": {"type": "default"}, "split": null, "regions": ["bcd90dbe-70ed-4fa4-bf6f-a731dd55f689"]}, {"id": "1c34f956-61e1-4bb4-a450-3a5d175c6670", "baseline": [[940, 394], [1333, 391]], "boundary": [[940, 394], [940, 404], [1331, 405], [1333, 391], [1330, 375], [939, 377], [940, 394]], "text": null, "base_dir": null, "type": "baselines", "imagename": null, "tags": {"type": "default"}, "split": null, "regions": ["bcd90dbe-70ed-4fa4-bf6f-a731dd55f689"]}, {"id": "aa773cfd-3689-47ec-877a-7add272b5325", "baseline": [[940, 420], [1355, 417]], "boundary": [[940, 420], [940, 430], [1355, 427], [1355, 417], [1353, 402], [939, 400], [940, 420]], "text": null, "base_dir": null, "type": "baselines", "imagename": null, "tags": {"type": "default"}, "split": null, "regions": ["bcd90dbe-70ed-4fa4-bf6f-a731dd55f689"]}, {"id": "82b4316b-8e55-4aff-8107-4036d9f9fb51", "baseline": [[941, 446], [1353, 444]], "boundary": [[1351, 428], [940, 425], [941, 446], [941, 461], [1352, 455], [1353, 444], [1352, 438], [1351, 428]], "text": null, "base_dir": null, "type": "baselines", "imagename": null, "tags": {"type": "default"}, "split": null, "regions": ["bcd90dbe-70ed-4fa4-bf6f-a731dd55f689"]}, {"id": "a087e5a5-c8a2-4f8d-89b0-b72ec2eea880", "baseline": [[941, 474], [1338, 469]], "boundary": [[941, 474], [941, 485], [1337, 481], [1338, 469], [1335, 453], [940, 453], [941, 474]], "text": null, "base_dir": null, "type": "baselines", "imagename": null, "tags": {"type": "default"}, "split": null, "regions": ["bcd90dbe-70ed-4fa4-bf6f-a731dd55f689"]}, {"id": "bcd61b8f-dc05-4380-ac8b-cf9c56a4099b", "baseline": [[942, 500], [1339, 497]], "boundary": [[942, 500], [942, 509], [1338, 506], [1339, 497], [1337, 481], [941, 481], [942, 500]], "text": null, "base_dir": null, "type": "baselines", "imagename": null, "tags": {"type": "default"}, "split": null, "regions": ["bcd90dbe-70ed-4fa4-bf6f-a731dd55f689"]}, {"id": "d3feb854-6595-4578-8c77-4ce601df5d69", "baseline": [[941, 527], [1351, 523]], "boundary": [[941, 527], [941, 541], [1150, 534], [1349, 537], [1351, 523], [1348, 505], [940, 508], [941, 527]], "text": null, "base_dir": null, "type": "baselines", "imagename": null, "tags": {"type": "default"}, "split": null, "regions": ["bcd90dbe-70ed-4fa4-bf6f-a731dd55f689"]}, {"id": "4130e326-1d92-4114-9850-8a1febca2e9e", "baseline": [[942, 550], [1356, 547]], "boundary": [[942, 550], [942, 565], [1355, 565], [1356, 547], [1353, 533], [941, 535], [942, 550]], "text": null, "base_dir": null, "type": "baselines", "imagename": null, "tags": {"type": "default"}, "split": null, "regions": ["bcd90dbe-70ed-4fa4-bf6f-a731dd55f689"]}, {"id": "ee8891fc-ddba-4208-a766-bf3ab48c58a7", "baseline": [[942, 578], [1361, 575]], "boundary": [[942, 578], [942, 587], [1361, 585], [1361, 575], [1358, 555], [941, 560], [942, 578]], "text": null, "base_dir": null, "type": "baselines", "imagename": null, "tags": {"type": "default"}, "split": null, "regions": ["bcd90dbe-70ed-4fa4-bf6f-a731dd55f689"]}, {"id": "0fd29f86-55c4-4f2d-ad3a-f17adebd0141", "baseline": [[941, 606], [1350, 600]], "boundary": [[941, 606], [941, 615], [1021, 621], [1022, 621], [1023, 621], [1042, 615], [1320, 617], [1321, 617], [1322, 617], [1350, 609], [1350, 600], [1347, 582], [940, 587], [941, 606]], "text": null, "base_dir": null, "type": "baselines", "imagename": null, "tags": {"type": "default"}, "split": null, "regions": ["bcd90dbe-70ed-4fa4-bf6f-a731dd55f689"]}, {"id": "7f2e9e9b-b032-4756-91ba-c5b88c2d0c37", "baseline": [[943, 633], [1343, 627]], "boundary": [[943, 633], [943, 643], [1342, 639], [1343, 627], [1341, 611], [1208, 606], [1207, 606], [1140, 607], [1139, 607], [1123, 614], [1082, 608], [1080, 608], [1079, 608], [1078, 608], [1067, 615], [942, 615], [943, 633]], "text": null, "base_dir": null, "type": "baselines", "imagename": null, "tags": {"type": "default"}, "split": null, "regions": ["bcd90dbe-70ed-4fa4-bf6f-a731dd55f689"]}, {"id": "d25cf8a0-a65b-42fc-b2b8-d5ac62c567d9", "baseline": [[943, 660], [1350, 653]], "boundary": [[943, 660], [943, 670], [1349, 667], [1350, 653], [1348, 638], [1313, 632], [1312, 632], [1211, 639], [942, 639], [943, 660]], "text": null, "base_dir": null, "type": "baselines", "imagename": null, "tags": {"type": "default"}, "split": null, "regions": ["bcd90dbe-70ed-4fa4-bf6f-a731dd55f689"]}, {"id": "0ead9441-c5fc-4ba5-bb2f-2126127f46f7", "baseline": [[945, 686], [1347, 680]], "boundary": [[945, 686], [945, 701], [1345, 690], [1347, 680], [1344, 665], [1267, 659], [1266, 659], [1264, 659], [1263, 659], [1256, 665], [1185, 660], [1184, 660], [1182, 660], [1167, 666], [1127, 661], [1126, 661], [1125, 661], [1101, 667], [1062, 662], [1060, 662], [944, 668], [945, 686]], "text": null, "base_dir": null, "type": "baselines", "imagename": null, "tags": {"type": "default"}, "split": null, "regions": ["bcd90dbe-70ed-4fa4-bf6f-a731dd55f689"]}, {"id": "8ccd5029-3e6c-4c82-97ea-fecfc10e0f6a", "baseline": [[944, 712], [1349, 707]], "boundary": [[944, 712], [944, 722], [1104, 727], [1105, 727], [1348, 717], [1349, 707], [1347, 692], [1273, 686], [1272, 686], [1271, 686], [1270, 686], [1270, 687], [1263, 692], [1203, 687], [1202, 687], [1128, 693], [1114, 688], [1113, 688], [1111, 688], [1110, 688], [1109, 688], [1098, 694], [995, 690], [994, 690], [993, 690], [970, 696], [954, 690], [953, 690], [952, 690], [951, 690], [950, 690], [943, 694], [944, 712]], "text": null, "base_dir": null, "type": "baselines", "imagename": null, "tags": {"type": "default"}, "split": null, "regions": ["bcd90dbe-70ed-4fa4-bf6f-a731dd55f689"]}, {"id": "926d5f2e-7160-4d59-b813-975540db3f97", "baseline": [[945, 740], [1355, 735]], "boundary": [[945, 740], [945, 753], [1355, 750], [1355, 735], [1352, 719], [1213, 720], [1168, 714], [1167, 714], [1124, 721], [1001, 717], [1000, 717], [944, 722], [945, 740]], "text": null, "base_dir": null, "type": "baselines", "imagename": null, "tags": {"type": "default"}, "split": null, "regions": ["bcd90dbe-70ed-4fa4-bf6f-a731dd55f689"]}, {"id": "d20fffd0-a3dc-4e03-83c5-6ea1f64247a0", "baseline": [[946, 765], [1348, 760]], "boundary": [[946, 765], [946, 780], [1347, 776], [1348, 760], [1344, 744], [945, 747], [946, 765]], "text": null, "base_dir": null, "type": "baselines", "imagename": null, "tags": {"type": "default"}, "split": null, "regions": ["bcd90dbe-70ed-4fa4-bf6f-a731dd55f689"]}, {"id": "989bc621-642c-4cd9-879c-930b8877711e", "baseline": [[946, 792], [1353, 786]], "boundary": [[946, 792], [946, 801], [1352, 795], [1353, 786], [1350, 769], [945, 771], [946, 792]], "text": null, "base_dir": null, "type": "baselines", "imagename": null, "tags": {"type": "default"}, "split": null, "regions": ["bcd90dbe-70ed-4fa4-bf6f-a731dd55f689"]}, {"id": "0467d0ad-0795-4e58-af16-869e7146a159", "baseline": [[946, 816], [1360, 810]], "boundary": [[946, 816], [946, 826], [1004, 833], [1005, 833], [1006, 833], [1029, 824], [1110, 824], [1127, 831], [1128, 831], [1129, 831], [1130, 831], [1158, 824], [1165, 830], [1166, 830], [1167, 830], [1168, 830], [1208, 824], [1271, 829], [1272, 829], [1273, 829], [1293, 822], [1323, 827], [1324, 827], [1359, 820], [1360, 810], [1356, 792], [945, 802], [946, 816]], "text": null, "base_dir": null, "type": "baselines", "imagename": null, "tags": {"type": "default"}, "split": null, "regions": ["bcd90dbe-70ed-4fa4-bf6f-a731dd55f689"]}, {"id": "3ec47d45-43a9-43d0-9363-2ef06a6ef28a", "baseline": [[946, 841], [1360, 841]], "boundary": [[946, 841], [946, 857], [1359, 858], [1360, 841], [1359, 821], [946, 824], [946, 841]], "text": null, "base_dir": null, "type": "baselines", "imagename": null, "tags": {"type": "default"}, "split": null, "regions": ["bcd90dbe-70ed-4fa4-bf6f-a731dd55f689"]}, {"id": "25d7e351-b4ce-402c-ad73-784836d5f628", "baseline": [[946, 868], [1340, 865]], "boundary": [[946, 868], [946, 884], [1339, 876], [1340, 865], [1338, 851], [945, 850], [946, 868]], "text": null, "base_dir": null, "type": "baselines", "imagename": null, "tags": {"type": "default"}, "split": null, "regions": ["bcd90dbe-70ed-4fa4-bf6f-a731dd55f689"]}, {"id": "029d032d-ace3-4424-b84a-3023d9efbec9", "baseline": [[947, 897], [1354, 889]], "boundary": [[947, 897], [947, 906], [1294, 907], [1296, 907], [1354, 897], [1354, 889], [1351, 868], [1318, 874], [1304, 868], [1303, 868], [1302, 868], [1301, 868], [1300, 868], [1289, 876], [964, 876], [963, 876], [962, 876], [946, 882], [947, 897]], "text": null, "base_dir": null, "type": "baselines", "imagename": null, "tags": {"type": "default"}, "split": null, "regions": ["bcd90dbe-70ed-4fa4-bf6f-a731dd55f689"]}, {"id": "867f1104-abf9-4223-b314-5cae3d007054", "baseline": [[949, 923], [1360, 918]], "boundary": [[949, 923], [949, 939], [1033, 939], [1033, 938], [1034, 938], [1052, 932], [1100, 932], [1108, 937], [1109, 937], [1110, 937], [1111, 937], [1165, 931], [1359, 934], [1360, 918], [1358, 902], [1308, 896], [1307, 896], [1270, 902], [1262, 896], [1261, 896], [1260, 896], [1259, 896], [1176, 903], [1155, 897], [1154, 897], [1152, 897], [1078, 904], [1050, 898], [1049, 898], [1048, 898], [1047, 898], [1037, 905], [1005, 899], [1004, 899], [947, 906], [949, 923]], "text": null, "base_dir": null, "type": "baselines", "imagename": null, "tags": {"type": "default"}, "split": null, "regions": ["bcd90dbe-70ed-4fa4-bf6f-a731dd55f689"]}, {"id": "48c14ab2-f054-469f-a757-b2b684e31418", "baseline": [[947, 948], [1352, 943]], "boundary": [[947, 948], [947, 957], [1026, 964], [1027, 964], [1028, 964], [1046, 957], [1188, 962], [1189, 962], [1352, 952], [1352, 943], [1350, 928], [1270, 923], [1269, 923], [1268, 923], [1252, 928], [1189, 924], [1188, 924], [946, 931], [947, 948]], "text": null, "base_dir": null, "type": "baselines", "imagename": null, "tags": {"type": "default"}, "split": null, "regions": ["bcd90dbe-70ed-4fa4-bf6f-a731dd55f689"]}, {"id": "11b8a921-b960-4ed6-8cab-3d840ef85206", "baseline": [[949, 974], [1349, 968]], "boundary": [[949, 974], [949, 990], [1054, 983], [1105, 988], [1106, 988], [1107, 988], [1120, 981], [1246, 986], [1247, 986], [1348, 978], [1349, 968], [1347, 955], [1272, 949], [1271, 949], [1270, 949], [1269, 949], [1269, 950], [1263, 956], [947, 956], [949, 974]], "text": null, "base_dir": null, "type": "baselines", "imagename": null, "tags": {"type": "default"}, "split": null, "regions": ["bcd90dbe-70ed-4fa4-bf6f-a731dd55f689"]}, {"id": "3629576f-a556-4fea-a476-eaef22ebd7b3", "baseline": [[949, 1000], [1350, 996]], "boundary": [[949, 1000], [949, 1010], [1349, 1006], [1350, 996], [1347, 974], [1268, 979], [1252, 974], [1251, 974], [1250, 974], [1249, 974], [1236, 980], [1148, 975], [1147, 975], [1146, 975], [1127, 981], [1049, 976], [1048, 976], [1047, 976], [1046, 976], [1038, 983], [947, 984], [949, 1000]], "text": null, "base_dir": null, "type": "baselines", "imagename": null, "tags": {"type": "default"}, "split": null, "regions": ["bcd90dbe-70ed-4fa4-bf6f-a731dd55f689"]}, {"id": "a46b8b8f-e278-4e90-8293-af8eaa3accd9", "baseline": [[951, 1024], [1352, 1019]], "boundary": [[951, 1024], [951, 1036], [1351, 1031], [1352, 1019], [1349, 1005], [950, 1006], [951, 1024]], "text": null, "base_dir": null, "type": "baselines", "imagename": null, "tags": {"type": "default"}, "split": null, "regions": ["bcd90dbe-70ed-4fa4-bf6f-a731dd55f689"]}, {"id": "79ad6abb-2f4b-48cb-afa1-5d7159bb96f7", "baseline": [[951, 1054], [1352, 1046]], "boundary": [[951, 1054], [951, 1061], [1352, 1057], [1352, 1046], [1349, 1030], [950, 1037], [951, 1054]], "text": null, "base_dir": null, "type": "baselines", "imagename": null, "tags": {"type": "default"}, "split": null, "regions": ["bcd90dbe-70ed-4fa4-bf6f-a731dd55f689"]}, {"id": "3b720054-0181-4ea2-b24f-c75703b55304", "baseline": [[951, 1078], [1351, 1073]], "boundary": [[951, 1078], [951, 1087], [1351, 1085], [1351, 1073], [1349, 1056], [1282, 1050], [1281, 1050], [1280, 1050], [1268, 1057], [1178, 1057], [1149, 1051], [1148, 1051], [950, 1059], [951, 1078]], "text": null, "base_dir": null, "type": "baselines", "imagename": null, "tags": {"type": "default"}, "split": null, "regions": ["bcd90dbe-70ed-4fa4-bf6f-a731dd55f689"]}, {"id": "8fe65a89-97be-423f-a198-0b5e10ec2c4a", "baseline": [[951, 1105], [1345, 1098]], "boundary": [[951, 1105], [951, 1117], [1344, 1110], [1345, 1098], [1343, 1080], [1033, 1079], [1032, 1079], [1031, 1079], [1013, 1087], [950, 1081], [951, 1105]], "text": null, "base_dir": null, "type": "baselines", "imagename": null, "tags": {"type": "default"}, "split": null, "regions": ["bcd90dbe-70ed-4fa4-bf6f-a731dd55f689"]}, {"id": "49ff20dc-adb1-4e1f-b890-438602038251", "baseline": [[951, 1133], [1347, 1127]], "boundary": [[951, 1133], [951, 1142], [1345, 1136], [1347, 1127], [1343, 1111], [950, 1113], [951, 1133]], "text": null, "base_dir": null, "type": "baselines", "imagename": null, "tags": {"type": "default"}, "split": null, "regions": ["bcd90dbe-70ed-4fa4-bf6f-a731dd55f689"]}, {"id": "f6a0d97c-f391-4391-83e4-583670f90983", "baseline": [[952, 1160], [1351, 1154]], "boundary": [[952, 1160], [952, 1169], [967, 1175], [968, 1175], [970, 1175], [971, 1175], [984, 1170], [1015, 1175], [1016, 1175], [1017, 1175], [1032, 1169], [1066, 1169], [1072, 1173], [1072, 1174], [1073, 1174], [1074, 1174], [1075, 1174], [1190, 1167], [1203, 1172], [1205, 1172], [1206, 1172], [1256, 1167], [1298, 1171], [1299, 1171], [1300, 1171], [1301, 1171], [1310, 1165], [1350, 1170], [1351, 1154], [1348, 1132], [951, 1138], [952, 1160]], "text": null, "base_dir": null, "type": "baselines", "imagename": null, "tags": {"type": "default"}, "split": null, "regions": ["bcd90dbe-70ed-4fa4-bf6f-a731dd55f689"]}, {"id": "ce3e8ae6-1f8a-4aba-8f82-f2402b36ebac", "baseline": [[954, 1185], [1345, 1180]], "boundary": [[954, 1185], [954, 1194], [1344, 1189], [1345, 1180], [1342, 1164], [953, 1167], [954, 1185]], "text": null, "base_dir": null, "type": "baselines", "imagename": null, "tags": {"type": "default"}, "split": null, "regions": ["bcd90dbe-70ed-4fa4-bf6f-a731dd55f689"]}, {"id": "45d3ec9c-f748-4945-9b5b-5342dc936ee2", "baseline": [[954, 1210], [1355, 1205]], "boundary": [[954, 1210], [954, 1220], [1354, 1215], [1355, 1205], [1351, 1183], [1330, 1189], [1282, 1183], [1281, 1183], [1280, 1183], [1279, 1183], [1272, 1189], [1207, 1184], [1206, 1184], [1151, 1191], [1054, 1185], [1053, 1185], [1052, 1185], [1050, 1185], [1042, 1192], [982, 1187], [981, 1187], [980, 1187], [953, 1193], [954, 1210]], "text": null, "base_dir": null, "type": "baselines", "imagename": null, "tags": {"type": "default"}, "split": null, "regions": ["bcd90dbe-70ed-4fa4-bf6f-a731dd55f689"]}, {"id": "922cfe2a-bfe5-489b-84a9-fc0932016bf0", "baseline": [[953, 1236], [1371, 1230]], "boundary": [[1366, 1213], [952, 1218], [953, 1236], [953, 1245], [1160, 1250], [1161, 1250], [1371, 1239], [1371, 1230], [1369, 1219], [1366, 1213]], "text": null, "base_dir": null, "type": "baselines", "imagename": null, "tags": {"type": "default"}, "split": null, "regions": ["bcd90dbe-70ed-4fa4-bf6f-a731dd55f689"]}, {"id": "05677135-684a-4088-9a83-c0ea5bd6cc68", "baseline": [[956, 1264], [1361, 1257]], "boundary": [[956, 1264], [956, 1274], [1360, 1267], [1361, 1257], [1359, 1238], [1292, 1235], [1291, 1235], [1258, 1242], [1225, 1236], [1223, 1236], [1154, 1244], [1100, 1239], [1099, 1239], [1098, 1239], [1097, 1239], [1085, 1246], [1022, 1246], [983, 1241], [982, 1241], [981, 1241], [955, 1247], [956, 1264]], "text": null, "base_dir": null, "type": "baselines", "imagename": null, "tags": {"type": "default"}, "split": null, "regions": ["bcd90dbe-70ed-4fa4-bf6f-a731dd55f689"]}, {"id": "f502596d-a1c8-4912-9691-14b260e98d91", "baseline": [[955, 1288], [1359, 1283]], "boundary": [[955, 1288], [955, 1303], [1359, 1295], [1359, 1283], [1355, 1264], [1114, 1271], [1045, 1266], [1044, 1266], [1043, 1266], [1042, 1266], [1033, 1272], [972, 1267], [971, 1267], [970, 1267], [954, 1272], [955, 1288]], "text": null, "base_dir": null, "type": "baselines", "imagename": null, "tags": {"type": "default"}, "split": null, "regions": ["bcd90dbe-70ed-4fa4-bf6f-a731dd55f689"]}, {"id": "a5eb16fd-704c-4b46-94a7-1f6a58caceb3", "baseline": [[956, 1315], [1353, 1310]], "boundary": [[956, 1315], [956, 1325], [1352, 1320], [1353, 1310], [1351, 1294], [1035, 1292], [1034, 1292], [955, 1298], [956, 1315]], "text": null, "base_dir": null, "type": "baselines", "imagename": null, "tags": {"type": "default"}, "split": null, "regions": ["bcd90dbe-70ed-4fa4-bf6f-a731dd55f689"]}, {"id": "3a08a37c-a63a-429e-8cac-859164b4e37f", "baseline": [[957, 1343], [1356, 1334]], "boundary": [[957, 1343], [957, 1353], [1356, 1345], [1356, 1334], [1354, 1318], [1106, 1317], [1105, 1317], [1104, 1317], [1087, 1324], [1045, 1320], [1044, 1320], [1043, 1320], [1032, 1325], [1017, 1320], [1016, 1320], [1015, 1320], [956, 1327], [957, 1343]], "text": null, "base_dir": null, "type": "baselines", "imagename": null, "tags": {"type": "default"}, "split": null, "regions": ["bcd90dbe-70ed-4fa4-bf6f-a731dd55f689"]}, {"id": "b4a0bbd1-1b79-492d-a6ca-1b43a8657b2f", "baseline": [[956, 1371], [1369, 1359]], "boundary": [[956, 1371], [956, 1382], [1368, 1371], [1369, 1359], [1365, 1336], [1281, 1344], [1242, 1339], [1241, 1339], [1158, 1347], [1118, 1343], [1117, 1343], [1075, 1351], [955, 1351], [956, 1371]], "text": null, "base_dir": null, "type": "baselines", "imagename": null, "tags": {"type": "default"}, "split": null, "regions": ["bcd90dbe-70ed-4fa4-bf6f-a731dd55f689"]}, {"id": "1a2ff2af-a9ed-430f-bec3-e4b645766256", "baseline": [[956, 1397], [1356, 1388]], "boundary": [[956, 1397], [956, 1408], [1356, 1398], [1356, 1388], [1354, 1372], [1055, 1372], [1054, 1372], [955, 1379], [956, 1397]], "text": null, "base_dir": null, "type": "baselines", "imagename": null, "tags": {"type": "default"}, "split": null, "regions": ["bcd90dbe-70ed-4fa4-bf6f-a731dd55f689"]}, {"id": "ff5e9d58-0878-4b40-9e4f-d192dda36015", "baseline": [[956, 1421], [1349, 1416]], "boundary": [[956, 1421], [956, 1430], [1348, 1425], [1349, 1416], [1347, 1400], [1269, 1395], [1268, 1395], [955, 1405], [956, 1421]], "text": null, "base_dir": null, "type": "baselines", "imagename": null, "tags": {"type": "default"}, "split": null, "regions": ["bcd90dbe-70ed-4fa4-bf6f-a731dd55f689"]}, {"id": "2fbc3bf8-34b2-4706-92fc-1b9edaab68e8", "baseline": [[956, 1448], [1354, 1444]], "boundary": [[956, 1448], [956, 1457], [1353, 1453], [1354, 1444], [1352, 1426], [1253, 1420], [1252, 1420], [1251, 1420], [1236, 1428], [1177, 1428], [1155, 1421], [1154, 1421], [1152, 1421], [1151, 1421], [1129, 1428], [1039, 1424], [1038, 1424], [1037, 1424], [1036, 1424], [1029, 1429], [1016, 1425], [1015, 1425], [1014, 1425], [955, 1430], [956, 1448]], "text": null, "base_dir": null, "type": "baselines", "imagename": null, "tags": {"type": "default"}, "split": null, "regions": ["bcd90dbe-70ed-4fa4-bf6f-a731dd55f689"]}, {"id": "6aaacf95-ec05-430c-94c6-809c6cfa8f16", "baseline": [[957, 1475], [1344, 1469]], "boundary": [[957, 1475], [957, 1487], [1343, 1478], [1344, 1469], [1342, 1451], [1188, 1448], [1187, 1448], [1186, 1448], [1172, 1454], [1014, 1451], [1013, 1451], [956, 1457], [957, 1475]], "text": null, "base_dir": null, "type": "baselines", "imagename": null, "tags": {"type": "default"}, "split": null, "regions": ["bcd90dbe-70ed-4fa4-bf6f-a731dd55f689"]}, {"id": "db73e3b0-2816-4aec-b8ff-e0e556b54563", "baseline": [[958, 1500], [1359, 1495]], "boundary": [[958, 1500], [958, 1512], [1358, 1505], [1359, 1495], [1355, 1472], [1270, 1479], [1187, 1475], [1186, 1475], [1185, 1475], [1184, 1475], [1184, 1476], [1178, 1480], [1118, 1475], [1117, 1475], [1116, 1475], [1115, 1475], [1105, 1481], [1005, 1477], [1004, 1477], [957, 1484], [958, 1500]], "text": null, "base_dir": null, "type": "baselines", "imagename": null, "tags": {"type": "default"}, "split": null, "regions": ["bcd90dbe-70ed-4fa4-bf6f-a731dd55f689"]}, {"id": "38ebf19b-9dd2-4238-a27c-6cb4575f8841", "baseline": [[957, 1525], [1364, 1519]], "boundary": [[957, 1525], [957, 1546], [1101, 1546], [1117, 1551], [1118, 1551], [1119, 1551], [1226, 1541], [1286, 1547], [1287, 1547], [1318, 1540], [1341, 1548], [1342, 1548], [1343, 1548], [1344, 1548], [1364, 1539], [1364, 1519], [1361, 1498], [956, 1504], [957, 1525]], "text": null, "base_dir": null, "type": "baselines", "imagename": null, "tags": {"type": "default"}, "split": null, "regions": ["bcd90dbe-70ed-4fa4-bf6f-a731dd55f689"]}, {"id": "8f015cda-0187-4190-a043-00e0e1594a6c", "baseline": [[1465, 505], [1485, 505]], "boundary": [[1476, 487], [1465, 494], [1465, 505], [1465, 520], [1485, 520], [1485, 505], [1483, 487], [1476, 487]], "text": null, "base_dir": null, "type": "baselines", "imagename": null, "tags": {"type": "default"}, "split": null, "regions": ["61c58a57-b73c-4871-94cb-004f6cc9f137"]}, {"id": "c4e8c526-8109-47ac-8b1a-a4b2e14412f8", "baseline": [[1533, 236], [1940, 233]], "boundary": [[1931, 221], [1920, 221], [1909, 221], [1898, 221], [1886, 221], [1875, 221], [1864, 221], [1853, 221], [1842, 221], [1831, 221], [1820, 221], [1809, 221], [1798, 221], [1787, 221], [1776, 221], [1764, 221], [1753, 221], [1742, 221], [1731, 221], [1720, 221], [1709, 221], [1698, 221], [1687, 221], [1676, 221], [1665, 221], [1654, 221], [1643, 221], [1631, 221], [1620, 221], [1609, 221], [1598, 221], [1587, 221], [1576, 221], [1565, 221], [1554, 221], [1543, 221], [1532, 221], [1533, 236], [1533, 244], [1937, 247], [1940, 233], [1936, 221], [1931, 221]], "text": null, "base_dir": null, "type": "baselines", "imagename": null, "tags": {"type": "default"}, "split": null, "regions": ["61c58a57-b73c-4871-94cb-004f6cc9f137"]}, {"id": "3d14e505-8cfe-41c5-b138-fc5ce1ff402b", "baseline": [[1531, 264], [1933, 260]], "boundary": [[1531, 264], [1531, 272], [1933, 268], [1933, 260], [1931, 242], [1731, 238], [1730, 238], [1702, 243], [1541, 240], [1539, 240], [1538, 240], [1537, 240], [1529, 243], [1531, 264]], "text": null, "base_dir": null, "type": "baselines", "imagename": null, "tags": {"type": "default"}, "split": null, "regions": ["61c58a57-b73c-4871-94cb-004f6cc9f137"]}, {"id": "4c543b1b-5ef0-4fa0-bdd8-b0c553abc0d5", "baseline": [[1532, 289], [1930, 284]], "boundary": [[1532, 289], [1532, 303], [1929, 300], [1930, 284], [1926, 267], [1531, 269], [1532, 289]], "text": null, "base_dir": null, "type": "baselines", "imagename": null, "tags": {"type": "default"}, "split": null, "regions": ["61c58a57-b73c-4871-94cb-004f6cc9f137"]}, {"id": "40c11016-02e0-4053-a256-6dd7bd369041", "baseline": [[1532, 316], [1932, 314]], "boundary": [[1532, 316], [1532, 326], [1930, 328], [1932, 314], [1930, 292], [1560, 292], [1559, 292], [1531, 298], [1532, 316]], "text": null, "base_dir": null, "type": "baselines", "imagename": null, "tags": {"type": "default"}, "split": null, "regions": ["61c58a57-b73c-4871-94cb-004f6cc9f137"]}, {"id": "eaf56fad-3e81-4272-bf5c-11cd7cf96e00", "baseline": [[1534, 345], [1939, 340]], "boundary": [[1534, 345], [1534, 355], [1939, 350], [1939, 340], [1935, 320], [1533, 323], [1534, 345]], "text": null, "base_dir": null, "type": "baselines", "imagename": null, "tags": {"type": "default"}, "split": null, "regions": ["61c58a57-b73c-4871-94cb-004f6cc9f137"]}, {"id": "a108d1c1-0e5a-4973-b20b-bb5ed00b17d5", "baseline": [[1533, 372], [1932, 367]], "boundary": [[1533, 372], [1533, 380], [1564, 386], [1565, 386], [1736, 379], [1830, 384], [1831, 384], [1866, 379], [1919, 383], [1920, 383], [1921, 383], [1922, 383], [1932, 376], [1932, 367], [1929, 351], [1532, 354], [1533, 372]], "text": null, "base_dir": null, "type": "baselines", "imagename": null, "tags": {"type": "default"}, "split": null, "regions": ["61c58a57-b73c-4871-94cb-004f6cc9f137"]}, {"id": "1198f242-b4bc-43e4-9842-60663f85f818", "baseline": [[1524, 399], [1931, 394]], "boundary": [[1524, 399], [1524, 411], [1931, 407], [1931, 394], [1929, 377], [1726, 373], [1725, 373], [1523, 381], [1524, 399]], "text": null, "base_dir": null, "type": "baselines", "imagename": null, "tags": {"type": "default"}, "split": null, "regions": ["61c58a57-b73c-4871-94cb-004f6cc9f137"]}, {"id": "880f3953-308a-4604-ae4c-0e75352b6638", "baseline": [[1536, 425], [1927, 418]], "boundary": [[1536, 425], [1536, 435], [1926, 433], [1927, 418], [1924, 401], [1535, 406], [1536, 425]], "text": null, "base_dir": null, "type": "baselines", "imagename": null, "tags": {"type": "default"}, "split": null, "regions": ["61c58a57-b73c-4871-94cb-004f6cc9f137"]}, {"id": "40ef0680-5cff-405d-bf3f-4b40c4522403", "baseline": [[1535, 452], [1934, 445]], "boundary": [[1535, 452], [1535, 461], [1599, 467], [1600, 467], [1674, 459], [1732, 465], [1733, 465], [1735, 465], [1756, 458], [1844, 463], [1845, 463], [1934, 454], [1934, 445], [1931, 423], [1666, 432], [1553, 428], [1552, 428], [1550, 428], [1534, 434], [1535, 452]], "text": null, "base_dir": null, "type": "baselines", "imagename": null, "tags": {"type": "default"}, "split": null, "regions": ["61c58a57-b73c-4871-94cb-004f6cc9f137"]}, {"id": "369dffd4-f2dc-44cb-a21b-35d5e1147fb3", "baseline": [[1524, 481], [1930, 472]], "boundary": [[1524, 481], [1524, 494], [1725, 485], [1732, 490], [1733, 490], [1735, 490], [1736, 490], [1782, 489], [1783, 489], [1784, 489], [1784, 488], [1789, 484], [1802, 489], [1803, 489], [1804, 489], [1805, 489], [1830, 484], [1894, 487], [1895, 487], [1930, 479], [1930, 472], [1926, 454], [1523, 461], [1524, 481]], "text": null, "base_dir": null, "type": "baselines", "imagename": null, "tags": {"type": "default"}, "split": null, "regions": ["61c58a57-b73c-4871-94cb-004f6cc9f137"]}, {"id": "ce853f1d-2d0a-47f8-beb4-12895bb74dc6", "baseline": [[1533, 504], [1942, 497]], "boundary": [[1547, 481], [1546, 481], [1532, 486], [1533, 504], [1533, 513], [1942, 510], [1942, 497], [1940, 481], [1873, 475], [1872, 475], [1803, 482], [1548, 481], [1547, 481]], "text": null, "base_dir": null, "type": "baselines", "imagename": null, "tags": {"type": "default"}, "split": null, "regions": ["61c58a57-b73c-4871-94cb-004f6cc9f137"]}, {"id": "aa5dc67a-e3ef-4d4d-a503-055a348d0a9c", "baseline": [[1533, 532], [1866, 524]], "boundary": [[1533, 532], [1533, 545], [1623, 549], [1624, 549], [1625, 549], [1626, 549], [1638, 538], [1659, 546], [1660, 546], [1661, 546], [1708, 537], [1769, 545], [1770, 545], [1771, 545], [1787, 537], [1796, 545], [1797, 545], [1798, 545], [1799, 545], [1800, 545], [1819, 535], [1856, 539], [1858, 539], [1859, 539], [1860, 539], [1866, 534], [1866, 524], [1864, 507], [1774, 502], [1773, 502], [1772, 502], [1758, 508], [1726, 504], [1725, 504], [1723, 504], [1706, 510], [1532, 510], [1533, 532]], "text": null, "base_dir": null, "type": "baselines", "imagename": null, "tags": {"type": "default"}, "split": null, "regions": ["61c58a57-b73c-4871-94cb-004f6cc9f137"]}, {"id": "82dfadc1-267f-4d81-a707-26f8e8590f73", "baseline": [[1624, 554], [1940, 550]], "boundary": [[1624, 554], [1624, 568], [1874, 561], [1906, 566], [1907, 566], [1940, 559], [1940, 550], [1936, 527], [1623, 530], [1624, 554]], "text": null, "base_dir": null, "type": "baselines", "imagename": null, "tags": {"type": "default"}, "split": null, "regions": ["61c58a57-b73c-4871-94cb-004f6cc9f137"]}, {"id": "de17da81-5fa0-4062-ad4d-d9fde258d5e5", "baseline": [[1627, 580], [1939, 577]], "boundary": [[1627, 580], [1628, 597], [1646, 591], [1707, 596], [1708, 596], [1937, 588], [1939, 577], [1936, 561], [1834, 556], [1833, 556], [1807, 561], [1731, 557], [1730, 557], [1729, 557], [1718, 563], [1644, 558], [1643, 558], [1641, 558], [1626, 564], [1627, 580]], "text": null, "base_dir": null, "type": "baselines", "imagename": null, "tags": {"type": "default"}, "split": null, "regions": ["61c58a57-b73c-4871-94cb-004f6cc9f137"]}, {"id": "13e58bbf-1a5f-4951-a28b-ca9557975f4a", "baseline": [[1538, 607], [1939, 601]], "boundary": [[1538, 607], [1539, 622], [1563, 617], [1616, 621], [1617, 621], [1697, 620], [1698, 620], [1699, 620], [1708, 615], [1937, 615], [1939, 601], [1935, 586], [1749, 589], [1723, 581], [1722, 581], [1721, 581], [1720, 581], [1709, 587], [1681, 582], [1680, 582], [1679, 582], [1658, 591], [1593, 591], [1584, 584], [1584, 582], [1583, 582], [1582, 582], [1580, 582], [1537, 582], [1538, 607]], "text": null, "base_dir": null, "type": "baselines", "imagename": null, "tags": {"type": "default"}, "split": null, "regions": ["61c58a57-b73c-4871-94cb-004f6cc9f137"]}, {"id": "ec8039fd-3c74-423e-95cf-7748e077ff5e", "baseline": [[1541, 636], [1946, 629]], "boundary": [[1541, 636], [1541, 645], [1946, 643], [1946, 629], [1943, 607], [1667, 616], [1609, 611], [1608, 611], [1607, 611], [1594, 617], [1544, 612], [1543, 612], [1542, 612], [1541, 612], [1541, 614], [1539, 614], [1541, 636]], "text": null, "base_dir": null, "type": "baselines", "imagename": null, "tags": {"type": "default"}, "split": null, "regions": ["61c58a57-b73c-4871-94cb-004f6cc9f137"]}, {"id": "f80a1bd2-6996-4e78-bf51-62069ef07ca2", "baseline": [[1544, 660], [1935, 653]], "boundary": [[1544, 660], [1544, 676], [1575, 670], [1603, 674], [1604, 674], [1605, 674], [1626, 669], [1668, 673], [1669, 673], [1670, 673], [1671, 673], [1679, 668], [1708, 672], [1709, 672], [1934, 666], [1935, 653], [1932, 636], [1543, 640], [1544, 660]], "text": null, "base_dir": null, "type": "baselines", "imagename": null, "tags": {"type": "default"}, "split": null, "regions": ["61c58a57-b73c-4871-94cb-004f6cc9f137"]}, {"id": "41494907-82ed-47e9-a047-d1d5e3c8bb34", "baseline": [[1543, 687], [1935, 680]], "boundary": [[1543, 687], [1544, 701], [1559, 696], [1606, 700], [1607, 700], [1608, 700], [1609, 700], [1616, 694], [1671, 699], [1672, 699], [1934, 691], [1935, 680], [1932, 659], [1542, 669], [1543, 687]], "text": null, "base_dir": null, "type": "baselines", "imagename": null, "tags": {"type": "default"}, "split": null, "regions": ["61c58a57-b73c-4871-94cb-004f6cc9f137"]}, {"id": "4d8b74b6-72fe-43d7-88d9-ed3f7e95e16d", "baseline": [[1543, 709], [1952, 704]], "boundary": [[1543, 709], [1543, 719], [1952, 718], [1952, 704], [1949, 686], [1542, 693], [1543, 709]], "text": null, "base_dir": null, "type": "baselines", "imagename": null, "tags": {"type": "default"}, "split": null, "regions": ["61c58a57-b73c-4871-94cb-004f6cc9f137"]}, {"id": "9325935c-6f6f-4501-95d1-435f604cd9c8", "baseline": [[1542, 735], [1949, 731]], "boundary": [[1542, 735], [1542, 749], [1949, 743], [1949, 731], [1945, 709], [1910, 714], [1866, 710], [1865, 710], [1864, 710], [1842, 715], [1641, 712], [1640, 712], [1541, 718], [1542, 735]], "text": null, "base_dir": null, "type": "baselines", "imagename": null, "tags": {"type": "default"}, "split": null, "regions": ["61c58a57-b73c-4871-94cb-004f6cc9f137"]}, {"id": "5d2afdbc-70a7-43ed-adab-c0fa8915305a", "baseline": [[1543, 761], [1945, 755]], "boundary": [[1543, 761], [1543, 773], [1945, 771], [1945, 755], [1943, 740], [1863, 734], [1862, 734], [1833, 741], [1542, 742], [1543, 761]], "text": null, "base_dir": null, "type": "baselines", "imagename": null, "tags": {"type": "default"}, "split": null, "regions": ["61c58a57-b73c-4871-94cb-004f6cc9f137"]}, {"id": "32329048-fd1c-419c-8939-c005e50cc6ed", "baseline": [[1542, 785], [1930, 781]], "boundary": [[1542, 785], [1542, 798], [1929, 793], [1930, 781], [1926, 766], [1541, 766], [1542, 785]], "text": null, "base_dir": null, "type": "baselines", "imagename": null, "tags": {"type": "default"}, "split": null, "regions": ["61c58a57-b73c-4871-94cb-004f6cc9f137"]}, {"id": "165f03fb-0245-4432-9ae5-7d8af529b42e", "baseline": [[1542, 812], [1952, 803]], "boundary": [[1542, 812], [1542, 829], [1601, 823], [1621, 829], [1623, 829], [1624, 829], [1625, 829], [1626, 829], [1636, 823], [1742, 826], [1743, 826], [1745, 826], [1746, 826], [1753, 820], [1784, 825], [1786, 825], [1900, 823], [1952, 814], [1952, 803], [1949, 786], [1541, 791], [1542, 812]], "text": null, "base_dir": null, "type": "baselines", "imagename": null, "tags": {"type": "default"}, "split": null, "regions": ["61c58a57-b73c-4871-94cb-004f6cc9f137"]}, {"id": "65e8f820-f5fd-4233-941e-d753bec17d40", "baseline": [[1541, 840], [1929, 833]], "boundary": [[1541, 840], [1541, 852], [1799, 852], [1799, 851], [1870, 844], [1917, 848], [1919, 848], [1920, 848], [1921, 848], [1929, 843], [1929, 833], [1925, 815], [1539, 821], [1541, 840]], "text": null, "base_dir": null, "type": "baselines", "imagename": null, "tags": {"type": "default"}, "split": null, "regions": ["61c58a57-b73c-4871-94cb-004f6cc9f137"]}, {"id": "a3e131c5-f01b-4c8d-993e-8c3c4be081b5", "baseline": [[1543, 864], [1946, 857]], "boundary": [[1543, 864], [1543, 876], [1946, 870], [1946, 857], [1943, 837], [1542, 844], [1543, 864]], "text": null, "base_dir": null, "type": "baselines", "imagename": null, "tags": {"type": "default"}, "split": null, "regions": ["61c58a57-b73c-4871-94cb-004f6cc9f137"]}, {"id": "81517097-45c0-4b8b-807e-794d0a5cdfa1", "baseline": [[1536, 889], [1937, 883]], "boundary": [[1536, 889], [1536, 897], [1937, 896], [1937, 883], [1934, 866], [1535, 868], [1536, 889]], "text": null, "base_dir": null, "type": "baselines", "imagename": null, "tags": {"type": "default"}, "split": null, "regions": ["61c58a57-b73c-4871-94cb-004f6cc9f137"]}, {"id": "0d0528e9-a059-43d6-975c-c238cfa252b9", "baseline": [[1539, 915], [1935, 908]], "boundary": [[1539, 915], [1539, 925], [1578, 931], [1579, 931], [1702, 923], [1732, 928], [1733, 928], [1735, 928], [1736, 928], [1736, 927], [1737, 927], [1741, 922], [1768, 922], [1801, 927], [1802, 927], [1934, 918], [1935, 908], [1932, 888], [1538, 894], [1539, 915]], "text": null, "base_dir": null, "type": "baselines", "imagename": null, "tags": {"type": "default"}, "split": null, "regions": ["61c58a57-b73c-4871-94cb-004f6cc9f137"]}, {"id": "bf29b766-c7af-4136-8d2b-7322786957d8", "baseline": [[1542, 943], [1927, 936]], "boundary": [[1542, 943], [1542, 953], [1926, 946], [1927, 936], [1924, 919], [1541, 922], [1542, 943]], "text": null, "base_dir": null, "type": "baselines", "imagename": null, "tags": {"type": "default"}, "split": null, "regions": ["61c58a57-b73c-4871-94cb-004f6cc9f137"]}, {"id": "dcdbd39f-42eb-40cf-aa6b-a87901a05539", "baseline": [[1543, 966], [1945, 964]], "boundary": [[1941, 953], [1937, 942], [1767, 942], [1766, 942], [1764, 942], [1740, 947], [1588, 943], [1587, 943], [1542, 948], [1543, 966], [1543, 975], [1676, 981], [1677, 981], [1678, 981], [1679, 981], [1679, 980], [1685, 975], [1745, 974], [1762, 980], [1763, 980], [1764, 981], [1817, 981], [1817, 980], [1818, 980], [1841, 974], [1906, 980], [1907, 980], [1944, 973], [1945, 964], [1943, 942], [1941, 942], [1941, 953]], "text": null, "base_dir": null, "type": "baselines", "imagename": null, "tags": {"type": "default"}, "split": null, "regions": ["61c58a57-b73c-4871-94cb-004f6cc9f137"]}, {"id": "80a371d3-e7db-4d2d-bf08-d82363ef6bf7", "baseline": [[1544, 995], [1936, 988]], "boundary": [[1544, 995], [1544, 1006], [1935, 999], [1936, 988], [1934, 973], [1886, 966], [1885, 966], [1822, 967], [1821, 967], [1802, 974], [1749, 968], [1748, 968], [1747, 968], [1729, 975], [1688, 969], [1687, 969], [1686, 969], [1667, 977], [1543, 977], [1544, 995]], "text": null, "base_dir": null, "type": "baselines", "imagename": null, "tags": {"type": "default"}, "split": null, "regions": ["61c58a57-b73c-4871-94cb-004f6cc9f137"]}, {"id": "3f68fbc8-9b92-447d-ba5e-06b7e3763972", "baseline": [[1545, 1019], [1946, 1015]], "boundary": [[1545, 1019], [1545, 1032], [1945, 1027], [1946, 1015], [1943, 996], [1544, 1003], [1545, 1019]], "text": null, "base_dir": null, "type": "baselines", "imagename": null, "tags": {"type": "default"}, "split": null, "regions": ["61c58a57-b73c-4871-94cb-004f6cc9f137"]}, {"id": "175607f7-ddd4-41d4-a9ff-0dc94645c620", "baseline": [[1544, 1047], [1953, 1040]], "boundary": [[1944, 1021], [1926, 1018], [1925, 1018], [1882, 1024], [1847, 1019], [1845, 1019], [1811, 1026], [1543, 1026], [1544, 1047], [1544, 1057], [1953, 1048], [1953, 1040], [1952, 1039], [1944, 1021]], "text": null, "base_dir": null, "type": "baselines", "imagename": null, "tags": {"type": "default"}, "split": null, "regions": ["61c58a57-b73c-4871-94cb-004f6cc9f137"]}, {"id": "815efc4e-c27f-44ad-8e86-3a2e49cb1851", "baseline": [[1545, 1071], [1950, 1068]], "boundary": [[1545, 1071], [1545, 1085], [1949, 1077], [1950, 1068], [1947, 1051], [1544, 1050], [1545, 1071]], "text": null, "base_dir": null, "type": "baselines", "imagename": null, "tags": {"type": "default"}, "split": null, "regions": ["61c58a57-b73c-4871-94cb-004f6cc9f137"]}, {"id": "c8f7c66c-b414-454b-90ba-eaed85d785ff", "baseline": [[1544, 1099], [1972, 1095]], "boundary": [[1964, 1078], [1963, 1076], [1863, 1071], [1862, 1071], [1822, 1077], [1773, 1072], [1772, 1072], [1735, 1079], [1543, 1079], [1544, 1099], [1544, 1110], [1972, 1110], [1972, 1095], [1971, 1091], [1964, 1078]], "text": null, "base_dir": null, "type": "baselines", "imagename": null, "tags": {"type": "default"}, "split": null, "regions": ["61c58a57-b73c-4871-94cb-004f6cc9f137"]}, {"id": "91887a2e-623d-4255-8af1-0c57ee88ca39", "baseline": [[1546, 1126], [1946, 1120]], "boundary": [[1546, 1126], [1546, 1139], [1630, 1133], [1697, 1138], [1698, 1138], [1699, 1138], [1700, 1138], [1708, 1132], [1770, 1137], [1771, 1137], [1772, 1137], [1792, 1131], [1927, 1134], [1929, 1134], [1930, 1134], [1946, 1128], [1946, 1120], [1942, 1097], [1924, 1102], [1784, 1098], [1783, 1098], [1545, 1108], [1546, 1126]], "text": null, "base_dir": null, "type": "baselines", "imagename": null, "tags": {"type": "default"}, "split": null, "regions": ["61c58a57-b73c-4871-94cb-004f6cc9f137"]}, {"id": "ddd90e4c-a08e-40a5-a727-706165053957", "baseline": [[1546, 1151], [1934, 1143]], "boundary": [[1546, 1151], [1546, 1162], [1934, 1155], [1934, 1143], [1931, 1126], [1545, 1134], [1546, 1151]], "text": null, "base_dir": null, "type": "baselines", "imagename": null, "tags": {"type": "default"}, "split": null, "regions": ["61c58a57-b73c-4871-94cb-004f6cc9f137"]}, {"id": "78ca8a3c-e0a8-4fc6-b240-362414c6409e", "baseline": [[1546, 1179], [1944, 1170]], "boundary": [[1546, 1179], [1546, 1191], [1944, 1180], [1944, 1170], [1941, 1150], [1545, 1157], [1546, 1179]], "text": null, "base_dir": null, "type": "baselines", "imagename": null, "tags": {"type": "default"}, "split": null, "regions": ["61c58a57-b73c-4871-94cb-004f6cc9f137"]}, {"id": "1b2c286a-aad7-43e5-a119-b143d84d5ba1", "baseline": [[1545, 1204], [1952, 1195]], "boundary": [[1545, 1204], [1545, 1211], [1952, 1205], [1952, 1195], [1949, 1177], [1544, 1184], [1545, 1204]], "text": null, "base_dir": null, "type": "baselines", "imagename": null, "tags": {"type": "default"}, "split": null, "regions": ["61c58a57-b73c-4871-94cb-004f6cc9f137"]}, {"id": "42e659c3-df61-43cc-b4a4-ecb4f37b6529", "baseline": [[1549, 1231], [1957, 1223]], "boundary": [[1549, 1231], [1549, 1245], [1957, 1234], [1957, 1223], [1953, 1199], [1936, 1204], [1898, 1199], [1896, 1199], [1822, 1201], [1821, 1201], [1820, 1201], [1820, 1202], [1814, 1206], [1685, 1204], [1684, 1204], [1652, 1210], [1634, 1204], [1633, 1204], [1631, 1204], [1630, 1204], [1629, 1204], [1623, 1211], [1548, 1211], [1549, 1231]], "text": null, "base_dir": null, "type": "baselines", "imagename": null, "tags": {"type": "default"}, "split": null, "regions": ["61c58a57-b73c-4871-94cb-004f6cc9f137"]}, {"id": "165d6835-404a-4d87-a17a-2f343a79b4c9", "baseline": [[1547, 1255], [1937, 1249]], "boundary": [[1547, 1255], [1547, 1267], [1855, 1261], [1870, 1265], [1871, 1265], [1872, 1265], [1937, 1257], [1937, 1249], [1934, 1231], [1546, 1239], [1547, 1255]], "text": null, "base_dir": null, "type": "baselines", "imagename": null, "tags": {"type": "default"}, "split": null, "regions": ["61c58a57-b73c-4871-94cb-004f6cc9f137"]}, {"id": "b6b15296-8ba3-4ff5-9c98-1773bde51cc7", "baseline": [[1547, 1284], [1932, 1274]], "boundary": [[1547, 1284], [1547, 1292], [1669, 1295], [1670, 1295], [1932, 1283], [1932, 1274], [1929, 1256], [1546, 1264], [1547, 1284]], "text": null, "base_dir": null, "type": "baselines", "imagename": null, "tags": {"type": "default"}, "split": null, "regions": ["61c58a57-b73c-4871-94cb-004f6cc9f137"]}, {"id": "7c638508-40d8-4090-9900-7b9b2f2fcca5", "baseline": [[1548, 1307], [1943, 1301]], "boundary": [[1548, 1307], [1548, 1316], [1943, 1311], [1943, 1301], [1940, 1280], [1547, 1285], [1548, 1307]], "text": null, "base_dir": null, "type": "baselines", "imagename": null, "tags": {"type": "default"}, "split": null, "regions": ["61c58a57-b73c-4871-94cb-004f6cc9f137"]}, {"id": "74affd84-da2c-48ae-8c6e-fb2860086273", "baseline": [[1548, 1334], [1934, 1325]], "boundary": [[1548, 1334], [1548, 1344], [1934, 1336], [1934, 1325], [1931, 1308], [1594, 1311], [1547, 1316], [1548, 1334]], "text": null, "base_dir": null, "type": "baselines", "imagename": null, "tags": {"type": "default"}, "split": null, "regions": ["61c58a57-b73c-4871-94cb-004f6cc9f137"]}, {"id": "78be6acf-8daa-4e30-a1fc-5c7a0315f3ad", "baseline": [[1549, 1359], [1961, 1351]], "boundary": [[1549, 1359], [1549, 1371], [1804, 1371], [1804, 1369], [1858, 1363], [1907, 1367], [1909, 1367], [1961, 1359], [1961, 1351], [1957, 1330], [1548, 1337], [1549, 1359]], "text": null, "base_dir": null, "type": "baselines", "imagename": null, "tags": {"type": "default"}, "split": null, "regions": ["61c58a57-b73c-4871-94cb-004f6cc9f137"]}, {"id": "1299c890-1899-4d0c-ad59-3ef78249443c", "baseline": [[1548, 1385], [1940, 1378]], "boundary": [[1548, 1385], [1548, 1395], [1939, 1388], [1940, 1378], [1937, 1362], [1613, 1362], [1611, 1362], [1547, 1368], [1548, 1385]], "text": null, "base_dir": null, "type": "baselines", "imagename": null, "tags": {"type": "default"}, "split": null, "regions": ["61c58a57-b73c-4871-94cb-004f6cc9f137"]}, {"id": "908265c9-cffa-4bba-b707-5e7ff43a449c", "baseline": [[1548, 1413], [1947, 1403]], "boundary": [[1548, 1413], [1548, 1424], [1947, 1414], [1947, 1403], [1944, 1380], [1901, 1387], [1882, 1383], [1881, 1383], [1880, 1383], [1808, 1389], [1773, 1384], [1772, 1384], [1721, 1392], [1547, 1390], [1548, 1413]], "text": null, "base_dir": null, "type": "baselines", "imagename": null, "tags": {"type": "default"}, "split": null, "regions": ["61c58a57-b73c-4871-94cb-004f6cc9f137"]}, {"id": "56af3fbf-177a-422d-a028-c2eab52c9f3b", "baseline": [[1548, 1440], [1939, 1430]], "boundary": [[1548, 1440], [1548, 1450], [1939, 1445], [1939, 1430], [1933, 1407], [1924, 1413], [1759, 1412], [1758, 1412], [1669, 1419], [1547, 1417], [1548, 1440]], "text": null, "base_dir": null, "type": "baselines", "imagename": null, "tags": {"type": "default"}, "split": null, "regions": ["61c58a57-b73c-4871-94cb-004f6cc9f137"]}, {"id": "32b400c3-699f-4331-8279-423f139fc66f", "baseline": [[1549, 1466], [1956, 1459]], "boundary": [[1549, 1466], [1549, 1476], [1955, 1474], [1956, 1459], [1953, 1443], [1548, 1448], [1549, 1466]], "text": null, "base_dir": null, "type": "baselines", "imagename": null, "tags": {"type": "default"}, "split": null, "regions": ["61c58a57-b73c-4871-94cb-004f6cc9f137"]}, {"id": "5ad6fa53-7cb9-4a07-a242-7caf88442a3e", "baseline": [[1548, 1492], [1997, 1486]], "boundary": [[1925, 1460], [1924, 1460], [1907, 1469], [1896, 1463], [1895, 1463], [1894, 1463], [1893, 1463], [1844, 1470], [1784, 1464], [1783, 1464], [1782, 1464], [1766, 1471], [1692, 1467], [1691, 1467], [1664, 1472], [1646, 1465], [1645, 1465], [1644, 1465], [1643, 1465], [1614, 1475], [1547, 1475], [1548, 1492], [1548, 1506], [1996, 1499], [1997, 1486], [1995, 1469], [1926, 1460], [1925, 1460]], "text": null, "base_dir": null, "type": "baselines", "imagename": null, "tags": {"type": "default"}, "split": null, "regions": ["61c58a57-b73c-4871-94cb-004f6cc9f137"]}, {"id": "8f5fef93-b0e9-403a-8714-c495d73aa87a", "baseline": [[2016, 232], [2445, 227]], "boundary": [[2436, 208], [2425, 208], [2414, 208], [2403, 208], [2392, 208], [2381, 208], [2370, 208], [2359, 208], [2348, 208], [2337, 208], [2325, 208], [2314, 208], [2303, 208], [2292, 208], [2281, 208], [2270, 208], [2259, 208], [2248, 208], [2237, 208], [2226, 208], [2215, 208], [2203, 208], [2192, 208], [2181, 208], [2170, 209], [2168, 209], [2165, 210], [2149, 209], [2148, 209], [2137, 209], [2126, 209], [2115, 210], [2104, 210], [2095, 210], [2095, 211], [2079, 210], [2070, 211], [2059, 211], [2048, 211], [2037, 211], [2026, 211], [2015, 220], [2016, 232], [2016, 243], [2444, 242], [2445, 227], [2443, 216], [2436, 208]], "text": null, "base_dir": null, "type": "baselines", "imagename": null, "tags": {"type": "default"}, "split": null, "regions": ["61c58a57-b73c-4871-94cb-004f6cc9f137"]}, {"id": "71ace38b-5bc3-4e16-b652-af4a09a67904", "baseline": [[2017, 259], [2432, 256]], "boundary": [[2017, 259], [2017, 269], [2432, 266], [2432, 256], [2429, 238], [2016, 239], [2017, 259]], "text": null, "base_dir": null, "type": "baselines", "imagename": null, "tags": {"type": "default"}, "split": null, "regions": ["61c58a57-b73c-4871-94cb-004f6cc9f137"]}, {"id": "1b49b5ce-64e0-4220-af03-b9af98ba90d2", "baseline": [[2017, 284], [2415, 281]], "boundary": [[2017, 284], [2017, 297], [2414, 294], [2415, 281], [2412, 266], [2016, 268], [2017, 284]], "text": null, "base_dir": null, "type": "baselines", "imagename": null, "tags": {"type": "default"}, "split": null, "regions": ["61c58a57-b73c-4871-94cb-004f6cc9f137"]}, {"id": "92054068-d29b-4409-b8b1-734d76e7ce68", "baseline": [[2017, 313], [2430, 311]], "boundary": [[2017, 313], [2017, 324], [2429, 322], [2430, 311], [2427, 295], [2229, 289], [2228, 289], [2227, 289], [2211, 295], [2028, 290], [2027, 290], [2026, 290], [2025, 290], [2016, 294], [2017, 313]], "text": null, "base_dir": null, "type": "baselines", "imagename": null, "tags": {"type": "default"}, "split": null, "regions": ["61c58a57-b73c-4871-94cb-004f6cc9f137"]}, {"id": "b2bfc393-c47b-4a40-906a-fcabcaad6734", "baseline": [[2017, 340], [2447, 340]], "boundary": [[2017, 340], [2017, 351], [2447, 351], [2447, 340], [2445, 320], [2017, 320], [2017, 340]], "text": null, "base_dir": null, "type": "baselines", "imagename": null, "tags": {"type": "default"}, "split": null, "regions": ["61c58a57-b73c-4871-94cb-004f6cc9f137"]}, {"id": "8227027d-8887-4022-b62f-54320018de86", "baseline": [[2017, 367], [2429, 363]], "boundary": [[2017, 367], [2017, 377], [2429, 374], [2429, 363], [2426, 346], [2016, 345], [2017, 367]], "text": null, "base_dir": null, "type": "baselines", "imagename": null, "tags": {"type": "default"}, "split": null, "regions": ["61c58a57-b73c-4871-94cb-004f6cc9f137"]}, {"id": "3a1a17b6-f15f-4316-a30c-83a81d69e4d5", "baseline": [[2017, 393], [2417, 389]], "boundary": [[2017, 393], [2017, 405], [2417, 399], [2417, 389], [2414, 372], [2016, 374], [2017, 393]], "text": null, "base_dir": null, "type": "baselines", "imagename": null, "tags": {"type": "default"}, "split": null, "regions": ["61c58a57-b73c-4871-94cb-004f6cc9f137"]}, {"id": "2c72d1f8-63a0-4581-bbfd-694ec0f5577f", "baseline": [[2019, 418], [2416, 415]], "boundary": [[2019, 418], [2019, 432], [2415, 428], [2416, 415], [2414, 399], [2018, 399], [2019, 418]], "text": null, "base_dir": null, "type": "baselines", "imagename": null, "tags": {"type": "default"}, "split": null, "regions": ["61c58a57-b73c-4871-94cb-004f6cc9f137"]}, {"id": "c1c568f1-9f7e-4d23-b27d-fcf100662807", "baseline": [[2018, 445], [2419, 442]], "boundary": [[2018, 445], [2018, 461], [2417, 453], [2419, 442], [2415, 423], [2017, 427], [2018, 445]], "text": null, "base_dir": null, "type": "baselines", "imagename": null, "tags": {"type": "default"}, "split": null, "regions": ["61c58a57-b73c-4871-94cb-004f6cc9f137"]}, {"id": "fe00b49a-f4b8-4701-b0fa-4d6a24f010c5", "baseline": [[2017, 473], [2433, 467]], "boundary": [[2017, 473], [2017, 484], [2433, 481], [2433, 467], [2430, 446], [2016, 449], [2017, 473]], "text": null, "base_dir": null, "type": "baselines", "imagename": null, "tags": {"type": "default"}, "split": null, "regions": ["61c58a57-b73c-4871-94cb-004f6cc9f137"]}, {"id": "a483b133-d6bc-4837-8c46-b8775b016b2b", "baseline": [[2019, 496], [2414, 496]], "boundary": [[2019, 496], [2019, 507], [2413, 510], [2414, 496], [2413, 475], [2019, 479], [2019, 496]], "text": null, "base_dir": null, "type": "baselines", "imagename": null, "tags": {"type": "default"}, "split": null, "regions": ["61c58a57-b73c-4871-94cb-004f6cc9f137"]}, {"id": "52d64e41-db6c-4478-816d-4f932be9cdb1", "baseline": [[2018, 523], [2426, 520]], "boundary": [[2018, 523], [2018, 535], [2425, 534], [2426, 520], [2424, 506], [2310, 506], [2298, 499], [2297, 499], [2296, 499], [2294, 499], [2293, 499], [2286, 505], [2060, 500], [2059, 500], [2017, 506], [2018, 523]], "text": null, "base_dir": null, "type": "baselines", "imagename": null, "tags": {"type": "default"}, "split": null, "regions": ["61c58a57-b73c-4871-94cb-004f6cc9f137"]}, {"id": "38dbe9f6-8df1-49e7-bcab-081e3a9a37fe", "baseline": [[2017, 549], [2433, 547]], "boundary": [[2017, 549], [2017, 558], [2431, 559], [2433, 547], [2430, 527], [2016, 532], [2017, 549]], "text": null, "base_dir": null, "type": "baselines", "imagename": null, "tags": {"type": "default"}, "split": null, "regions": ["61c58a57-b73c-4871-94cb-004f6cc9f137"]}, {"id": "77a3a0c8-1e68-4144-9dec-3d2a4f2570cf", "baseline": [[2017, 575], [2429, 575]], "boundary": [[2017, 575], [2017, 585], [2429, 584], [2429, 575], [2429, 556], [2017, 553], [2017, 575]], "text": null, "base_dir": null, "type": "baselines", "imagename": null, "tags": {"type": "default"}, "split": null, "regions": ["61c58a57-b73c-4871-94cb-004f6cc9f137"]}, {"id": "537686f4-fddc-4ee0-be41-97f794f03bbf", "baseline": [[2018, 601], [2424, 597]], "boundary": [[2018, 601], [2018, 614], [2423, 608], [2424, 597], [2421, 579], [2017, 581], [2018, 601]], "text": null, "base_dir": null, "type": "baselines", "imagename": null, "tags": {"type": "default"}, "split": null, "regions": ["61c58a57-b73c-4871-94cb-004f6cc9f137"]}, {"id": "1a89bdf8-acd2-48da-a462-61cb1e5b71a8", "baseline": [[2018, 628], [2419, 622]], "boundary": [[2018, 628], [2018, 638], [2417, 632], [2419, 622], [2416, 607], [2355, 601], [2354, 601], [2353, 601], [2333, 607], [2257, 602], [2256, 602], [2254, 602], [2242, 608], [2225, 604], [2223, 604], [2222, 604], [2017, 609], [2018, 628]], "text": null, "base_dir": null, "type": "baselines", "imagename": null, "tags": {"type": "default"}, "split": null, "regions": ["61c58a57-b73c-4871-94cb-004f6cc9f137"]}, {"id": "d548c426-8cae-4d71-bf50-fa0b86462398", "baseline": [[2019, 655], [2443, 647]], "boundary": [[2019, 655], [2019, 663], [2078, 669], [2079, 669], [2225, 661], [2253, 666], [2254, 666], [2256, 666], [2257, 666], [2263, 660], [2442, 661], [2443, 647], [2440, 631], [2018, 638], [2019, 655]], "text": null, "base_dir": null, "type": "baselines", "imagename": null, "tags": {"type": "default"}, "split": null, "regions": ["61c58a57-b73c-4871-94cb-004f6cc9f137"]}, {"id": "ca6f06bf-1c53-4987-bbe9-2efdd49b4ea3", "baseline": [[2013, 683], [2439, 673]], "boundary": [[2013, 683], [2014, 700], [2043, 693], [2090, 698], [2092, 698], [2093, 698], [2119, 690], [2185, 690], [2196, 696], [2197, 696], [2198, 696], [2264, 688], [2280, 693], [2281, 693], [2282, 693], [2283, 693], [2302, 688], [2437, 688], [2439, 673], [2436, 657], [2413, 651], [2412, 651], [2293, 659], [2116, 657], [2115, 657], [2114, 657], [2099, 663], [2012, 660], [2013, 683]], "text": null, "base_dir": null, "type": "baselines", "imagename": null, "tags": {"type": "default"}, "split": null, "regions": ["61c58a57-b73c-4871-94cb-004f6cc9f137"]}, {"id": "942f9b86-45fe-47f3-83ef-855362b2414f", "baseline": [[2018, 707], [2440, 699]], "boundary": [[2018, 707], [2018, 718], [2439, 711], [2440, 699], [2436, 679], [2135, 689], [2085, 684], [2084, 684], [2083, 684], [2070, 690], [2032, 686], [2031, 686], [2029, 686], [2017, 690], [2018, 707]], "text": null, "base_dir": null, "type": "baselines", "imagename": null, "tags": {"type": "default"}, "split": null, "regions": ["61c58a57-b73c-4871-94cb-004f6cc9f137"]}, {"id": "fd84d83e-ef06-4fe5-8519-426db0446739", "baseline": [[2018, 731], [2429, 727]], "boundary": [[2018, 731], [2018, 745], [2429, 738], [2429, 727], [2425, 706], [2017, 713], [2018, 731]], "text": null, "base_dir": null, "type": "baselines", "imagename": null, "tags": {"type": "default"}, "split": null, "regions": ["61c58a57-b73c-4871-94cb-004f6cc9f137"]}, {"id": "3fcc991a-d317-4828-b760-2ceba7a56c2b", "baseline": [[2018, 755], [2420, 751]], "boundary": [[2018, 755], [2018, 765], [2419, 764], [2420, 751], [2416, 737], [2017, 738], [2018, 755]], "text": null, "base_dir": null, "type": "baselines", "imagename": null, "tags": {"type": "default"}, "split": null, "regions": ["61c58a57-b73c-4871-94cb-004f6cc9f137"]}, {"id": "ce76c99d-28a2-43b4-87a5-4075466f2287", "baseline": [[2018, 779], [2426, 776]], "boundary": [[2018, 779], [2018, 789], [2425, 786], [2426, 776], [2424, 759], [2017, 758], [2018, 779]], "text": null, "base_dir": null, "type": "baselines", "imagename": null, "tags": {"type": "default"}, "split": null, "regions": ["61c58a57-b73c-4871-94cb-004f6cc9f137"]}, {"id": "820d0517-30ac-4ca6-aebe-aafe65a25d5d", "baseline": [[2019, 803], [2435, 801]], "boundary": [[2019, 803], [2019, 813], [2434, 814], [2435, 801], [2433, 784], [2018, 783], [2019, 803]], "text": null, "base_dir": null, "type": "baselines", "imagename": null, "tags": {"type": "default"}, "split": null, "regions": ["61c58a57-b73c-4871-94cb-004f6cc9f137"]}, {"id": "fb166da0-6f50-4e0d-8b62-be57936858f4", "baseline": [[2018, 832], [2420, 826]], "boundary": [[2018, 832], [2018, 843], [2161, 847], [2162, 847], [2164, 847], [2165, 847], [2172, 842], [2218, 846], [2219, 846], [2220, 846], [2236, 841], [2256, 846], [2257, 846], [2258, 846], [2419, 837], [2420, 826], [2416, 810], [2017, 812], [2018, 832]], "text": null, "base_dir": null, "type": "baselines", "imagename": null, "tags": {"type": "default"}, "split": null, "regions": ["61c58a57-b73c-4871-94cb-004f6cc9f137"]}, {"id": "1e681ef8-2a85-485b-9604-1c475bbc6fd2", "baseline": [[2019, 860], [2431, 854]], "boundary": [[2019, 860], [2019, 870], [2430, 864], [2431, 854], [2429, 839], [2359, 833], [2358, 833], [2099, 842], [2034, 837], [2033, 837], [2032, 837], [2018, 842], [2019, 860]], "text": null, "base_dir": null, "type": "baselines", "imagename": null, "tags": {"type": "default"}, "split": null, "regions": ["61c58a57-b73c-4871-94cb-004f6cc9f137"]}, {"id": "3d53b1d6-dbd3-425e-9b06-fe2638d0c26d", "baseline": [[2019, 884], [2434, 876]], "boundary": [[2019, 884], [2019, 895], [2433, 892], [2434, 876], [2431, 856], [2018, 867], [2019, 884]], "text": null, "base_dir": null, "type": "baselines", "imagename": null, "tags": {"type": "default"}, "split": null, "regions": ["61c58a57-b73c-4871-94cb-004f6cc9f137"]}, {"id": "a4916de6-b707-4d71-bc8b-322a51948c69", "baseline": [[2019, 909], [2435, 906]], "boundary": [[2019, 909], [2019, 922], [2435, 918], [2435, 906], [2432, 884], [2018, 891], [2019, 909]], "text": null, "base_dir": null, "type": "baselines", "imagename": null, "tags": {"type": "default"}, "split": null, "regions": ["61c58a57-b73c-4871-94cb-004f6cc9f137"]}, {"id": "321d3274-a4f4-4b61-ab34-4ec5314e7684", "baseline": [[2019, 937], [2421, 931]], "boundary": [[2019, 937], [2019, 948], [2353, 948], [2353, 947], [2420, 940], [2421, 931], [2417, 914], [2018, 919], [2019, 937]], "text": null, "base_dir": null, "type": "baselines", "imagename": null, "tags": {"type": "default"}, "split": null, "regions": ["61c58a57-b73c-4871-94cb-004f6cc9f137"]}, {"id": "76dd2a15-6e93-4028-8021-28a4647f9b9c", "baseline": [[2019, 965], [2422, 956]], "boundary": [[2019, 965], [2019, 978], [2422, 965], [2422, 956], [2419, 935], [2018, 945], [2019, 965]], "text": null, "base_dir": null, "type": "baselines", "imagename": null, "tags": {"type": "default"}, "split": null, "regions": ["61c58a57-b73c-4871-94cb-004f6cc9f137"]}, {"id": "6875bb4f-6a3e-4794-86a8-85eb93373c88", "baseline": [[2021, 988], [2437, 978]], "boundary": [[2021, 988], [2021, 999], [2436, 989], [2437, 978], [2434, 959], [2019, 972], [2021, 988]], "text": null, "base_dir": null, "type": "baselines", "imagename": null, "tags": {"type": "default"}, "split": null, "regions": ["61c58a57-b73c-4871-94cb-004f6cc9f137"]}, {"id": "cf0eafef-2c00-4f69-ba01-68dc22c373a2", "baseline": [[2022, 1014], [2429, 1004]], "boundary": [[2022, 1014], [2022, 1024], [2429, 1014], [2429, 1004], [2425, 987], [2021, 996], [2022, 1014]], "text": null, "base_dir": null, "type": "baselines", "imagename": null, "tags": {"type": "default"}, "split": null, "regions": ["61c58a57-b73c-4871-94cb-004f6cc9f137"]}, {"id": "0ac862e4-fa61-4cb5-bd8d-4f52adb84e87", "baseline": [[2019, 1038], [2424, 1030]], "boundary": [[2019, 1038], [2019, 1050], [2246, 1051], [2247, 1051], [2424, 1041], [2424, 1030], [2421, 1014], [2018, 1016], [2019, 1038]], "text": null, "base_dir": null, "type": "baselines", "imagename": null, "tags": {"type": "default"}, "split": null, "regions": ["61c58a57-b73c-4871-94cb-004f6cc9f137"]}, {"id": "2126a6f5-1ab2-47f1-8f0a-70c38a3dc8f7", "baseline": [[2019, 1069], [2426, 1060]], "boundary": [[2019, 1069], [2019, 1083], [2426, 1075], [2426, 1060], [2423, 1038], [2018, 1051], [2019, 1069]], "text": null, "base_dir": null, "type": "baselines", "imagename": null, "tags": {"type": "default"}, "split": null, "regions": ["61c58a57-b73c-4871-94cb-004f6cc9f137"]}, {"id": "21025908-11d8-44fe-a586-7f7b37e711b2", "baseline": [[2014, 1095], [2443, 1087]], "boundary": [[2014, 1095], [2014, 1108], [2259, 1099], [2442, 1100], [2443, 1087], [2440, 1069], [2013, 1073], [2014, 1095]], "text": null, "base_dir": null, "type": "baselines", "imagename": null, "tags": {"type": "default"}, "split": null, "regions": ["61c58a57-b73c-4871-94cb-004f6cc9f137"]}, {"id": "05e56073-e817-4d26-ace5-70fec6b8b36d", "baseline": [[2014, 1118], [2439, 1112]], "boundary": [[2014, 1118], [2014, 1128], [2097, 1133], [2098, 1133], [2439, 1122], [2439, 1112], [2436, 1095], [2190, 1093], [2189, 1093], [2013, 1101], [2014, 1118]], "text": null, "base_dir": null, "type": "baselines", "imagename": null, "tags": {"type": "default"}, "split": null, "regions": ["61c58a57-b73c-4871-94cb-004f6cc9f137"]}, {"id": "26c46706-eceb-4051-a6bc-4552775b2d41", "baseline": [[2023, 1142], [2454, 1136]], "boundary": [[2023, 1142], [2023, 1160], [2090, 1160], [2090, 1159], [2092, 1159], [2093, 1159], [2103, 1151], [2130, 1157], [2131, 1157], [2177, 1150], [2205, 1157], [2206, 1157], [2207, 1157], [2248, 1149], [2288, 1155], [2289, 1155], [2290, 1155], [2312, 1148], [2329, 1154], [2330, 1154], [2331, 1154], [2332, 1154], [2333, 1154], [2342, 1149], [2363, 1154], [2364, 1154], [2365, 1154], [2366, 1154], [2398, 1147], [2424, 1153], [2425, 1153], [2426, 1153], [2454, 1149], [2454, 1136], [2451, 1121], [2022, 1127], [2023, 1142]], "text": null, "base_dir": null, "type": "baselines", "imagename": null, "tags": {"type": "default"}, "split": null, "regions": ["61c58a57-b73c-4871-94cb-004f6cc9f137"]}, {"id": "338e1328-503e-40dd-acda-44801aece717", "baseline": [[2110, 1169], [2425, 1160]], "boundary": [[2110, 1169], [2110, 1184], [2154, 1178], [2179, 1182], [2180, 1182], [2424, 1171], [2425, 1160], [2423, 1143], [2398, 1138], [2396, 1138], [2395, 1138], [2380, 1143], [2312, 1139], [2311, 1139], [2310, 1139], [2309, 1139], [2300, 1146], [2281, 1140], [2280, 1140], [2279, 1140], [2225, 1148], [2109, 1146], [2110, 1169]], "text": null, "base_dir": null, "type": "baselines", "imagename": null, "tags": {"type": "default"}, "split": null, "regions": ["61c58a57-b73c-4871-94cb-004f6cc9f137"]}, {"id": "0b09be6b-eb67-4e9f-b343-45ade927ecf8", "baseline": [[2110, 1193], [2423, 1187]], "boundary": [[2110, 1193], [2110, 1210], [2370, 1199], [2407, 1203], [2409, 1203], [2410, 1203], [2423, 1197], [2423, 1187], [2421, 1171], [2266, 1168], [2264, 1168], [2109, 1177], [2110, 1193]], "text": null, "base_dir": null, "type": "baselines", "imagename": null, "tags": {"type": "default"}, "split": null, "regions": ["61c58a57-b73c-4871-94cb-004f6cc9f137"]}, {"id": "9bfc706b-b1ed-47ae-8465-54feccdef490", "baseline": [[2017, 1222], [2431, 1212]], "boundary": [[2017, 1222], [2017, 1232], [2430, 1223], [2431, 1212], [2427, 1193], [2059, 1205], [2016, 1201], [2017, 1222]], "text": null, "base_dir": null, "type": "baselines", "imagename": null, "tags": {"type": "default"}, "split": null, "regions": ["61c58a57-b73c-4871-94cb-004f6cc9f137"]}, {"id": "a1706e42-d67b-43d2-9d6b-2200ff4b5b5a", "baseline": [[2021, 1250], [2440, 1240]], "boundary": [[2021, 1250], [2021, 1265], [2439, 1255], [2440, 1240], [2436, 1223], [2019, 1226], [2021, 1250]], "text": null, "base_dir": null, "type": "baselines", "imagename": null, "tags": {"type": "default"}, "split": null, "regions": ["61c58a57-b73c-4871-94cb-004f6cc9f137"]}, {"id": "b31288b3-001d-4df5-9e0d-6b957abca2f4", "baseline": [[2021, 1275], [2423, 1266]], "boundary": [[2021, 1275], [2021, 1288], [2423, 1280], [2423, 1266], [2420, 1250], [2019, 1257], [2021, 1275]], "text": null, "base_dir": null, "type": "baselines", "imagename": null, "tags": {"type": "default"}, "split": null, "regions": ["61c58a57-b73c-4871-94cb-004f6cc9f137"]}, {"id": "ea1e3760-cf13-4718-9ecc-9172b350b68d", "baseline": [[2021, 1300], [2426, 1292]], "boundary": [[2021, 1300], [2021, 1313], [2389, 1303], [2425, 1307], [2426, 1292], [2423, 1274], [2019, 1280], [2021, 1300]], "text": null, "base_dir": null, "type": "baselines", "imagename": null, "tags": {"type": "default"}, "split": null, "regions": ["61c58a57-b73c-4871-94cb-004f6cc9f137"]}, {"id": "afe05ce0-2be3-488d-b1b7-2d7742b02ab3", "baseline": [[2019, 1325], [2421, 1315]], "boundary": [[2019, 1325], [2019, 1337], [2421, 1328], [2421, 1315], [2419, 1300], [2196, 1300], [2195, 1300], [2103, 1307], [2075, 1303], [2074, 1303], [2073, 1303], [2058, 1308], [2018, 1304], [2019, 1325]], "text": null, "base_dir": null, "type": "baselines", "imagename": null, "tags": {"type": "default"}, "split": null, "regions": ["61c58a57-b73c-4871-94cb-004f6cc9f137"]}, {"id": "b527ea90-48f8-4cb2-8472-dd6824899d10", "baseline": [[2018, 1352], [2424, 1345]], "boundary": [[2018, 1352], [2018, 1363], [2423, 1356], [2424, 1345], [2421, 1324], [2017, 1331], [2018, 1352]], "text": null, "base_dir": null, "type": "baselines", "imagename": null, "tags": {"type": "default"}, "split": null, "regions": ["61c58a57-b73c-4871-94cb-004f6cc9f137"]}, {"id": "ff75fae3-4c4f-43e5-8340-e49dd6534367", "baseline": [[2019, 1377], [2424, 1371]], "boundary": [[2019, 1377], [2019, 1386], [2424, 1379], [2424, 1371], [2421, 1354], [2018, 1359], [2019, 1377]], "text": null, "base_dir": null, "type": "baselines", "imagename": null, "tags": {"type": "default"}, "split": null, "regions": ["61c58a57-b73c-4871-94cb-004f6cc9f137"]}, {"id": "ba514bc2-95c2-447a-915a-b2e7883582fa", "baseline": [[2019, 1404], [2419, 1397]], "boundary": [[2019, 1404], [2019, 1414], [2417, 1407], [2419, 1397], [2415, 1380], [2018, 1386], [2019, 1404]], "text": null, "base_dir": null, "type": "baselines", "imagename": null, "tags": {"type": "default"}, "split": null, "regions": ["61c58a57-b73c-4871-94cb-004f6cc9f137"]}, {"id": "3d07a7cb-ec84-46e4-8932-a30b4701343b", "baseline": [[2018, 1431], [2434, 1420]], "boundary": [[2350, 1399], [2344, 1399], [2343, 1399], [2340, 1404], [2140, 1404], [2139, 1404], [2138, 1404], [2137, 1404], [2128, 1409], [2066, 1406], [2065, 1406], [2017, 1412], [2018, 1431], [2018, 1440], [2099, 1445], [2100, 1445], [2145, 1438], [2182, 1443], [2184, 1443], [2434, 1433], [2434, 1420], [2430, 1396], [2407, 1402], [2355, 1398], [2350, 1399]], "text": null, "base_dir": null, "type": "baselines", "imagename": null, "tags": {"type": "default"}, "split": null, "regions": ["61c58a57-b73c-4871-94cb-004f6cc9f137"]}, {"id": "e6a016f9-c26a-424c-8481-38f2cf3bf4a9", "baseline": [[2012, 1459], [2446, 1448]], "boundary": [[2443, 1439], [2434, 1425], [2180, 1437], [2011, 1436], [2012, 1459], [2012, 1472], [2445, 1464], [2446, 1448], [2443, 1425], [2442, 1425], [2443, 1439]], "text": null, "base_dir": null, "type": "baselines", "imagename": null, "tags": {"type": "default"}, "split": null, "regions": ["61c58a57-b73c-4871-94cb-004f6cc9f137"]}, {"id": "280cd52a-7005-4c15-a161-cc2a5936e11d", "baseline": [[2016, 1486], [2427, 1477]], "boundary": [[2016, 1486], [2016, 1496], [2323, 1495], [2427, 1486], [2427, 1477], [2424, 1456], [2015, 1463], [2016, 1486]], "text": null, "base_dir": null, "type": "baselines", "imagename": null, "tags": {"type": "default"}, "split": null, "regions": ["61c58a57-b73c-4871-94cb-004f6cc9f137"]}, {"id": "516fe197-13f6-40d6-b0d3-a94bf63cf8df", "baseline": [[1549, 1520], [2427, 1504]], "boundary": [[1549, 1520], [1549, 1533], [1570, 1541], [1572, 1541], [1573, 1541], [1574, 1541], [1589, 1535], [1758, 1539], [1759, 1539], [1760, 1539], [1794, 1529], [1840, 1538], [1841, 1538], [1842, 1538], [1866, 1532], [1924, 1536], [1925, 1536], [1926, 1536], [1960, 1526], [2044, 1533], [2045, 1533], [2089, 1526], [2104, 1532], [2105, 1532], [2106, 1532], [2107, 1532], [2126, 1527], [2249, 1530], [2250, 1530], [2251, 1530], [2282, 1520], [2323, 1527], [2324, 1527], [2325, 1527], [2327, 1527], [2339, 1518], [2384, 1518], [2426, 1526], [2427, 1504], [2425, 1486], [2390, 1480], [2389, 1480], [2305, 1488], [2115, 1486], [2114, 1486], [2113, 1486], [2100, 1491], [2074, 1486], [2073, 1486], [2072, 1486], [2070, 1486], [2063, 1492], [2015, 1487], [2014, 1487], [1960, 1488], [1958, 1488], [1957, 1488], [1950, 1495], [1921, 1490], [1920, 1490], [1893, 1496], [1847, 1491], [1845, 1491], [1844, 1491], [1832, 1498], [1700, 1499], [1687, 1494], [1686, 1494], [1685, 1494], [1684, 1494], [1682, 1494], [1674, 1500], [1548, 1500], [1549, 1520]], "text": null, "base_dir": null, "type": "baselines", "imagename": null, "tags": {"type": "default"}, "split": null, "regions": ["61c58a57-b73c-4871-94cb-004f6cc9f137"]}, {"id": "726e0700-64ea-4025-91a3-e3509a4a3f40", "baseline": [[1878, 1561], [1917, 1561]], "boundary": [[1878, 1561], [1878, 1579], [1917, 1574], [1917, 1561], [1916, 1537], [1878, 1542], [1878, 1561]], "text": null, "base_dir": null, "type": "baselines", "imagename": null, "tags": {"type": "default"}, "split": null, "regions": ["61c58a57-b73c-4871-94cb-004f6cc9f137"]}, {"id": "6bf569fa-14e0-45ea-a58a-eacfdc0ca127", "baseline": [[1474, 843], [1498, 843]], "boundary": [[1474, 843], [1475, 929], [1498, 923], [1498, 843], [1496, 817], [1474, 823], [1474, 843]], "text": null, "base_dir": null, "type": "baselines", "imagename": null, "tags": {"type": "default"}, "split": null, "regions": []}, {"id": "624298e6-2b22-42f6-a071-5aa265c88c46", "baseline": [[2646, 109], [2684, 109]], "boundary": [[2646, 107], [2646, 109], [2646, 127], [2684, 126], [2684, 109], [2684, 94], [2654, 94], [2646, 107]], "text": null, "base_dir": null, "type": "baselines", "imagename": null, "tags": {"type": "default"}, "split": null, "regions": ["fb2c88aa-6447-4d6d-bdd0-0fc6a01c0a3e"]}], "regions": {"text": [{"id": "2f180ab0-a8d5-4974-a6e0-518278a0a9e5", "boundary": [[507, 217], [863, 217], [868, 238], [823, 256], [452, 247], [456, 221], [507, 217]], "imagename": null, "tags": {"type": "text"}}, {"id": "e0625826-88ea-4e95-bcd6-30acc2df7de5", "boundary": [[460, 297], [837, 297], [872, 332], [885, 407], [868, 456], [881, 1537], [474, 1546], [456, 987], [460, 297]], "imagename": null, "tags": {"type": "text"}}, {"id": "bcd90dbe-70ed-4fa4-bf6f-a731dd55f689", "boundary": [[956, 212], [1351, 221], [1351, 340], [1369, 350], [1351, 469], [1364, 536], [1360, 1191], [1373, 1219], [1364, 1532], [953, 1532], [931, 243], [956, 212]], "imagename": null, "tags": {"type": "text"}}, {"id": "9d4bd9e4-7503-4cd6-9fd1-452a93a76665", "boundary": [[1488, 829], [1488, 832], [1485, 832], [1485, 829], [1488, 829]], "imagename": null, "tags": {"type": "text"}}, {"id": "20bd4fb5-20f4-448a-81d7-1e82b617fa9e", "boundary": [[1505, 571], [1505, 579], [1502, 579], [1502, 571], [1505, 571]], "imagename": null, "tags": {"type": "text"}}, {"id": "61c58a57-b73c-4871-94cb-004f6cc9f137", "boundary": [[2228, 208], [2441, 208], [2450, 221], [2450, 349], [2427, 415], [2441, 452], [2436, 623], [2450, 638], [2436, 1031], [2458, 1142], [2436, 1188], [2432, 1399], [2450, 1461], [2432, 1515], [2092, 1528], [2050, 1547], [2050, 1594], [1949, 1621], [1922, 1577], [1865, 1568], [1851, 1537], [1550, 1532], [1537, 931], [1511, 894], [1515, 860], [1533, 854], [1533, 815], [1511, 810], [1533, 801], [1533, 580], [1523, 561], [1498, 566], [1481, 535], [1498, 505], [1472, 517], [1463, 504], [1467, 487], [1502, 490], [1506, 416], [1528, 371], [1528, 221], [1944, 221], [1957, 814], [1940, 938], [1957, 1076], [1975, 1081], [1953, 1155], [1958, 1179], [1988, 1183], [1972, 1201], [2015, 1205], [2007, 1086], [1994, 1080], [2016, 991], [2012, 230], [2021, 212], [2228, 208]], "imagename": null, "tags": {"type": "text"}}, {"id": "fb2c88aa-6447-4d6d-bdd0-0fc6a01c0a3e", "boundary": [[2658, 88], [2680, 93], [2680, 118], [2646, 114], [2658, 88]], "imagename": null, "tags": {"type": "text"}}]}, "line_orders": []}